Workbook

Sheet Read_Me
A1: Microsoft License Cost Allocation Model
A3: Purpose
A4: Allocate total Microsoft license costs to internal cost centres (RS, AFS, Namibia, Mozambique)
A5: based on active licensed users, using per-license SKU allocation aligned with Microsoft invoicing.
A7: How To Use (Monthly)
A8: 1. Complete Invoice_Input: enter invoice total (incl VAT), VAT rate, exchange rate, billing period
A9: 2. Replace License_Raw data with the new month's Microsoft Admin Centre export
A10: 3. Update Employee_Master if there are new starters/leavers
A11: 4. Enter monthly invoice line-item amounts per SKU on SKU_Cost_Input (yellow cells)
A12: 5. CHECK: Verify the Reconciliation section on Division_Summary — variance must be R0.00
A13: 6. Review the Review_Queue for any unresolved user mappings
A14: 7. Send Division_Summary to Finance
... A51: Review_Queue → Unresolved/flagged users requiring attention

Sheet Invoice_Input
A1: Monthly Invoice Input
A2: Complete ALL yellow cells before entering SKU amounts. This is the control sheet for reconciliation.
A4: Billing Period | B4: March 2026 | C4: e.g. March 2026
A5: Invoice Number | B5: INV-0303 | C5: From Microsoft invoice
A6: Invoice Date | B6: 25/03/2026 | C6: Date on the invoice (DD/MM/YYYY)
A7: Snapshot Date | C7: Date the user list was exported from Admin Centre
A9: Invoice Total (incl VAT) ZAR | B9: 60184.38 | C9: Exact Rand total from the invoice including VAT
A10: VAT Rate % | B10: 0.15 | C10: South Africa standard = 15%
A11: Invoice Total (excl VAT) ZAR | B11: =IF(B10=0,0,B9/(1+B10)) | C11: Calculated: =incl / (1 + VAT rate)
A13: Exchange Rate (USD to ZAR) | B13: 0 | C13: Enter 0 if invoice is already in ZAR. Otherwise enter the rate used.
A14: Invoice Total (USD) | B14: 0 | C14: Enter 0 if invoice is in ZAR. Otherwise enter USD total from invoice.
A15: Converted Total (ZAR) | B15: =IF(B13=0,0,B14*B13) | C15: Calculated: USD × rate. If invoice is already ZAR, this is ignored.
A17: SKU Total (excl VAT) ZAR | B17: =SKU_Cost_Input!D17 | C17: Auto-calculated from SKU_Cost_Input — must match Invoice Total excl VAT
A18: Variance (must be R0.00) | B18: =B11-B17 | C18: =Invoice excl VAT − SKU total. RED if non-zero.
A19: Reconciliation Status | B19: =IF(ABS(B18)<0.01,"PASS","FAIL - SKU amounts do not match invoice") | C19: PASS or FAIL

Sheet Employee_Master
A1: Company Email | B1: Employee Name | C1: Employee Code | D1: Department | E1: Department Group | F1: Site | G1: Division | H1: Job Title | I1: Supervisor | J1: Cell Number | K1: Status
A2: a.ludick@wearcheckRS.com | B2: Adri Ludick | C2: WC492 | D2: ARC-NDT | E2: GP Consult | G2: RS | H2: Manager Mechanical | I2: Philip Schutte | J2: 0832816896 | K2: Submitted
A3: adriaanb@wearcheckrs.com | B3: Adriaan Pertus Johannes Bouwer | C3: WC383 | D3: ARC-RCM | E3: WearCheck | F3: KwaZulu Natal | G3: RS | H3: Thermal Manager | I3: Louis Peacock | J3: 0608498504 | K3: Submitted
A4: marshallr@wearcheckrs.com | B4: Ailwel Marshall Rasimphi | C4: WEC094 | D4: ARC-RCM | E4: GP Consult | F4: Valterra - Waterval | G4: RS | H4: Reliability Technician | I4: Riaan de Beer | J4: 0768219444 | K4: Submitted
A5: alex@wearcheckrs.com | B5: Alexander Outram | C5: WEC105 | D5: ARC-RCM | E5: GP Consult | F5: RBMR and PMR | G5: RS | H5: Reliability Technologist | I5: Micheal Pretorius | J5: 0662213616 / 0720164289 | K5: Submitted
A6: allan@wearcheckrs.com | B6: Allan Stuurman | C6: WEC123 | D6: ARC-RCM | E6: GP Consult | F6: Samancor - ECM Tweefontein | G6: RS | H6: Reliability Technologist - Site Suprevisor | I6: Peet Peacock | J6: 0799121301 | K6: Submitted
A7: andree@wearcheck.co.za | B7: André Erasmus | C7: WC511 | D7: ARC-TCA | E7: AFS | G7: AFS | H7: Machinery Inspector / Auditor | I7: Johan Stols | J7: 0833088571 | K7: Submitted
A8: andrew@wearcheckRS.com | B8: Andrew John Walker Robb | C8: WEC103 | D8: ARC-RCM | E8: GP Consult | F8: Remote Centre | G8: RS | H8: ARC Centre Manager | I8: Louis Peacock | J8: 0636504444 | K8: Submitted
A9: annahm@wearcheckrs.com | B9: Annah Seipone Modutwane | C9: WC484 | D9: ARC-RCM | E9: WearCheck | F9: Valterra - Mototolo | G9: RS | H9: Trainee Inspector B5 | I9: Londolani Managa | J9: 0833579812 | K9: Submitted
A10: annemie@wearcheckrs.com | B10: Annemie Willer | C10: WC319 | D10: ARC-RCM | E10: WearCheck | F10: Longmeadow H/O | G10: RS | H10: Divisional Manager | I10: Philip Schutte | J10: 0716096197 | K10: Incomplete
A11: antonio.ehrke@wearcheckrs.com | B11: Antonio Ehrke | C11: WC503 | D11: ARC-RCA | E11: AFS | G11: AFS | H11: RCA Inspector | I11: Roger Henwood | J11: 0834695668 | K11: Submitted
A12: armindo@wearcheckrs.com | B12: Armindo Muchacho | C12: Unknown | D12: ARC-RCM | E12: WearCheck | F12: Mozambique | G12: Mozambique | H12: Site Supervisor | I12: Riaan du Plooy | J12: 258848349643 | K12: Submitted
A13: Arnold@WearCheckRS.com | B13: Arnoldus Johannes van Zyl | C13: WC526 | D13: ARC-TCA | E13: AFS | G13: AFS | H13: Electrical Inspector | I13: Johan Stols | J13: 067412 1369 | K13: Submitted
A14: aubrey@wearcheckRS.com | B14: Aubrey Tshabalala | C14: WEC114 | D14: ARC-RCM | E14: GP Consult | F14: Valterra - Mototolo | G14: RS | H14: Reliability Technologist | I14: Annah Modutwane | J14: 0824871527 | K14: Submitted
A15: N/A | B15: Benedito Timana | C15: Unknown | D15: ARC-RCM | E15: WearCheck | F15: Mozambique | G15: Mozambique | H15: Oil Sampler / Data collector | I15: Riaan du Plooy | J15: 258 879321970 | K15: Submitted
A16: Bianka@WearCheckRS.com | B16: Bianka de Beer | C16: WEC142 | D16: ARC-RCM | E16: GP Consult | F16: Longmeadow H/O | G16: RS | H16: Administrator | I16: Megan Salzwedel | J16: 0740317981 | K16: Submitted
A17: chicco@wearcheckrs.com | B17: Chicco Fransisco Tivane | C17: WC380 | D17: ARC-RCM | E17: WearCheck | F17: Steelpoort | G17: RS | H17: Reliability Technologist | I17: Londolani Managa | J17: 0818190051 | K17: Submitted
A18: chrism@wearcheckrs.com | B18: Chris Mostert | C18: WEC100 | D18: ARC-RCM | E18: GP Consult | F18: Springs | G18: RS | H18: Reliability Analyst | I18: Eddie Pieterse Snr | J18: 0636922876 | K18: Submitted
A19: chrstene@wearcheckrs.com | B19: Christene Smal | C19: WC285 | D19: ARC-RCM | E19: WearCheck | F19: Longmeadow H/O | G19: RS | H19: RS Administrator | I19: Megan Salzwedel | J19: 0720591125 | K19: Submitted
A20: cj@wearcheckrs.com | B20: CJ Woller | C20: WEC120 | D20: ARC-RCM | E20: GP Consult | F20: RBMR and PMR | G20: RS | H20: Reliability Technician | I20: Michael Preotrius | J20: 0835965562 | K20: Submitted
A21: colleen.pyper@WearCheckRS.com | B21: Colleen Pyper | C21: WC486 | D21: AFS | E21: AFS | G21: AFS | H21: Admin and Finance Assistant | I21: Adri Ludick | J21: 0662916811 | K21: Submitted
A22: greeffm@wearcheck.co.za | B22: Daniel Greef Meintjies | C22: WC528 | D22: ARC-NDT | E22: AFS | G22: AFS | H22: Inspector (Lifting and NDT) | I22: Adri Ludick | J22: 0674121318 | K22: Submitted
A23: daniel@wearcheckrs.com | B23: Tshegofatsho Daniel Molapo | C23: WC402 | D23: ARC-RCM | E23: GP Consult | F23: Valterra - Mototolo | G23: RS | H23: Reliability Technologist | I23: Annah Modutwane | J23: 0828023079 | K23: Submitted
A24: David@wearcheckrs.com | B24: David Viljoen | C24: WEC081 | D24: ARC-RCM | E24: GP Consult | F24: Roamer | G24: RS | H24: Precision Maintenance Technologist | I24: Peet Peacock | J24: 0810106409 | K24: Submitted
A25: davidl@wearcheckrs.com | B25: David Lipague | C25: Unknown | D25: ARC-RCM | E25: WearCheck | F25: Mozambique | G25: Mozambique | H25: Reliability Technician | I25: Riaan du Plooy | J25: 258847817888 | K25: Submitted
A26: deon@wearcheckrs.com | B26: Deon Gaarkeuken | C26: WC358 | D26: ARC-RCM | E26: WearCheck | F26: Roamer | G26: RS | H26: ARC Reliability Specialist | I26: Andrew Robb | J26: 0712524040 | K26: Submitted
A27: desmond@wearcheckrs.com | B27: Desmond Ngomane | C27: WEC086 | D27: ARC-RCM | E27: GP Consult | F27: Valterra - Mototolo | G27: RS | H27: Reliability Technologist | I27: Annah Modutwane | J27: 0796083125 | K27: Submitted
A28: dian@wearcheckrs.com | B28: Dian Leff | C28: WCN008 | D28: ARC-RCM | E28: WearCheck | F28: Namibia | G28: Namibia | H28: Reliability Technician | I28: Rohan Willer | J28: 0817614612 | K28: Submitted
A29: Douglas@WearcheckRS.com | B29: Douglas Prout-Jones | C29: WEC119 | D29: ARC-RCM | E29: GP Consult | F29: Valterra - Waterval | G29: RS | H29: Reliability Technician | I29: Riaan de Beer | J29: 0832855788 / 0823125521 | K29: Submitted
A30: eben@wearcheckrs.com | B30: Eben Prinsloo | C30: WEC122 | D30: ARC-RCM | E30: GP Consult | F30: Roamer | G30: RS | H30: Reliability Technologist | I30: Edward Pieterse Jnr | J30: 0824146986 | K30: Submitted
A31: edwardfp@wearcheckrs.com | B31: Edward Frederick IV Pieterse | C31: WC274 | D31: ARC-RCM | E31: WearCheck | F31: Longmeadow H/O | G31: RS | H31: Operations Manager | I31: Annemie Willer | J31: 0837930923 | K31: Submitted
A32: edwin@wearcheckrs.com | B32: Edwin Ashley Gibbons | C32: WEC138 | D32: ARC-TCA | E32: AFS | G32: AFS | H32: ARC TC Machinery Inspector | I32: Johan Stols | J32: 0725336075 | K32: Submitted
A33: ethel.mienie@WearCheckRS.com | B33: Ethel Mienie | C33: WC488 | D33: AFS | E33: AFS | G33: AFS | H33: Administration Assistant | I33: Adri Ludick | J33: 0660215452 | K33: Submitted
A34: epieterse@wearcheckrs.com | B34: Edward Pieterse | C34: WC271 | D34: ARC-RCM | E34: WearCheck | F34: Springs | G34: RS | H34: ARC Reliability Specialist | I34: Peet Peacock | J34: 0829057637 | K34: Submitted
A35: eugene@wearcheckrs.com | B35: Eugene Scheepers | C35: WEC090 | D35: ARC-RCM | E35: GP Consult | F35: Neopak - Rosslyn | G35: RS | H35: Reliability Technician | I35: Francois Pretorius | J35: 0790542385 | K35: Submitted
A36: evertv@wearcheck.co.za | B36: Evert Viljoen | C36: WC497 | D36: ARC-NDT | E36: AFS | G36: AFS | H36: Senior Machinery Inspector | I36: Adri Ludick | J36: 0795284219 | K36: Submitted
A37: Franciosp@wearcheckRS.com | B37: Michael Francios Pretorius | C37: WEC080 | D37: ARC-RCM | E37: GP Consult | F37: Neopak - Rosslyn | G37: RS | H37: Reliability Analyst | I37: Peet Peacock | J37: 0832773047 | K37: Submitted
A38: francoisve@wearcheckrs.com | B38: Francois Jacobus van Eeden | C38: WC287 | D38: ARC-RCM | E38: WearCheck | F38: Remote Centre | G38: RS | H38: Condition Monitoring Specialist | I38: Andrew Robb | J38: 0828023072 | K38: Submitted
A39: francoisp@wearcheckrs.com | B39: Jozua Francois Joubert Pienaar | C39: WEC111 | D39: ARC-RCM | E39: GP Consult | F39: KwaZulu Natal - Hillside | G39: RS | H39: Reliability Analyst | I39: Peet Peacock | J39: 0785618579 | K39: Submitted
A40: Freddy-Ben@wearcheckRS.com | B40: Freddy-Ben Gariseb | C40: WCN004 | D40: ARC-RCM | E40: WearCheck | F40: Namibia | G40: Namibia | H40: Reliability Technician | I40: Rohan Willer | J40: 264813707010 | K40: Submitted
A41: gabriel@wearcheckrs.com | B41: Gabriel Shikongo Nuunyango | C41: WCN007 | D41: ARC-RCM | E41: WearCheck | F41: Namibia | G41: Namibia | H41: Reliability Technician | I41: Rohan Willer | J41: +264 81 364 5524 | K41: Submitted
A42: godfreyb@wearcheck.co.za | B42: Godfrey Boikhutso | C42: WC510 | D42: ARC-TCA | E42: AFS | G42: AFS | H42: Inspector | I42: Johan Stols | J42: 0718609242 | K42: Submitted
A43: freddieh@wearcheck.co.za | B43: Gordon John Frederick Hoy | C43: WEC093 | D43: AFS | E43: GP Consult | G43: AFS | H43: Mechanical Technician | I43: Adri Ludick | J43: 0825967126 | K43: Submitted
A44: gustav@wearcheckrs.com | B44: Gustav Lourens | C44: WC270 | D44: ARC-RCM | E44: WearCheck | F44: Springs | G44: RS | H44: Reliability Technologist | I44: Eddie Pieterse Snr | J44: 0829057631 | K44: Submitted
A45: hannest@wearcheckrs.com | B45: Hannest Koegelenberg | C45: WEC047 | D45: ARC-RCM | E45: GP Consult | F45: Springs | G45: RS | H45: Reliability Technologist | I45: Eddie Pieterse Snr | J45: 0823832542 | K45: Submitted
A46: heinc@wearcheckrs.com | B46: Hein Coetzer | C46: WEC129 | D46: ARC-RCM | E46: GP Consult | F46: Samancor - TAS | G46: RS | H46: Precision Maintenance Technologist | I46: Peet Peacock | J46: 0828887419 | K46: Submitted
A47: heinrich@wearcheckrs.com | B47: Fritz Kusel | C47: WEC134 | D47: ARC-RCA | E47: GP Consult | G47: RS | H47: RCA Technician | I47: Roger Henwood | J47: 0796959474 | K47: Submitted
A48: henry@wearcheckrs.com | B48: Henry Mherekumombe | C48: WEC098 | D48: ARC-NDT | E48: GP Consult | G48: RS | H48: Level 2 Inspector | I48: Adri Ludick | J48: 0664844117 | K48: Submitted
A49: isac@wearcheckrs.com | B49: Isac Zacarias | C49: Unknown | D49: ARC-RCM | E49: WearCheck | F49: Mozambique | G49: Mozambique | H49: Reliability Technician | I49: Riaan du Plooy | J49: 258849439848 | K49: Submitted
A50: jacov@wearcheck.co.za | B50: Jacobus Frederick Venter | C50: WC493 | D50: ARC-NDT | E50: AFS | G50: AFS | H50: Senior Machinery Inspector | I50: Adri Ludick | J50: 0834009604 | K50: Submitted
A51: jaco@wearcheckrs.com | B51: Jacobus Johannes Willer | C51: WC352 | D51: ARC-RCM | E51: WearCheck | F51: Longmeadow H/O | G51: RS | H51: Foreign Operations Business Unit Manager | I51: Philip Schutte | J51: 0762681425 | K51: Submitted
A52: jacodb@wearcheckrs.com | B52: Theunis Gerhardus Jacobus de Beer | C52: WEC097 | D52: ARC-RCM | E52: GP Consult | F52: Roamer | G52: RS | H52: Reliability Technologist | I52: Eben Prinsloo | J52: 0715236313 | K52: Submitted
A53: james@WearCheckRS.com | B53: James Papayito Tshabalala | C53: WC236 | D53: ARC-RCM | E53: WearCheck | F53: Valterra - Mototolo | G53: RS | H53: Reliability Technologist | I53: Annah Modutwane | J53: 0662479987 | K53: Submitted
A54: janb@wearcheck.co.za | B54: Jan Booysens | C54: WC496 | D54: ARC-NDT | E54: AFS | G54: AFS | H54: Senior Machinery Inspector | I54: Adri Ludick | J54: 0718665249 | K54: Submitted
A55: janniel@wearcheck.co.za | B55: Johann Louw | C55: WC494 | D55: ARC-NDT | E55: AFS | G55: AFS | H55: Inspector | I55: Adri Ludick | J55: 0718607663 | K55: Submitted
A56: jj@wearcheckrs.com | B56: Jean Jacques de Beer | C56: WEC137 | D56: ARC-RCM | E56: GP Consult | F56: Remote Centre | G56: RS | H56: Technical Advisor | I56: Andrew Robb | J56: 0676700396 | K56: Submitted
A57: JohanB@wearcheckRS.com | B57: Johan Bekker | C57: WC645 | D57: ARC-TCA | E57: AFS | G57: AFS | H57: ARC TC Inspector | I57: Johan Stols | J57: 0675951633 | K57: Submitted
A58: johanr@wearcheckrs.com | B58: Johan Rossouw | C58: WC491 | D58: ARC-TCA | E58: AFS | G58: AFS | H58: Senior Inspector | I58: Johan Stols | J58: 0829274240 | K58: Submitted
A59: Johans@wearcheckrs.com | B59: Johannes Gideon Francios Stols | C59: WC508 | D59: ARC-TCA | E59: AFS | G59: AFS | H59: ARC TC Manager | I59: Philip Schutte | J59: 0832943748 | K59: Submitted
A60: johandre@wearcheckrs.com | B60: Johannes Andréas Oosthuizen | C60: WEC089 | D60: ARC-RCM | E60: GP Consult | F60: Samancor - Mooinooi | G60: RS | H60: Reliability Technician | J60: 0834373969 | K60: Submitted
A61: josephk@wearcheck.co.za | B61: Joseph Benjamin Kies | C61: WC531 | D61: ARC-TCA | E61: AFS | G61: AFS | H61: Machinery Inspector | I61: Johan Stols | J61: 0674121368 | K61: Submitted
A62: jeanj@wearcheck.co.za | B62: Jean-Pierre Jordaan | C62: WC527 | D62: ARC-NDT | E62: AFS | G62: AFS | H62: Inspector (Lifting and NDT) | I62: Adri Ludick | J62: 0674121382 | K62: Submitted
A63: kevin@wearcheckrs.com | B63: Kevin Henwood | C63: WEC135 | D63: ARC-RCA | E63: GP Consult | G63: RS | H63: RCA Technician | I63: Roger Henwood | J63: 0829072077 | K63: Submitted
A64: khotso@wearcheckrs.com | B64: Khotso Thabo Mosala | C64: WC482 | D64: ARC-TCA | E64: AFS | G64: AFS | H64: Inspector | I64: Johan Stols | J64: 0823321905 | K64: Submitted
A65: Leon@wearcheckrs.com | B65: Leon Coetzee | C65: WC455 | D65: ARC-RCM | E65: WearCheck | F65: Steelpoort | G65: RS | H65: Reliability Technologist | I65: Londolani Managa | J65: 0832881463 | K65: Submitted
A66: Lesego@WearCheckRS.com | B66: Lesego Khuthwane | C66: WEC126 | D66: ARC-RCM | E66: GP Consult | F66: Longmeadow H/O | G66: RS | H66: Remote Centre Administrator | I66: Andrew Robb | J66: 0849892260 | K66: Submitted
A67: lorrainem@wearcheck.co.za | B67: Lorraine Lerato Mokgethi | C67: WC495 | D67: ARC-NDT | E67: AFS | G67: AFS | H67: Technician | I67: Adri Ludick | J67: 786 672 158 | K67: Submitted
A68: londolanim@wearcheckrs.com | B68: Londolani Managa | C68: WC648 | D68: ARC-RCM | E68: WearCheck | F68: Samancor - MFC | G68: RS | H68: Precision Maintenance Technologist | I68: Peet Peacock | J68: 0711682839 | K68: Submitted
A69: lopim@wearcheck.co.za | B69: Bernard Lopi Molangoane | C69: WC269 | D69: ARC-RCM | E69: WearCheck | F69: Valterra - Mototolo | G69: RS | H69: Sampler | I69: Annah Modutwane | J69: 0636888886 | K69: Submitted
A70: louis@wearcheckrs.com | B70: Louis Robert Peacock | C70: WC277 | D70: ARC-RCM | E70: WearCheck | F70: Longmeadow H/O | G70: RS | H70: Technical & Training Manager | I70: Annemie Willer | K70: Incomplete
A71: lubby@wearcheckrs.com | B71: Labby Jeffrey Lubis | C71: WEC118 | D71: ARC-RCM | E71: GP Consult | F71: Samancor - Doornbosch | G71: RS | H71: Reliability Technologist - Site Suprevisor | I71: Peet Peacock | J71: 0796915943 | K71: Submitted
A72: lucas@wearcheckrs.com | B72: Lucas Johannes Bartel Luus | C72: WEC068 | D72: ARC-RCM | E72: GP Consult | F72: Kathu | G72: RS | H72: Reliability Technician | I72: Andrew Robb | J72: 0763455962 | K72: Submitted
A73: mande@wearcheckrs.com | B73: Mandé Coetzee | C73: WEC116 | D73: ARC-RCM | E73: GP Consult | F73: Longmeadow H/O | G73: RS | H73: RS Administrator | I73: Shivon Alberts | J73: 079 128 9133 | K73: Submitted
A74: marcel@wearcheckrs.com | B74: Marcel Schoeman | C74: WEC102 | D74: ARC-RCM | E74: GP Consult | F74: Roamer | G74: RS | H74: Sales Manager | I74: Annemie Willer | J74: 0767946353 | K74: Submitted
A75: mariette@wearcheckrs.com | B75: Mariette du Rand | C75: WEC109 | D75: ARC-RCM | E75: GP Consult | F75: Longmeadow H/O | G75: RS | H75: RS Administrator | I75: Megan Salzwedel | J75: 0837835814 | K75: Submitted
A76: martiens@wearcheckrs.com | B76: Marthinus Jacobus van Aarde | C76: WEC106 | D76: ARC-RCM | E76: GP Consult | F76: Eskom - Matimba | G76: RS | H76: Reliability Technician | I76: Tsietsi Monnanyne | J76: 0834550909 | K76: Submitted
A77: mikes@weacheckrs.com | B77: Mike Mbongeni Shongwe | C77: WC483 | D77: ARC-NDT | E77: AFS | G77: AFS | H77: Senior Inspector | I77: Adri Ludick | J77: 0718507077 | K77: Submitted
A78: megan@wearcheckrs.com | B78: Megan Salzwedel | C78: WEC104 | D78: ARC-RCM | E78: GP Consult | F78: Longmeadow H/O | G78: RS | H78: Administration Manager | I78: Edward Pieterse Jnr | J78: 0720591125 | K78: Submitted
A79: mervyng@wearcheck.co.za | B79: Mervyn Thomas Gibbons | C79: WC536 | D79: ARC-TCA | E79: AFS | G79: AFS | H79: ARC TC Machinery Inspector | I79: Johan Stols | J79: 0674193633 | K79: Submitted
A80: meshack@wearcheckrs.com | B80: Meshack Welcome Nxumalo | C80: WEC088 | D80: ARC-RCM | E80: GP Consult | F80: KwaZulu Natal | G80: RS | H80: Reliability Technologist | I80: Francois Pienaar | J80: 0638165404 | K80: Submitted
A81: micheal@wearcheckrs.com | B81: Micheal Francios Pretorius | C81: WEC076 | D81: ARC-RCM | E81: GP Consult | F81: RBMR and PMR | G81: RS | H81: Reliability Analyst - Site Supervisor | I81: Peet Peacock | J81: 0828864900 | K81: Submitted
A82: michealm@wearcheckrs.com | B82: Seporo Micheal Masemola | C82: WC291 | D82: ARC-RCM | E82: WearCheck | F82: Valterra - Mototolo | G82: RS | H82: Reliability Technologist | I82: Annah Modutwane | J82: 0820828925 | K82: Submitted
A83: betty@wearcheckrs.com | B83: Mmatapa Betty Monyepao | C83: WC465 | D83: ARC-RCM | E83: WearCheck | F83: Valterra - Mototolo | G83: RS | H83: Reliability Technician | I83: Annah Modutwane | J83: 0768125164 | K83: Submitted
A84: mornea@wearcheckrs.com | B84: Mórne Alberts | C84: WC361 | D84: ARC-RCM | E84: WearCheck | F84: Remote Centre | G84: RS | H84: ARC Reliability Specialist | I84: Andrew Robb | J84: 0810132168 | K84: Submitted
A85: nadhira@wearcheckrs.com | B85: Nadhira Bux | C85: WEC113 | D85: ARC-RCM | E85: GP Consult | F85: Longmeadow H/O | G85: RS | H85: Integration Co-Ordinator | I85: Louis Peacock | J85: 0625831366 | K85: Submitted
A86: nico.duplessis@wearcheckrs.com | B86: Nicolaas du Plessis | C86: WC506 | D86: ARC-RCA | E86: AFS | G86: AFS | H86: RCA Inspector | I86: Roger Henwood | J86: 0718937378 | K86: Submitted
A87: Muhamad@wearcheckRS.com | B87: Muhamad Hanif | C87: Unknown | D87: ARC-RCM | E87: WearCheck | F87: Mozambique | G87: Mozambique | H87: Reliability Technician | I87: Riaan du Plooy | J87: 258878054903 | K87: Submitted
A88: lloyd@wearcheckrs.com | B88: Lloyd Ngobeni | C88: WEC099 | D88: ARC-NDT | E88: GP Consult | F88: Valterra - Waterval | G88: RS | H88: Precision Maintenance Technologist | I88: Riaan de Beer | J88: 0664844084 | K88: Submitted
A89: nomvulam@wearcheckrs.com | B89: Nomvula Mkhize | C89: WC651 | D89: ARC-RCM | E89: WearCheck | F89: Samancor - MFC | G89: RS | H89: Precision Maintenance Technologist | I89: Peet Peacock | J89: 0747023211 | K89: Submitted
A90: Landus@wearcheckrs.com | B90: Norman Landus Walters | C90: WC509 | D90: ARC-TCA | E90: AFS | G90: AFS | H90: Machinery Inspector | I90: Johan Stols | J90: 076 385 2151 | K90: Submitted
A91: passwell@wearcheckrs.com | B91: Putaneng Paswell Mashoeu | C91: WC348 | D91: ARC-RCM | E91: WearCheck | F91: Valterra - Mototolo | G91: RS | H91: Sampler | I91: Annah Modutwane | J91: 06364888867 | K91: Submitted
A92: patrick@wearcheckrs.com | B92: Patrick Nel | C92: WC498 | D92: ARC-NDT | E92: AFS | G92: AFS | H92: Machinery Inspector | I92: Adri Ludick | J92: 0723633245 | K92: Submitted
A93: Peet@wearcheckrs.com | B93: Petrus Johannes Peacock | C93: WC520 | D93: ARC-RCM | E93: WearCheck | G93: RS | H93: Service Manager | I93: Annemie Willer | J93: 0716700710 | K93: Submitted
A94: percy@wearcheckrs.com | B94: Percy Hall | C94: WEC115 | D94: ARC-RCM | E94: GP Consult | F94: Seriti - Khutala | G94: RS | H94: Reliability Technologist | I94: Londolani Managa | J94: 0826828862 / 0827307344 | K94: Submitted
A95: permission@wearcheckrs.com | B95: Katishi Permission Malele | C95: WC393 | D95: ARC-RCM | E95: WearCheck | F95: Valterra - Mototolo | G95: RS | H95: Sampler | I95: Annah Modutwane | J95: 606314865 | K95: Submitted
A96: N/A | B96: Peter Ivo Mateus Mahlangu | D96: ARC-RCM | E96: WearCheck | F96: Mozambique | G96: Mozambique | H96: Senior Technician | I96: Riaan du Plooy | J96: 258842628215 | K96: Submitted
A97: philip@wearcheckrs.com | B97: Philippus Jacobus Wilhelmus (Philip) Schutte | C97: WC253 | D97: ARC-RCM | E97: WearCheck | F97: Longmeadow H/O | G97: RS | H97: General Manager | I97: N/A | J97: 0769829774 | K97: Incomplete
A98: Placido@wearcheckrs.com | B98: Placido Maculuve | C98: Unknown | D98: ARC-RCM | E98: WearCheck | F98: Mozambique | G98: Mozambique | H98: Senior Technician | I98: Riaan du Plooy | J98: 258845070300 | K98: Submitted
A99: reinierk@wearcheckrs.com | B99: Reinier Kalp | C99: WC382 | D99: ARC-RCM | E99: WearCheck | F99: Remote Centre | G99: RS | H99: Remote Center Analyst | I99: Andrew Robb | J99: 0810132176 | K99: Submitted
A100: Riaandp@wearcheckRS.com | B100: Adriaan Johannes du Plooy | C100: WC591 | D100: ARC-RCM | E100: WearCheck | F100: Mozambique | G100: Mozambique | H100: Country Manager | I100: Jaco Willer | J100: 0835965562 | K100: Submitted
...

Sheet License_Raw
A1: Display Name | B1: User Principal Name | C1: Licenses
A2: Admin | B2: admin@WearCheckRS.com | C2: Microsoft Defender for Office 365 (Plan 2)+Microsoft Fabric (Free)+Microsoft 365 E3
A3: Adri Ludick | B3: A.Ludick@WearCheckRS.com | C3: Microsoft 365 Business Premium+Microsoft Copilot Studio Viral Trial+Microsoft Defender for Office 365 (Plan 2)+Microsoft Power Automate Free
A4: Adri Ludick Old | B4: Adri.ludick@WearCheckRS.com | C4: Microsoft Defender for Office 365 (Plan 2)+Microsoft Power Automate Free+Microsoft 365 Business Standard
A5: Adriaan Bouwer | B5: adriaanb@WearCheckRS.com | C5: Microsoft Defender for Office 365 (Plan 2)+Microsoft Power Automate Free+Microsoft 365 Business Standard+Microsoft Fabric (Free)
A6: AFS Application | B6: afs_app@WearCheckRS.com | C6: Microsoft Power Automate Free+Exchange Online (Plan 1)
A7: Alex Outram | B7: Alex@WearCheckRS.com | C7: Microsoft Defender for Office 365 (Plan 2)+Microsoft Power Automate Free+Microsoft Fabric (Free)+Microsoft 365 Business Standard
A8: Allan Stuurman | B8: Allan@WearCheckRS.com | C8: Microsoft Defender for Office 365 (Plan 2)+Microsoft 365 Business Standard
A9: Andrew Robb | B9: Andrew@wearcheckrs.com | C9: Microsoft 365 Business Premium+Microsoft Defender for Office 365 (Plan 2)+Microsoft Fabric (Free)
A10: Annah Modutwane | B10: annahm@WearCheckRS.com | C10: Microsoft Defender for Office 365 (Plan 2)+Microsoft Power Automate Free+Microsoft Fabric (Free)+Microsoft 365 Business Standard
A11: Annemie Willer | B11: annemie@WearCheckRS.com | C11: Microsoft Defender for Office 365 (Plan 2)+Power BI Premium Per User+Microsoft Copilot Studio Viral Trial+Microsoft Power Apps Plan 2 Trial+Microsoft 365 E3+Microsoft Fabric (Free)+Microsoft Power Automate Free
A12: Antonio Ehrke | B12: Antonio.Ehrke@WearCheckRS.com | C12: Microsoft Defender for Office 365 (Plan 2)+Microsoft 365 Business Standard
... A148: Wihan Willer | B148: Wihan@WearCheckRS.com | C148: Microsoft Defender for Office 365 (Plan 2)+Microsoft 365 Business Standard

Sheet User_Match
A1: Licensed Display Name | B1: Licensed Email | C1: Matched Employee Name | D1: Candidate Employee Email | E1: Employee Number | F1: Division | G1: Match Status | H1: Confidence | I1: Review Required | J1: User Status | K1: Mapping Note | L1: License SKU Count | M1: All Licenses Raw | N1: Duplicate Flag
A2: Admin | B2: admin@WearCheckRS.com | F2: RS | G2: Mapped by rule | H2: High | I2: No | J2: Active | K2: Generic/shared/service account defaulted to RS per instruction | L2: 3 | M2: Microsoft Defender for Office 365 (Plan 2)+Microsoft Fabric (Free)+Microsoft 365 E3
A3: Adri Ludick | B3: A.Ludick@WearCheckRS.com | C3: Adri Ludick | D3: a.ludick@wearcheckRS.com | E3: WC492 | F3: RS | G3: Matched | H3: High | I3: No | J3: Active | K3: Exact company email match | L3: 4 | M3: Microsoft 365 Business Premium+Microsoft Copilot Studio Viral Trial+Microsoft Defender for Office 365 (Plan 2)+Microsoft Power Automate Free
A4: Adri Ludick Old | B4: Adri.ludick@WearCheckRS.com | F4: RS | G4: Ex-Employee | H4: High | I4: No | J4: Ex-Employee | K4: Old account — new email A.Ludick@WearCheckRS.com is active. FLAG: Remove this licence. | L4: 3 | M4: Microsoft Defender for Office 365 (Plan 2)+Microsoft Power Automate Free+Microsoft 365 Business Standard
A5: Adriaan Bouwer | B5: adriaanb@WearCheckRS.com | C5: Adriaan Pertus Johannes Bouwer | D5: adriaanb@wearcheckrs.com | E5: WC383 | F5: RS | G5: Matched | H5: High | I5: No | J5: Active | K5: Exact company email match | L5: 4 | M5: Microsoft Defender for Office 365 (Plan 2)+Microsoft Power Automate Free+Microsoft 365 Business Standard+Microsoft Fabric (Free)
A6: AFS Application | B6: afs_app@WearCheckRS.com | F6: AFS | G6: Mapped by rule | H6: High | I6: No | J6: Active | K6: Generic/shared/service account defaulted to RS per instruction | L6: 2 | M6: Microsoft Power Automate Free+Exchange Online (Plan 1)
A7: Alex Outram | B7: Alex@WearCheckRS.com | C7: Alexander Outram | D7: alex@wearcheckrs.com | E7: WEC105 | F7: RS | G7: Matched | H7: High | I7: No | J7: Active | K7: Exact company email match | L7: 4 | M7: Microsoft Defender for Office 365 (Plan 2)+Microsoft Power Automate Free+Microsoft Fabric (Free)+Microsoft 365 Business Standard
A8: Allan Stuurman | B8: Allan@WearCheckRS.com | C8: Allan Stuurman | D8: allan@wearcheckrs.com | E8: WEC123 | F8: RS | G8: Matched | H8: High | I8: No | J8: Active | K8: Exact company email match | L8: 2 | M8: Microsoft Defender for Office 365 (Plan 2)+Microsoft 365 Business Standard
A9: Andrew Robb | B9: Andrew@wearcheckrs.com | C9: Andrew John Walker Robb | D9: andrew@wearcheckRS.com | E9: WEC103 | F9: RS | G9: Matched | H9: High | I9: No | J9: Active | K9: Exact company email match | L9: 3 | M9: Microsoft 365 Business Premium+Microsoft Defender for Office 365 (Plan 2)+Microsoft Fabric (Free)
A10: Annah Modutwane | B10: annahm@WearCheckRS.com | C10: Annah Seipone Modutwane | D10: annahm@wearcheckrs.com | E10: WC484 | F10: RS | G10: Matched | H10: High | I10: No | J10: Active | K10: Exact company email match | L10: 4 | M10: Microsoft Defender for Office 365 (Plan 2)+Microsoft Power Automate Free+Microsoft Fabric (Free)+Microsoft 365 Business Standard
A11: Annemie Willer | B11: annemie@WearCheckRS.com | C11: Annemie Willer | D11: annemie@wearcheckrs.com | E11: WC319 | F11: RS | G11: Matched | H11: High | I11: No | J11: Active | K11: Exact company email match | L11: 7 | M11: Microsoft Defender for Office 365 (Plan 2)+Power BI Premium Per User+Microsoft Copilot Studio Viral Trial+Microsoft Power Apps Plan 2 Trial+Microsoft 365 E3+Microsoft Fabric (Free)+Microsoft Power Automate Free
A12: Antonio Ehrke | B12: Antonio.Ehrke@WearCheckRS.com | C12: Antonio Ehrke | D12: antonio.ehrke@wearcheckrs.com | E12: WC503 | F12: AFS | G12: Matched | H12: High | I12: No | J12: Active | K12: Exact company email match | L12: 2 | M12: Microsoft Defender for Office 365 (Plan 2)+Microsoft 365 Business Standard
A13: Armindo Mucacho | B13: Armindo@WearCheckRS.com | C13: Armindo Muchacho | D13: armindo@wearcheckrs.com | E13: Unknown | F13: Mozambique | G13: Matched | H13: High | I13: No | J13: Active | K13: Exact company email match | L13: 3 | M13: Microsoft Defender for Office 365 (Plan 2)+Microsoft Fabric (Free)+Microsoft 365 Business Standard
A14: Arnold van Zyl | B14: Arnold@WearCheckRS.com | C14: Arnoldus Johannes van Zyl | D14: Arnold@WearCheckRS.com | E14: WC526 | F14: AFS | G14: Matched | H14: High | I14: No | J14: Active | K14: Exact company email match | L14: 2 | M14: Microsoft Defender for Office 365 (Plan 2)+Microsoft 365 Business Standard
A15: Aubrey Tshabalala | B15: Aubrey@WearCheckRS.com | C15: Aubrey Tshabalala | D15: aubrey@wearcheckRS.com | E15: WEC114 | F15: RS | G15: Matched | H15: High | I15: No | J15: Active | K15: Exact company email match | L15: 2 | M15: Microsoft Defender for Office 365 (Plan 2)+Microsoft 365 Business Standard
A16: Bernard Lopi Molangoane | B16: lopi@WearCheckRS.com | C16: Bernard Lopi Molangoane | D16: lopim@wearcheck.co.za | E16: WC269 | F16: RS | G16: Matched | H16: Medium | I16: No | J16: Active | K16: Matched via exact name | L16: 2 | M16: Microsoft Defender for Office 365 (Plan 2)+Microsoft 365 Business Standard
A17: Betty Monyepao | B17: betty@WearCheckRS.com | C17: Mmatapa Betty Monyepao | D17: betty@wearcheckrs.com | E17: WC465 | F17: RS | G17: Matched | H17: High | I17: No | J17: Active | K17: Exact company email match | L17: 2 | M17: Microsoft Defender for Office 365 (Plan 2)+Microsoft 365 Business Standard
A18: Bianka De Beer | B18: Bianka@WearCheckRS.com | C18: Bianka de Beer | D18: Bianka@WearCheckRS.com | E18: WEC142 | F18: RS | G18: Matched | H18: High | I18: No | J18: Active | K18: Exact company email match | L18: 9 | M18: Microsoft Power Automate Free+Microsoft Power Apps Plan 2 Trial+Microsoft Fabric (Free)+Microsoft Copilot Studio Viral Trial+Microsoft Power Apps for Developer+Power Pages vTrial for Makers+Microsoft Defender for Office 365 (Plan 2)+Dynamics 365 Customer Insights Self-Service+Microsoft 365 Business Premium
A19: Boitumelo Makgamatha | B19: Boitumelo@WearCheckRS.com | F19: RS | G19: Confirmed | H19: High | I19: No | J19: Active | K19: User now added to employee master (reviewed) | L19: 2 | M19: Microsoft Defender for Office 365 (Plan 2)+Microsoft 365 Business Standard
A20: Chicco Tivane | B20: chicco@WearCheckRS.com | C20: Chicco Fransisco Tivane | D20: chicco@wearcheckrs.com | E20: WC380 | F20: RS | G20: Matched | H20: High | I20: No | J20: Active | K20: Exact company email match | L20: 2 | M20: Microsoft Defender for Office 365 (Plan 2)+Microsoft 365 Business Standard
A21: Chris Mostert | B21: ChrisM@wearcheckrs.com | C21: Chris Mostert | D21: chrism@wearcheckrs.com | E21: WEC100 | F21: RS | G21: Matched | H21: High | I21: No | J21: Active | K21: Exact company email match | L21: 2 | M21: Microsoft Defender for Office 365 (Plan 2)+Microsoft 365 Business Standard
A22: Christene Fourie | B22: Christene@WearCheckRS.com | F22: RS | G22: Confirmed | H22: High | I22: No | J22: Active | K22: Confirmed email alias match to chrstene@wearcheckrs.com (reviewed) | L22: 3 | M22: Microsoft Defender for Office 365 (Plan 2)+Microsoft Power Automate Free+Microsoft 365 Business Standard
A23: Christian Geel | B23: Christian@WearCheckRS.com | F23: RS | G23: Ex-Employee | H23: High | I23: No | J23: Ex-Employee | K23: No longer an employee. FLAG: Remove licence. | L23: 2 | M23: Microsoft Fabric (Free)+Microsoft Power Automate Free
A24: Christie | B24: christie.samancor@WearCheckRS.com | F24: RS | G24: Management Review | H24: Low | I24: Yes | J24: Management Review | K24: Not an employee — has free Fabric licence only. Flagged for management review. | L24: 1 | M24: Microsoft Fabric (Free)
A25: CJ Woller | B25: cj@WearCheckRS.com | C25: CJ Woller | D25: cj@wearcheckrs.com | E25: WEC120 | F25: RS | G25: Matched | H25: High | I25: No | J25: Active | K25: Exact company email match | L25: 3 | M25: Microsoft Defender for Office 365 (Plan 2)+Microsoft Power Automate Free+Microsoft 365 Business Standard
A26: Colleen Pyper | B26: colleen.pyper@WearCheckRS.com | C26: Colleen Pyper | D26: colleen.pyper@WearCheckRS.com | E26: WC486 | F26: AFS | G26: Matched | H26: High | I26: No | J26: Active | K26: Exact company email match | L26: 3 | M26: Microsoft Defender for Office 365 (Plan 2)+Microsoft Power Automate Free+Microsoft 365 Business Standard
A27: Daniel Molapo | B27: daniel@WearCheckRS.com | C27: Tshegofatsho Daniel Molapo | D27: daniel@wearcheckrs.com | E27: WC402 | F27: RS | G27: Matched | H27: High | I27: No | J27: Active | K27: Exact company email match | L27: 4 | M27: Microsoft Defender for Office 365 (Plan 2)+Microsoft 365 E3+Microsoft Fabric (Free)+Microsoft Power Automate Free
A28: David Lipange | B28: DavidL@WearCheckRS.com | C28: David Lipague | D28: davidl@wearcheckrs.com | E28: Unknown | F28: Mozambique | G28: Matched | H28: High | I28: No | J28: Active | K28: Exact company email match | L28: 3 | M28: Microsoft Defender for Office 365 (Plan 2)+Microsoft Fabric (Free)+Microsoft 365 Business Standard
A29: David Viljoen | B29: David@WearCheckRS.com | C29: David Viljoen | D29: David@wearcheckrs.com | E29: WEC081 | F29: RS | G29: Matched | H29: High | I29: No | J29: Active | K29: Exact company email match | L29: 4 | M29: Microsoft Defender for Office 365 (Plan 2)+Microsoft Fabric (Free)+Microsoft 365 Business Standard+Microsoft Power Automate Free
A30: Deon Gaarkeuken | B30: Deon@WearCheckRS.com | C30: Deon Gaarkeuken | D30: deon@wearcheckrs.com | E30: WC358 | F30: RS | G30: Matched | H30: High | I30: No | J30: Active | K30: Exact company email match | L30: 5 | M30: Microsoft Defender for Office 365 (Plan 2)+Power BI Premium Per User+Microsoft 365 E3+Microsoft Fabric (Free)+Microsoft Power Automate Free
A31: Desmond Ngomane | B31: desmond@WearCheckRS.com | C31: Desmond Ngomane | D31: desmond@wearcheckrs.com | E31: WEC086 | F31: RS | G31: Matched | H31: High | I31: No | J31: Active | K31: Exact company email match | L31: 3 | M31: Microsoft Defender for Office 365 (Plan 2)+Microsoft Fabric (Free)+Microsoft 365 Business Standard
A32: Dian Leff | B32: dian@WearCheckRS.com | C32: Dian Leff | D32: dian@wearcheckrs.com | E32: WCN008 | F32: Namibia | G32: Matched | H32: High | I32: No | J32: Active | K32: Exact company email match | L32: 2 | M32: Microsoft Defender for Office 365 (Plan 2)+Microsoft 365 Business Standard
A33: Douglas Prout-Jones | B33: douglas@WearCheckRS.com | C33: Douglas Prout-Jones | D33: Douglas@WearcheckRS.com | E33: WEC119 | F33: RS | G33: Matched | H33: High | I33: No | J33: Active | K33: Exact company email match | L33: 3 | M33: Microsoft Defender for Office 365 (Plan 2)+Microsoft Power Automate Free+Microsoft 365 Business Standard
A34: Eben Prinsloo | B34: eben@WearCheckRS.com | C34: Eben Prinsloo | D34: eben@wearcheckrs.com | E34: WEC122 | F34: RS | G34: Matched | H34: High | I34: No | J34: Active | K34: Exact company email match | L34: 3 | M34: Microsoft Defender for Office 365 (Plan 2)+Microsoft 365 Business Standard+Microsoft Fabric (Free)
A35: Edward Pieterse Jnr | B35: edwardfp@WearCheckRS.com | C35: Edward Frederick IV Pieterse | D35: edwardfp@wearcheckrs.com | E35: WC274 | F35: RS | G35: Matched | H35: High | I35: No | J35: Active | K35: Exact company email match | L35: 5 | M35: Microsoft Defender for Office 365 (Plan 2)+Microsoft Power Apps for Developer+Microsoft 365 E3+Microsoft Fabric (Free)+Microsoft Power Automate Free
A36: Edward Pieterse Snr | B36: epieterse@wearcheckrs.com | C36: Edward Pieterse | D36: epieterse@wearcheckrs.com | E36: WC271 | F36: RS | G36: Matched | H36: High | I36: No | J36: Active | K36: Exact company email match | L36: 4 | M36: Microsoft 365 Business Premium+Microsoft Defender for Office 365 (Plan 2)+Microsoft Power Automate Free+Microsoft Fabric (Free)
... A40: Evert Viljoen | B40: Evert@WearCheckRS.com | C40: Evert Viljoen | D40: evertv@wearcheck.co.za | E40: WC497 | F40: AFS | G40: Matched | H40: Medium | I40: No | J40: Active | K40: Matched via exact name | L40: 2 | M40: Microsoft Defender for Office 365 (Plan 2)+Microsoft 365 Business Premium
A41: FLIRIRVM1 | B41: flirirvm1@WearCheckRS.com | F41: RS | G41: Mapped by rule | H41: High | I41: No | J41: Active | K41: Generic/shared/service account defaulted to RS per instruction | L41: 2 | M41: Microsoft Defender for Office 365 (Plan 2)+Microsoft 365 Business Standard
A42: flirirvm2 | B42: flirirvm2@WearCheckRS.com | F42: RS | G42: Mapped by rule | H42: High | I42: No | J42: Active | K42: Generic/shared/service account defaulted to RS per instruction | L42: 3 | M42: Microsoft Defender for Office 365 (Plan 2)+Microsoft Fabric (Free)+Microsoft 365 Business Standard
A43: flirirvm3 | B43: flirirvm3@WearCheckRS.com | F43: RS | G43: Mapped by rule | H43: High | I43: No | J43: Active | K43: Generic/shared/service account defaulted to RS per instruction | L43: 3 | M43: Microsoft Defender for Office 365 (Plan 2)+Microsoft Fabric (Free)+Microsoft 365 Business Standard
A44: Francios Pretorius | B44: franciosp@WearCheckRS.com | C44: Michael Francios Pretorius | D44: Franciosp@wearcheckRS.com | E44: WEC080 | F44: RS | G44: Matched | H44: High | I44: No | J44: Active | K44: Exact company email match | L44: 3 | M44: Microsoft Defender for Office 365 (Plan 2)+Microsoft Power Automate Free+Microsoft 365 Business Standard
A45: Francois Pienaar | B45: FrancoisP@WearCheckRS.com | C45: Jozua Francois Joubert Pienaar | D45: francoisp@wearcheckrs.com | E45: WEC111 | F45: RS | G45: Matched | H45: High | I45: No | J45: Active | K45: Exact company email match | L45: 4 | M45: Microsoft Defender for Office 365 (Plan 2)+Microsoft Fabric (Free)+Microsoft 365 Business Standard+Microsoft Power Automate Free
A46: Francois van Eden | B46: francoisve@wearcheckrs.com | C46: Francois Jacobus van Eeden | D46: francoisve@wearcheckrs.com | E46: WC287 | F46: RS | G46: Matched | H46: High | I46: No | J46: Active | K46: Exact company email match | L46: 4 | M46: Microsoft 365 Business Premium+Microsoft Defender for Office 365 (Plan 2)+Microsoft Fabric (Free)+Microsoft Power Automate Free
A47: Freddy-Ben Gariseb | B47: Freddy-Ben@WearCheckRS.com | C47: Freddy-Ben Gariseb | D47: Freddy-Ben@wearcheckRS.com | E47: WCN004 | F47: Namibia | G47: Matched | H47: High | I47: No | J47: Active | K47: Exact company email match | L47: 2 | M47: Microsoft Defender for Office 365 (Plan 2)+Microsoft 365 Business Standard
A48: Gabriel | B48: Gabriel@WearCheckRS.com | C48: Gabriel Shikongo Nuunyango | D48: gabriel@wearcheckrs.com | E48: WCN007 | F48: Namibia | G48: Matched | H48: High | I48: No | J48: Active | K48: Exact company email match | L48: 3 | M48: Microsoft Defender for Office 365 (Plan 2)+Microsoft Fabric (Free)+Microsoft 365 Business Standard
A49: Gladwin Sekharume | B49: GladwinS@WearCheckRS.com | F49: RS | G49: Ex-Employee | H49: High | I49: No | J49: Ex-Employee | K49: No longer an employee. FLAG: Remove licence. | L49: 2 | M49: Microsoft Defender for Office 365 (Plan 2)+Microsoft 365 Business Standard
A50: Godfrey Boikhutso | B50: Godfrey@WearCheckRS.com | C50: Godfrey Boikhutso | D50: godfreyb@wearcheck.co.za | E50: WC510 | F50: AFS | G50: Matched | H50: Medium | I50: No | J50: Active | K50: Matched via exact name | L50: 2 | M50: Microsoft Defender for Office 365 (Plan 2)+Microsoft 365 Business Premium
A51: Gustav Lourens | B51: gustav@WearCheckRS.com | C51: Gustav Lourens | D51: gustav@wearcheckrs.com | E51: WC270 | F51: RS | G51: Matched | H51: High | I51: No | J51: Active | K51: Exact company email match | L51: 2 | M51: Microsoft Defender for Office 365 (Plan 2)+Microsoft 365 Business Standard
A52: Hannest Koegelenberg | B52: hannest@WearCheckRS.com | C52: Hannest Koegelenberg | D52: hannest@wearcheckrs.com | E52: WEC047 | F52: RS | G52: Matched | H52: High | I52: No | J52: Active | K52: Exact company email match | L52: 2 | M52: Microsoft Defender for Office 365 (Plan 2)+Microsoft 365 Business Standard
A53: Hein Coetzer | B53: heinc@WearCheckRS.com | C53: Hein Coetzer | D53: heinc@wearcheckrs.com | E53: WEC129 | F53: RS | G53: Matched | H53: High | I53: No | J53: Active | K53: Exact company email match | L53: 2 | M53: Microsoft Defender for Office 365 (Plan 2)+Microsoft 365 Business Standard
A54: Heinrich Kusel | B54: Heinrich@WearCheckRS.com | C54: Fritz Kusel | D54: heinrich@wearcheckrs.com | E54: WEC134 | F54: RS | G54: Matched | H54: High | I54: No | J54: Active | K54: Exact company email match | L54: 2 | M54: Microsoft Defender for Office 365 (Plan 2)+Microsoft 365 Business Standard
A55: Henry Mherekumombe | B55: Henry@WearCheckRS.com | C55: Henry Mherekumombe | D55: henry@wearcheckrs.com | E55: WEC098 | F55: RS | G55: Matched | H55: High | I55: No | J55: Active | K55: Exact company email match | L55: 3 | M55: Microsoft Defender for Office 365 (Plan 2)+Microsoft Power Automate Free+Microsoft 365 Business Standard
A56: Isac Zacarias | B56: Isac@WearCheckRS.com | C56: Isac Zacarias | D56: isac@wearcheckrs.com | E56: Unknown | F56: Mozambique | G56: Matched | H56: High | I56: No | J56: Active | K56: Exact company email match | L56: 3 | M56: Microsoft Defender for Office 365 (Plan 2)+Microsoft Fabric (Free)+Microsoft 365 Business Standard
A57: Ivan Langa | B57: Ivan@WearCheckRS.com | F57: RS | G57: Ex-Employee | H57: High | I57: No | J57: Ex-Employee | K57: No longer an employee. FLAG: Remove licence. | L57: 3 | M57: Microsoft Defender for Office 365 (Plan 2)+Microsoft Fabric (Free)+Microsoft 365 Business Standard
A58: Jaco De Beer | B58: jacodb@WearCheckRS.com | C58: Theunis Gerhardus Jacobus de Beer | D58: jacodb@wearcheckrs.com | E58: WEC097 | F58: RS | G58: Matched | H58: High | I58: No | J58: Active | K58: Exact company email match | L58: 2 | M58: Microsoft Defender for Office 365 (Plan 2)+Microsoft 365 Business Standard
A59: Jaco Venter | B59: JacoV@WearCheckRS.com | C59: Jacobus Frederick Venter | D59: jacov@wearcheck.co.za | E59: WC493 | F59: AFS | G59: Matched | H59: Medium | I59: No | J59: Active | K59: Matched via email alias/local-part | L59: 2 | M59: Microsoft Defender for Office 365 (Plan 2)+Microsoft 365 Business Premium
A60: Jaco Willer | B60: jaco@wearcheckrs.com | C60: Jacobus Johannes Willer | D60: jaco@wearcheckrs.com | E60: WC352 | F60: RS | G60: Matched | H60: High | I60: No | J60: Active | K60: Exact company email match | L60: 3 | M60: Microsoft 365 Business Premium+Microsoft Defender for Office 365 (Plan 2)+Microsoft Power Automate Free
A61: James Tshabalala | B61: james@WearCheckRS.com | C61: James Papayito Tshabalala | D61: james@WearCheckRS.com | E61: WC236 | F61: RS | G61: Matched | H61: High | I61: No | J61: Active | K61: Exact company email match | L61: 4 | M61: Microsoft Defender for Office 365 (Plan 2)+Microsoft Power Automate Free+Microsoft Fabric (Free)+Microsoft 365 Business Standard
A62: Jean-Jacques | B62: jj@WearCheckRS.com | C62: Jean Jacques de Beer | D62: jj@wearcheckrs.com | E62: WEC137 | F62: RS | G62: Matched | H62: High | I62: No | J62: Active | K62: Exact company email match | L62: 4 | M62: Microsoft 365 Business Premium+Microsoft Power Automate Free+Microsoft Fabric (Free)+Microsoft Defender for Office 365 (Plan 2)
A63: Jean Pierre Du Plessis | B63: Jean-Pierre@WearCheckRS.com | F63: AFS | G63: Confirmed | H63: High | I63: No | J63: Active | K63: Confirmed match via exact name (reviewed) | L63: 2 | M63: Microsoft 365 Business Standard+Microsoft Defender for Office 365 (Plan 2)
A64: Joe Kies | B64: Joe@WearCheckRS.com | F64: AFS | G64: Confirmed | H64: High | I64: No | J64: Active | K64: Confirmed match via manual alias/name rule (reviewed) | L64: 9 | M64: Microsoft Power Automate Free+Microsoft 365 Business Standard+Microsoft Power Apps Plan 2 Trial+Microsoft Fabric (Free)+Microsoft Copilot Studio Viral Trial+Microsoft Power Apps for Developer+Power Pages vTrial for Makers+Microsoft Defender for Office 365 (Plan 2)+Dynamics 365 Customer Insights Self-Service
A65: Johan Bekker | B65: JohanB@WearCheckRS.com | C65: Johan Bekker | D65: JohanB@wearcheckRS.com | E65: WC645 | F65: AFS | G65: Matched | H65: High | I65: No | J65: Active | K65: Exact company email match | L65: 3 | M65: Microsoft Defender for Office 365 (Plan 2)+Microsoft Power Automate Free+Microsoft 365 Business Standard
A66: Johan Rossouw | B66: JohanR@WearCheckRS.com | C66: Johan Rossouw | D66: johanr@wearcheckrs.com | E66: WC491 | F66: AFS | G66: Matched | H66: High | I66: No | J66: Active | K66: Exact company email match | L66: 2 | M66: Microsoft Defender for Office 365 (Plan 2)+Microsoft 365 Business Standard
A67: Johan Stols | B67: Johan.Stols@WearCheckRS.com | F67: AFS | G67: Confirmed | H67: High | I67: No | J67: Active | K67: Confirmed match via manual alias/name rule (reviewed) | L67: 3 | M67: Microsoft Defender for Office 365 (Plan 2)+Microsoft Power Automate Free+Microsoft 365 Business Standard
A68: Johandre Oosthuizen | B68: johandre@WearCheckRS.com | C68: Johannes Andréas Oosthuizen | D68: johandre@wearcheckrs.com | E68: WEC089 | F68: RS | G68: Matched | H68: High | I68: No | J68: Active | K68: Exact company email match | L68: 2 | M68: Microsoft Defender for Office 365 (Plan 2)+Microsoft 365 Business Standard
A69: jordanlionmasters | B69: jordanlionmasters_gmail.com#EXT#@wearcheckrs.onmicrosoft.com | F69: RS | G69: Mapped by rule | H69: High | I69: No | J69: Active | K69: Generic/shared/service account defaulted to RS per instruction | L69: 1 | M69: Microsoft Fabric (Free)
A70: Kenneth Moremi | B70: kenneth@WearCheckRS.com | F70: RS | G70: Ex-Employee | H70: High | I70: No | J70: Ex-Employee | K70: No longer an employee. FLAG: Remove licence. | L70: 2 | M70: Microsoft Defender for Office 365 (Plan 2)+Microsoft 365 Business Standard
A71: Kevin Henwood | B71: Kevin@WearCheckRS.com | C71: Kevin Henwood | D71: kevin@wearcheckrs.com | E71: WEC135 | F71: RS | G71: Matched | H71: High | I71: No | J71: Active | K71: Exact company email match | L71: 2 | M71: Microsoft Defender for Office 365 (Plan 2)+Microsoft 365 Business Standard
A72: Kevin Jonker | B72: kevinj@WearCheckRS.com | F72: RS | G72: Ex-Employee | H72: High | I72: No | J72: Ex-Employee | K72: No longer an employee. FLAG: Remove licence. | L72: 2 | M72: Microsoft Fabric (Free)+Microsoft Power Automate Free
A73: Khotso Mosala | B73: Khotso@WearCheckRS.com | C73: Khotso Thabo Mosala | D73: khotso@wearcheckrs.com | E73: WC482 | F73: AFS | G73: Matched | H73: High | I73: No | J73: Active | K73: Exact company email match | L73: 2 | M73: Microsoft Defender for Office 365 (Plan 2)+Microsoft 365 Business Standard
A74: Landus Walters | B74: Landus@WearCheckRS.com | C74: Norman Landus Walters | D74: Landus@wearcheckrs.com | E74: WC509 | F74: AFS | G74: Matched | H74: High | I74: No | J74: Active | K74: Exact company email match | L74: 2 | M74: Microsoft Defender for Office 365 (Plan 2)+Microsoft 365 Business Standard
A75: Lea Bodenstein | B75: Lea@WearCheckRS.com | F75: RS | G75: Contractor | H75: High | I75: No | J75: Contractor | K75: Not an employee — contractor. Licence allocated to RS. | L75: 3 | M75: Microsoft 365 Business Premium+Microsoft Defender for Office 365 (Plan 2)+Microsoft Fabric (Free)
A76: Leon Coetzee | B76: leon@WearCheckRS.com | C76: Leon Coetzee | D76: Leon@wearcheckrs.com | E76: WC455 | F76: RS | G76: Matched | H76: High | I76: No | J76: Active | K76: Exact company email match | L76: 3 | M76: Microsoft Defender for Office 365 (Plan 2)+Microsoft Power Automate Free+Microsoft 365 Business Standard
A77: Lesego Khuthwane | B77: Lesego@WearCheckRS.com | C77: Lesego Khuthwane | D77: Lesego@WearCheckRS.com | E77: WEC126 | F77: RS | G77: Matched | H77: High | I77: No | J77: Active | K77: Exact company email match | L77: 9 | M77: Microsoft 365 E3+Power BI Premium Per User+Microsoft Defender for Office 365 (Plan 2)+Microsoft Power Apps for Developer+Power Pages vTrial for Makers+Microsoft Fabric (Free)+Microsoft Power Apps Plan 2 Trial+Microsoft Copilot Studio Viral Trial+Microsoft Power Automate Free
A78: Lloyd Ngobeni | B78: Lloyd@WearCheckRS.com | C78: Lloyd Ngobeni | D78: lloyd@wearcheckrs.com | E78: WEC099 | F78: RS | G78: Matched | H78: High | I78: No | J78: Active | K78: Exact company email match | L78: 3 | M78: Microsoft Defender for Office 365 (Plan 2)+Microsoft Power Automate Free+Microsoft 365 Business Standard
A79: Londolani Managa | B79: LondolaniM@WearCheckRS.com | C79: Londolani Managa | D79: londolanim@wearcheckrs.com | E79: WC648 | F79: RS | G79: Matched | H79: High | I79: No | J79: Active | K79: Exact company email match | L79: 2 | M79: Microsoft Defender for Office 365 (Plan 2)+Microsoft 365 Business Standard
A80: Lorraine Mokgethi | B80: Lorraine@WearCheckRS.com | F80: AFS | G80: Confirmed | H80: High | I80: No | J80: Active | K80: Confirmed: she belongs here (reviewed) | L80: 2 | M80: Microsoft Defender for Office 365 (Plan 2)+Microsoft 365 Business Premium
A81: Louis Peacock | B81: louis@WearCheckRS.com | C81: Louis Robert Peacock | D81: louis@wearcheckrs.com | E81: WC277 | F81: RS | G81: Matched | H81: High | I81: No | J81: Active | K81: Exact company email match | L81: 4 | M81: Microsoft Defender for Office 365 (Plan 2)+Power BI Premium Per User+Microsoft 365 E3+Microsoft Power Automate Free | N81: Duplicate: 2 accounts (louis@WearCheckRS.com, Louis_Zoho@WearCheckRS.com)
A82: Louis Zoho | B82: Louis_Zoho@WearCheckRS.com | C82: Louis Robert Peacock | D82: louis@wearcheckrs.com | E82: WC277 | F82: RS | G82: Matched | H82: Medium | I82: No | J82: Active | K82: Matched via email alias/local-part | L82: 1 | M82: Microsoft 365 Business Standard | N82: Duplicate: 2 accounts (louis@WearCheckRS.com, Louis_Zoho@WearCheckRS.com)
A83: Lubby Lubis | B83: lubby@WearCheckRS.com | C83: Labby Jeffrey Lubis | D83: lubby@wearcheckrs.com | E83: WEC118 | F83: RS | G83: Matched | H83: High | I83: No | J83: Active | K83: Exact company email match | L83: 2 | M83: Microsoft Defender for Office 365 (Plan 2)+Microsoft 365 Business Standard
A84: Lucas Luus | B84: lucas@WearCheckRS.com | C84: Lucas Johannes Bartel Luus | D84: lucas@wearcheckrs.com | E84: WEC068 | F84: RS | G84: Matched | H84: High | I84: No | J84: Active | K84: Exact company email match | L84: 2 | M84: Microsoft Defender for Office 365 (Plan 2)+Microsoft 365 Business Standard
A85: Mandé Coetzee | B85: Mande@WearCheckRS.com | C85: Mandé Coetzee | D85: mande@wearcheckrs.com | E85: WEC116 | F85: RS | G85: Matched | H85: High | I85: No | J85: Active | K85: Exact company email match | L85: 4 | M85: Microsoft Defender for Office 365 (Plan 2)+Microsoft Fabric (Free)+Microsoft Power Automate Free+Microsoft 365 E3
A86: Mandiso Muchanga | B86: Mandiso@WearCheckRS.com | F86: RS | G86: Ex-Employee | H86: High | I86: No | J86: Ex-Employee | K86: No longer an employee. FLAG: Remove licence. | L86: 2 | M86: Microsoft Defender for Office 365 (Plan 2)+Microsoft 365 Business Standard
A87: Marcel Schoeman | B87: Marcel@WearCheckRS.com | C87: Marcel Schoeman | D87: marcel@wearcheckrs.com | E87: WEC102 | F87: RS | G87: Matched | H87: High | I87: No | J87: Active | K87: Exact company email match | L87: 3 | M87: Microsoft 365 Business Premium+Microsoft Defender for Office 365 (Plan 2)+Microsoft Fabric (Free)
A88: Mariette Du Rand | B88: mariette@WearCheckRS.com | C88: Mariette du Rand | D88: mariette@wearcheckrs.com | E88: WEC109 | F88: RS | G88: Matched | H88: High | I88: No | J88: Active | K88: Exact company email match | L88: 2 | M88: Microsoft 365 Business Premium+Microsoft Defender for Office 365 (Plan 2)
A89: Marshall Rasimphi | B89: marshallr@WearCheckRS.com | C89: Ailwel Marshall Rasimphi | D89: marshallr@wearcheckrs.com | E89: WEC094 | F89: RS | G89: Matched | H89: High | I89: No | J89: Active | K89: Exact company email match | L89: 2 | M89: Microsoft Defender for Office 365 (Plan 2)+Microsoft 365 Business Standard
A90: Marthinus Admin Account | B90: marthinus_admin@wearcheckrs.com | F90: RS | G90: Mapped by rule | H90: High | I90: No | J90: Active | K90: Generic/shared/service account defaulted to RS per instruction | L90: 2 | M90: Microsoft Power Automate Free+Microsoft Fabric (Free)
A91: Marthinus Steenkamp | B91: Marthinus@WearCheckRS.com | F91: RS | G91: Contractor | H91: High | I91: No | J91: Contractor | K91: Not an employee — contractor. Licence allocated to RS. | L91: 3 | M91: Microsoft Defender for Office 365 (Plan 2)+Microsoft 365 E3+Microsoft Fabric (Free)
A92: Martiens Van Aarde | B92: martiens@WearCheckRS.com | C92: Marthinus Jacobus van Aarde | D92: martiens@wearcheckrs.com | E92: WEC106 | F92: RS | G92: Matched | H92: High | I92: No | J92: Active | K92: Exact company email match | L92: 3 | M92: Microsoft Power Automate Free+Microsoft Defender for Office 365 (Plan 2)+Microsoft 365 Business Standard
A93: Martin Prinsloo | B93: martin.prinsloo@WearCheckRS.com | F93: RS | G93: Ex-Employee | H93: High | I93: No | J93: Ex-Employee | K93: No longer an employee. FLAG: Remove licence. | L93: 1 | M93: Microsoft Fabric (Free)
A94: Megan Salzwedel | B94: Megan@wearcheckrs.com | C94: Megan Salzwedel | D94: megan@wearcheckrs.com | E94: WEC104 | F94: RS | G94: Matched | H94: High | I94: No | J94: Active | K94: Exact company email match | L94: 5 | M94: Microsoft 365 Business Premium+Microsoft Defender for Office 365 (Plan 2)+Microsoft Power Apps Plan 2 Trial+Microsoft Fabric (Free)+Microsoft Power Automate Free
A95: Mervyn Gibbons | B95: Mervyn@WearCheckRS.com | F95: AFS | G95: Confirmed | H95: High | I95: No | J95: Active | K95: Confirmed match to mervyng@wearcheck.co.za (reviewed) | L95: 9 | M95: Microsoft Power Automate Free+Microsoft 365 Business Standard+Microsoft Power Apps Plan 2 Trial+Microsoft Fabric (Free)+Microsoft Copilot Studio Viral Trial+Microsoft Power Apps for Developer+Power Pages vTrial for Makers+Microsoft Defender for Office 365 (Plan 2)+Dynamics 365 Customer Insights Self-Service
A96: Meshack Nxumalo | B96: meshack@WearCheckRS.com | C96: Meshack Welcome Nxumalo | D96: meshack@wearcheckrs.com | E96: WEC088 | F96: RS | G96: Matched | H96: High | I96: No | J96: Active | K96: Exact company email match | L96: 2 | M96: Microsoft Defender for Office 365 (Plan 2)+Microsoft 365 Business Standard
A97: Micheal Masemola | B97: michealm@WearCheckRS.com | C97: Seporo Micheal Masemola | D97: michealm@wearcheckrs.com | E97: WC291 | F97: RS | G97: Matched | H97: High | I97: No | J97: Active | K97: Exact company email match | L97: 2 | M97: Microsoft Defender for Office 365 (Plan 2)+Microsoft 365 Business Standard
A98: Micheal Pretorius | B98: micheal@WearCheckRS.com | C98: Micheal Francios Pretorius | D98: micheal@wearcheckrs.com | E98: WEC076 | F98: RS | G98: Matched | H98: High | I98: No | J98: Active | K98: Exact company email match | L98: 3 | M98: Microsoft Defender for Office 365 (Plan 2)+Microsoft Power Automate Free+Microsoft 365 Business Standard
A99: Mike Shongwe | B99: MikeS@WearCheckRS.com | C99: Mike Mbongeni Shongwe | D99: mikes@weacheckrs.com | E99: WC483 | F99: AFS | G99: Matched | H99: Medium | I99: No | J99: Active | K99: Matched via email alias/local-part | L99: 2 | M99: Microsoft Defender for Office 365 (Plan 2)+Microsoft 365 Business Standard
A100: Morne Alberts | B100: mornea@wearcheckrs.com | C100: Mórne Alberts | D100: mornea@wearcheckrs.com | E100: WC361 | F100: RS | G100: Matched | H100: High | I100: No | J100: Active | K100: Exact company email match | L100: 3 | M100: Microsoft 365 Business Premium+Microsoft Defender for Office 365 (Plan 2)+Microsoft Fabric (Free)
A101: Muhamad Ikram Hanif | B101: Muhamad@WearCheckRS.com | C101: Muhamad Hanif | D101: Muhamad@wearcheckRS.com | E101: Unknown | F101: Mozambique | G101: Matched | H101: High | I101: No | J101: Active | K101: Exact company email match | L101: 3 | M101: Microsoft Defender for Office 365 (Plan 2)+Microsoft Fabric (Free)+Microsoft 365 Business Standard
A102: Nadhira Bux | B102: Nadhira@WearCheckRS.com | C102: Nadhira Bux | D102: nadhira@wearcheckrs.com | E102: WEC113 | F102: RS | G102: Matched | H102: High | I102: No | J102: Active | K102: Exact company email match | L102: 7 | M102: Microsoft 365 Business Premium+Microsoft Defender for Office 365 (Plan 2)+Microsoft Power Apps for Developer+Power Pages vTrial for Makers+Microsoft Copilot Studio Viral Trial+Microsoft Power Automate Free+Microsoft Fabric (Free)
A103: Nico du Plessis | B103: Nico.duPlessis@WearCheckRS.com | C103: Nicolaas du Plessis | D103: nico.duplessis@wearcheckrs.com | E103: WC506 | F103: AFS | G103: Matched | H103: High | I103: No | J103: Active | K103: Exact company email match | L103: 3 | M103: Microsoft Power Automate Free+Microsoft Defender for Office 365 (Plan 2)+Microsoft 365 Business Standard
...

Sheet SKU_Cost_Input
A1: SKU | B1: Active Users | C1: Billing Hint | D1: Monthly Invoice Amount (excl VAT, ZAR) | E1: Unit Cost Per User (excl VAT) | F1: VAT Amount | G1: Total incl VAT | H1: Notes | I1: Invoice Qty | J1: Qty Variance (Admin − Invoice) | K1: Variance Note
A2: Microsoft Defender for Office 365 (Plan 2) | B2: 130 | C2: Likely billable | D2: 10892.7 | E2: =IF(B2=0,0,D2/B2) | F2: =D2*Invoice_Input!B10 | G2: =D2+F2 | H2: Pre-filled from Invoice INV-0303 (invoice-only SKU — not in admin export) | I2: 130 | J2: 0 | K2: Match
A3: Microsoft 365 Business Standard | B3: 100 | C3: Likely billable | D3: 20326.35 | E3: =IF(B3=0,0,D3/B3) | F3: =D3*Invoice_Input!B10 | G3: =D3+F3 | H3: Pre-filled from Invoice INV-0303 (invoice-only SKU — not in admin export) | I3: 97 | J3: 3 | K3: Admin has 3 more — likely added after invoice billing date
A4: Microsoft Power Automate Free | B4: 52 | C4: Likely free / trial | D4: 0 | E4: =IF(B4=0,0,D4/B4) | F4: =D4*Invoice_Input!B10 | G4: =D4+F4 | H4: Free/trial — R0.00 pre-filled (no invoice cost expected) | I4: N/A | J4: N/A | K4: Not on invoice (free/trial)
A5: Microsoft Fabric (Free) | B5: 50 | C5: Likely free / trial | D5: 0 | E5: =IF(B5=0,0,D5/B5) | F5: =D5*Invoice_Input!B10 | G5: =D5+F5 | H5: Free/trial — R0.00 pre-filled (no invoice cost expected) | I5: N/A | J5: N/A | K5: Not on invoice (free/trial)
A6: Microsoft 365 Business Premium | B6: 21 | C6: Likely billable | D6: 8479.64 | E6: =IF(B6=0,0,D6/B6) | F6: =D6*Invoice_Input!B10 | G6: =D6+F6 | H6: Pre-filled from Invoice INV-0303 (invoice-only SKU — not in admin export) | I6: 23 | J6: -2 | K6: Invoice has 2 more — users may have been removed after billing
A7: Microsoft 365 E3 | B7: 14 | C7: Likely billable | D7: 9049.35 | E7: =IF(B7=0,0,D7/B7) | F7: =D7*Invoice_Input!B10 | G7: =D7+F7 | H7: Pre-filled from Invoice INV-0303 (invoice-only SKU — not in admin export) | I7: 15 | J7: -1 | K7: Invoice has 1 more — users may have been removed after billing
A8: Microsoft Copilot Studio Viral Trial | B8: 7 | C8: Likely free / trial | D8: 0 | E8: =IF(B8=0,0,D8/B8) | F8: =D8*Invoice_Input!B10 | G8: =D8+F8 | H8: Free/trial — R0.00 pre-filled (no invoice cost expected) | I8: N/A | J8: N/A | K8: Not on invoice (free/trial)
A9: Microsoft Power Apps Plan 2 Trial | B9: 6 | C9: Likely free / trial | D9: 0 | E9: =IF(B9=0,0,D9/B9) | F9: =D9*Invoice_Input!B10 | G9: =D9+F9 | H9: Free/trial — R0.00 pre-filled (no invoice cost expected) | I9: N/A | J9: N/A | K9: Not on invoice (free/trial)
A10: Microsoft Power Apps for Developer | B10: 6 | C10: Likely billable | D10: 0 | E10: =IF(B10=0,0,D10/B10) | F10: =D10*Invoice_Input!B10 | G10: =D10+F10 | H10: Enter the excl-VAT invoice amount for this SKU line item | I10: N/A | J10: N/A | K10: Not on invoice (free/trial)
A11: Power BI Premium Per User | B11: 6 | C11: Likely billable | D11: 2815.33 | E11: =IF(B11=0,0,D11/B11) | F11: =D11*Invoice_Input!B10 | G11: =D11+F11 | H11: Pre-filled from Invoice INV-0303 (invoice-only SKU — not in admin export) | I11: 7 | J11: -1 | K11: Invoice has 1 more — users may have been removed after billing
A12: Power Pages vTrial for Makers | B12: 5 | C12: Likely free / trial | D12: 0 | E12: =IF(B12=0,0,D12/B12) | F12: =D12*Invoice_Input!B10 | G12: =D12+F12 | H12: Free/trial — R0.00 pre-filled (no invoice cost expected) | I12: N/A | J12: N/A | K12: Not on invoice (free/trial)
A13: Exchange Online (Plan 1) | B13: 4 | C13: Likely billable | D13: 268.12 | E13: =IF(B13=0,0,D13/B13) | F13: =D13*Invoice_Input!B10 | G13: =D13+F13 | H13: Pre-filled from Invoice INV-0303 (invoice-only SKU — not in admin export) | I13: 4 | J13: 0 | K13: Match
A14: Dynamics 365 Customer Insights Self-Service | B14: 3 | C14: Likely billable | D14: 0 | E14: =IF(B14=0,0,D14/B14) | F14: =D14*Invoice_Input!B10 | G14: =D14+F14 | H14: Enter the excl-VAT invoice amount for this SKU line item | I14: N/A | J14: N/A | K14: Not on invoice (free/trial)
A15: Power Apps per app plan (1 app or website) | B15: 3 | C15: Likely billable | D15: 251.37 | E15: =IF(B15=0,0,D15/B15) | F15: =D15*Invoice_Input!B10 | G15: =D15+F15 | H15: Pre-filled from Invoice INV-0303 (invoice-only SKU — not in admin export) | I15: 3 | J15: -3 | K15: Invoice has 3 more — users may have been removed after billing
A16: Power Automate per user plan | B16: 1 | C16: Likely billable | D16: 251.37 | E16: =IF(B16=0,0,D16/B16) | F16: =D16*Invoice_Input!B10 | G16: =D16+F16 | H16: Pre-filled from Invoice INV-0303 (invoice-only SKU — not in admin export) | I16: 1 | J16: 0 | K16: Match
A17: TOTAL | B17: =SUM(B2:B16) | D17: =SUM(D2:D16) | F17: =SUM(F2:F16) | G17: =SUM(G2:G16) | I17: 280
A19: RECONCILIATION CHECK | C19: Invoice excl VAT | D19: =Invoice_Input!B11
C20: SKU Total excl VAT | D20: =D17
C21: Variance | D21: =D19-D20
C22: Status | D22: =IF(ABS(D21)<0.01,"PASS - Reconciled","FAIL - Check SKU amounts")
A25: QUANTITY DISCREPANCY: Invoice vs Admin Export
A26: SKUs where the invoice quantity differs from the Admin Centre user count. Investigate and rectify before finalising allocation.
A27: SKU | B27: Admin Users | C27: Invoice Qty | D27: Variance | E27: Impact | F27: Action Required
A28: Microsoft 365 Business Standard | B28: 100 | C28: 97 | D28: 3 | E28: Admin has 3 more user(s) — cost per user is lower than invoiced unit price | F28: Check if user(s) were added after the invoice billing date (25/03/2026)
A29: Microsoft 365 Business Premium | B29: 21 | C29: 23 | D29: -2 | E29: Invoice bills 2 more user(s) — paying for user(s) not in admin export | F29: Check if user(s) were removed after billing — confirm with COITE/Microsoft
A30: Microsoft 365 E3 | B30: 14 | C30: 15 | D30: -1 | E30: Invoice bills 1 more user(s) — paying for user(s) not in admin export | F30: Check if user(s) were removed after billing — confirm with COITE/Microsoft
A31: Power BI Premium Per User | B31: 6 | C31: 7 | D31: -1 | E31: Invoice bills 1 more user(s) — paying for user(s) not in admin export | F31: Check if user(s) were removed after billing — confirm with COITE/Microsoft
A32: Power Apps per app plan (1 app or website) | B32: 0 | C32: 3 | D32: -3 | E32: Invoice bills 3 more user(s) — paying for user(s) not in admin export | F32: Check if user(s) were removed after billing — confirm with COITE/Microsoft

Sheet Allocation_Detail
A1: Licensed Email | B1: Licensed Display Name | C1: Division | D1: Employee Number | E1: Match Status | F1: Review Required | G1: SKU | H1: Billing Hint | I1: Monthly Invoice Amount | J1: Active Users on SKU | K1: Unit Cost | L1: Allocated Cost | M1: Mapping Note | N1: Optimisation Flag
A2: admin@WearCheckRS.com | B2: Admin | C2: RS | E2: Mapped by rule | F2: No | G2: Microsoft Defender for Office 365 (Plan 2) | H2: Likely billable | I2: =IFERROR(VLOOKUP(G2,SKU_Cost_Input!$A$2:$E$16,4,FALSE),0) | J2: =IFERROR(VLOOKUP(G2,SKU_Cost_Input!$A$2:$E$16,2,FALSE),0) | K2: =IF(J2=0,0,I2/J2) | L2: =K2 | M2: Generic/shared/service account defaulted to RS per instruction
A3: admin@WearCheckRS.com | B3: Admin | C3: RS | E3: Mapped by rule | F3: No | G3: Microsoft Fabric (Free) | H3: Likely free / trial | I3: =IFERROR(VLOOKUP(G3,SKU_Cost_Input!$A$2:$E$16,4,FALSE),0) | J3: =IFERROR(VLOOKUP(G3,SKU_Cost_Input!$A$2:$E$16,2,FALSE),0) | K3: =IF(J3=0,0,I3/J3) | L3: =K3 | M3: Generic/shared/service account defaulted to RS per instruction
A4: admin@WearCheckRS.com | B4: Admin | C4: RS | E4: Mapped by rule | F4: No | G4: Microsoft 365 E3 | H4: Likely billable | I4: =IFERROR(VLOOKUP(G4,SKU_Cost_Input!$A$2:$E$16,4,FALSE),0) | J4: =IFERROR(VLOOKUP(G4,SKU_Cost_Input!$A$2:$E$16,2,FALSE),0) | K4: =IF(J4=0,0,I4/J4) | L4: =K4 | M4: Generic/shared/service account defaulted to RS per instruction | N4: Review: E3 may be downgradeable to E1 or Business Basic
A5: A.Ludick@WearCheckRS.com | B5: Adri Ludick | C5: RS | D5: WC492 | E5: Matched | F5: No | G5: Microsoft 365 Business Premium | H5: Likely billable | I5: =IFERROR(VLOOKUP(G5,SKU_Cost_Input!$A$2:$E$16,4,FALSE),0) | J5: =IFERROR(VLOOKUP(G5,SKU_Cost_Input!$A$2:$E$16,2,FALSE),0) | K5: =IF(J5=0,0,I5/J5) | L5: =K5 | M5: Exact company email match | N5: Review: Business Premium — consider Business Basic/Standard
A6: A.Ludick@WearCheckRS.com | B6: Adri Ludick | C6: RS | D6: WC492 | E6: Matched | F6: No | G6: Microsoft Copilot Studio Viral Trial | H6: Likely free / trial | I6: =IFERROR(VLOOKUP(G6,SKU_Cost_Input!$A$2:$E$16,4,FALSE),0) | J6: =IFERROR(VLOOKUP(G6,SKU_Cost_Input!$A$2:$E$16,2,FALSE),0) | K6: =IF(J6=0,0,I6/J6) | L6: =K6 | M6: Exact company email match
A7: A.Ludick@WearCheckRS.com | B7: Adri Ludick | C7: RS | D7: WC492 | E7: Matched | F7: No | G7: Microsoft Defender for Office 365 (Plan 2) | H7: Likely billable | I7: =IFERROR(VLOOKUP(G7,SKU_Cost_Input!$A$2:$E$16,4,FALSE),0) | J7: =IFERROR(VLOOKUP(G7,SKU_Cost_Input!$A$2:$E$16,2,FALSE),0) | K7: =IF(J7=0,0,I7/J7) | L7: =K7 | M7: Exact company email match
A8: A.Ludick@WearCheckRS.com | B8: Adri Ludick | C8: RS | D8: WC492 | E8: Matched | F8: No | G8: Microsoft Power Automate Free | H8: Likely free / trial | I8: =IFERROR(VLOOKUP(G8,SKU_Cost_Input!$A$2:$E$16,4,FALSE),0) | J8: =IFERROR(VLOOKUP(G8,SKU_Cost_Input!$A$2:$E$16,2,FALSE),0) | K8: =IF(J8=0,0,I8/J8) | L8: =K8 | M8: Exact company email match
A9: Adri.ludick@WearCheckRS.com | B9: Adri Ludick Old | C9: RS | E9: Ex-Employee | F9: No | G9: Microsoft Defender for Office 365 (Plan 2) | H9: Likely billable | I9: =IFERROR(VLOOKUP(G9,SKU_Cost_Input!$A$2:$E$16,4,FALSE),0) | J9: =IFERROR(VLOOKUP(G9,SKU_Cost_Input!$A$2:$E$16,2,FALSE),0) | K9: =IF(J9=0,0,I9/J9) | L9: =K9 | M9: Old account — new email A.Ludick@WearCheckRS.com is active. FLAG: Remove this licence.
A10: Adri.ludick@WearCheckRS.com | B10: Adri Ludick Old | C10: RS | E10: Ex-Employee | F10: No | G10: Microsoft Power Automate Free | H10: Likely free / trial | I10: =IFERROR(VLOOKUP(G10,SKU_Cost_Input!$A$2:$E$16,4,FALSE),0) | J10: =IFERROR(VLOOKUP(G10,SKU_Cost_Input!$A$2:$E$16,2,FALSE),0) | K10: =IF(J10=0,0,I10/J10) | L10: =K10 | M10: Old account — new email A.Ludick@WearCheckRS.com is active. FLAG: Remove this licence.
A11: Adri.ludick@WearCheckRS.com | B11: Adri Ludick Old | C11: RS | E11: Ex-Employee | F11: No | G11: Microsoft 365 Business Standard | H11: Likely billable | I11: =IFERROR(VLOOKUP(G11,SKU_Cost_Input!$A$2:$E$16,4,FALSE),0) | J11: =IFERROR(VLOOKUP(G11,SKU_Cost_Input!$A$2:$E$16,2,FALSE),0) | K11: =IF(J11=0,0,I11/J11) | L11: =K11 | M11: Old account — new email A.Ludick@WearCheckRS.com is active. FLAG: Remove this licence. | N11: Review: Business Standard — consider Business Basic if sufficient
A12: adriaanb@WearCheckRS.com | B12: Adriaan Bouwer | C12: RS | D12: WC383 | E12: Matched | F12: No | G12: Microsoft Defender for Office 365 (Plan 2) | H12: Likely billable | I12: =IFERROR(VLOOKUP(G12,SKU_Cost_Input!$A$2:$E$16,4,FALSE),0) | J12: =IFERROR(VLOOKUP(G12,SKU_Cost_Input!$A$2:$E$16,2,FALSE),0) | K12: =IF(J12=0,0,I12/J12) | L12: =K12 | M12: Exact company email match
A13: adriaanb@WearCheckRS.com | B13: Adriaan Bouwer | C13: RS | D13: WC383 | E13: Matched | F13: No | G13: Microsoft Power Automate Free | H13: Likely free / trial | I13: =IFERROR(VLOOKUP(G13,SKU_Cost_Input!$A$2:$E$16,4,FALSE),0) | J13: =IFERROR(VLOOKUP(G13,SKU_Cost_Input!$A$2:$E$16,2,FALSE),0) | K13: =IF(J13=0,0,I13/J13) | L13: =K13 | M13: Exact company email match
A14: adriaanb@WearCheckRS.com | B14: Adriaan Bouwer | C14: RS | D14: WC383 | E14: Matched | F14: No | G14: Microsoft 365 Business Standard | H14: Likely billable | I14: =IFERROR(VLOOKUP(G14,SKU_Cost_Input!$A$2:$E$16,4,FALSE),0) | J14: =IFERROR(VLOOKUP(G14,SKU_Cost_Input!$A$2:$E$16,2,FALSE),0) | K14: =IF(J14=0,0,I14/J14) | L14: =K14 | M14: Exact company email match | N14: Review: Business Standard — consider Business Basic if sufficient
A15: adriaanb@WearCheckRS.com | B15: Adriaan Bouwer | C15: RS | D15: WC383 | E15: Matched | F15: No | G15: Microsoft Fabric (Free) | H15: Likely free / trial | I15: =IFERROR(VLOOKUP(G15,SKU_Cost_Input!$A$2:$E$16,4,FALSE),0) | J15: =IFERROR(VLOOKUP(G15,SKU_Cost_Input!$A$2:$E$16,2,FALSE),0) | K15: =IF(J15=0,0,I15/J15) | L15: =K15 | M15: Exact company email match
A16: afs_app@WearCheckRS.com | B16: AFS Application | C16: AFS | E16: Mapped by rule | F16: No | G16: Microsoft Power Automate Free | H16: Likely free / trial | I16: =IFERROR(VLOOKUP(G16,SKU_Cost_Input!$A$2:$E$16,4,FALSE),0) | J16: =IFERROR(VLOOKUP(G16,SKU_Cost_Input!$A$2:$E$16,2,FALSE),0) | K16: =IF(J16=0,0,I16/J16) | L16: =K16 | M16: Generic/shared/service account defaulted to RS per instruction
A17: afs_app@WearCheckRS.com | B17: AFS Application | C17: AFS | E17: Mapped by rule | F17: No | G17: Exchange Online (Plan 1) | H17: Likely billable | I17: =IFERROR(VLOOKUP(G17,SKU_Cost_Input!$A$2:$E$16,4,FALSE),0) | J17: =IFERROR(VLOOKUP(G17,SKU_Cost_Input!$A$2:$E$16,2,FALSE),0) | K17: =IF(J17=0,0,I17/J17) | L17: =K17 | M17: Generic/shared/service account defaulted to RS per instruction
A18: Alex@WearCheckRS.com | B18: Alex Outram | C18: RS | D18: WEC105 | E18: Matched | F18: No | G18: Microsoft Defender for Office 365 (Plan 2) | H18: Likely billable | I18: =IFERROR(VLOOKUP(G18,SKU_Cost_Input!$A$2:$E$16,4,FALSE),0) | J18: =IFERROR(VLOOKUP(G18,SKU_Cost_Input!$A$2:$E$16,2,FALSE),0) | K18: =IF(J18=0,0,I18/J18) | L18: =K18 | M18: Exact company email match
A19: Alex@WearCheckRS.com | B19: Alex Outram | C19: RS | D19: WEC105 | E19: Matched | F19: No | G19: Microsoft Power Automate Free | H19: Likely free / trial | I19: =IFERROR(VLOOKUP(G19,SKU_Cost_Input!$A$2:$E$16,4,FALSE),0) | J19: =IFERROR(VLOOKUP(G19,SKU_Cost_Input!$A$2:$E$16,2,FALSE),0) | K19: =IF(J19=0,0,I19/J19) | L19: =K19 | M19: Exact company email match
A20: Alex@WearCheckRS.com | B20: Alex Outram | C20: RS | D20: WEC105 | E20: Matched | F20: No | G20: Microsoft Fabric (Free) | H20: Likely free / trial | I20: =IFERROR(VLOOKUP(G20,SKU_Cost_Input!$A$2:$E$16,4,FALSE),0) | J20: =IFERROR(VLOOKUP(G20,SKU_Cost_Input!$A$2:$E$16,2,FALSE),0) | K20: =IF(J20=0,0,I20/J20) | L20: =K20 | M20: Exact company email match
A21: Alex@WearCheckRS.com | B21: Alex Outram | C21: RS | D21: WEC105 | E21: Matched | F21: No | G21: Microsoft 365 Business Standard | H21: Likely billable | I21: =IFERROR(VLOOKUP(G21,SKU_Cost_Input!$A$2:$E$16,4,FALSE),0) | J21: =IFERROR(VLOOKUP(G21,SKU_Cost_Input!$A$2:$E$16,2,FALSE),0) | K21: =IF(J21=0,0,I21/J21) | L21: =K21 | M21: Exact company email match | N21: Review: Business Standard — consider Business Basic if sufficient
A22: Allan@WearCheckRS.com | B22: Allan Stuurman | C22: RS | D22: WEC123 | E22: Matched | F22: No | G22: Microsoft Defender for Office 365 (Plan 2) | H22: Likely billable | I22: =IFERROR(VLOOKUP(G22,SKU_Cost_Input!$A$2:$E$16,4,FALSE),0) | J22: =IFERROR(VLOOKUP(G22,SKU_Cost_Input!$A$2:$E$16,2,FALSE),0) | K22: =IF(J22=0,0,I22/J22) | L22: =K22 | M22: Exact company email match
A23: Allan@WearCheckRS.com | B23: Allan Stuurman | C23: RS | D23: WEC123 | E23: Matched | F23: No | G23: Microsoft 365 Business Standard | H23: Likely billable | I23: =IFERROR(VLOOKUP(G23,SKU_Cost_Input!$A$2:$E$16,4,FALSE),0) | J23: =IFERROR(VLOOKUP(G23,SKU_Cost_Input!$A$2:$E$16,2,FALSE),0) | K23: =IF(J23=0,0,I23/J23) | L23: =K23 | M23: Exact company email match | N23: Review: Business Standard — consider Business Basic if sufficient
A24: Andrew@wearcheckrs.com | B24: Andrew Robb | C24: RS | D24: WEC103 | E24: Matched | F24: No | G24: Microsoft 365 Business Premium | H24: Likely billable | I24: =IFERROR(VLOOKUP(G24,SKU_Cost_Input!$A$2:$E$16,4,FALSE),0) | J24: =IFERROR(VLOOKUP(G24,SKU_Cost_Input!$A$2:$E$16,2,FALSE),0) | K24: =IF(J24=0,0,I24/J24) | L24: =K24 | M24: Exact company email match | N24: Review: Business Premium — consider Business Basic/Standard
A25: Andrew@wearcheckrs.com | B25: Andrew Robb | C25: RS | D25: WEC103 | E25: Matched | F25: No | G25: Microsoft Defender for Office 365 (Plan 2) | H25: Likely billable | I25: =IFERROR(VLOOKUP(G25,SKU_Cost_Input!$A$2:$E$16,4,FALSE),0) | J25: =IFERROR(VLOOKUP(G25,SKU_Cost_Input!$A$2:$E$16,2,FALSE),0) | K25: =IF(J25=0,0,I25/J25) | L25: =K25 | M25: Exact company email match
A26: Andrew@wearcheckrs.com | B26: Andrew Robb | C26: RS | D26: WEC103 | E26: Matched | F26: No | G26: Microsoft Fabric (Free) | H26: Likely free / trial | I26: =IFERROR(VLOOKUP(G26,SKU_Cost_Input!$A$2:$E$16,4,FALSE),0) | J26: =IFERROR(VLOOKUP(G26,SKU_Cost_Input!$A$2:$E$16,2,FALSE),0) | K26: =IF(J26=0,0,I26/J26) | L26: =K26 | M26: Exact company email match
A27: annahm@WearCheckRS.com | B27: Annah Modutwane | C27: RS | D27: WC484 | E27: Matched | F27: No | G27: Microsoft Defender for Office 365 (Plan 2) | H27: Likely billable | I27: =IFERROR(VLOOKUP(G27,SKU_Cost_Input!$A$2:$E$16,4,FALSE),0) | J27: =IFERROR(VLOOKUP(G27,SKU_Cost_Input!$A$2:$E$16,2,FALSE),0) | K27: =IF(J27=0,0,I27/J27) | L27: =K27 | M27: Exact company email match
A28: annahm@WearCheckRS.com | B28: Annah Modutwane | C28: RS | D28: WC484 | E28: Matched | F28: No | G28: Microsoft Power Automate Free | H28: Likely free / trial | I28: =IFERROR(VLOOKUP(G28,SKU_Cost_Input!$A$2:$E$16,4,FALSE),0) | J28: =IFERROR(VLOOKUP(G28,SKU_Cost_Input!$A$2:$E$16,2,FALSE),0) | K28: =IF(J28=0,0,I28/J28) | L28: =K28 | M28: Exact company email match
A29: annahm@WearCheckRS.com | B29: Annah Modutwane | C29: RS | D29: WC484 | E29: Matched | F29: No | G29: Microsoft Fabric (Free) | H29: Likely free / trial | I29: =IFERROR(VLOOKUP(G29,SKU_Cost_Input!$A$2:$E$16,4,FALSE),0) | J29: =IFERROR(VLOOKUP(G29,SKU_Cost_Input!$A$2:$E$16,2,FALSE),0) | K29: =IF(J29=0,0,I29/J29) | L29: =K29 | M29: Exact company email match
A30: annahm@WearCheckRS.com | B30: Annah Modutwane | C30: RS | D30: WC484 | E30: Matched | F30: No | G30: Microsoft 365 Business Standard | H30: Likely billable | I30: =IFERROR(VLOOKUP(G30,SKU_Cost_Input!$A$2:$E$16,4,FALSE),0) | J30: =IFERROR(VLOOKUP(G30,SKU_Cost_Input!$A$2:$E$16,2,FALSE),0) | K30: =IF(J30=0,0,I30/J30) | L30: =K30 | M30: Exact company email match | N30: Review: Business Standard — consider Business Basic if sufficient
A31: annemie@WearCheckRS.com | B31: Annemie Willer | C31: RS | D31: WC319 | E31: Matched | F31: No | G31: Microsoft Defender for Office 365 (Plan 2) | H31: Likely billable | I31: =IFERROR(VLOOKUP(G31,SKU_Cost_Input!$A$2:$E$16,4,FALSE),0) | J31: =IFERROR(VLOOKUP(G31,SKU_Cost_Input!$A$2:$E$16,2,FALSE),0) | K31: =IF(J31=0,0,I31/J31) | L31: =K31 | M31: Exact company email match
A32: annemie@WearCheckRS.com | B32: Annemie Willer | C32: RS | D32: WC319 | E32: Matched | F32: No | G32: Power BI Premium Per User | H32: Likely billable | I32: =IFERROR(VLOOKUP(G32,SKU_Cost_Input!$A$2:$E$16,4,FALSE),0) | J32: =IFERROR(VLOOKUP(G32,SKU_Cost_Input!$A$2:$E$16,2,FALSE),0) | K32: =IF(J32=0,0,I32/J32) | L32: =K32 | M32: Exact company email match
A33: annemie@WearCheckRS.com | B33: Annemie Willer | C33: RS | D33: WC319 | E33: Matched | F33: No | G33: Microsoft Copilot Studio Viral Trial | H33: Likely free / trial | I33: =IFERROR(VLOOKUP(G33,SKU_Cost_Input!$A$2:$E$16,4,FALSE),0) | J33: =IFERROR(VLOOKUP(G33,SKU_Cost_Input!$A$2:$E$16,2,FALSE),0) | K33: =IF(J33=0,0,I33/J33) | L33: =K33 | M33: Exact company email match
A34: annemie@WearCheckRS.com | B34: Annemie Willer | C34: RS | D34: WC319 | E34: Matched | F34: No | G34: Microsoft Power Apps Plan 2 Trial | H34: Likely free / trial | I34: =IFERROR(VLOOKUP(G34,SKU_Cost_Input!$A$2:$E$16,4,FALSE),0) | J34: =IFERROR(VLOOKUP(G34,SKU_Cost_Input!$A$2:$E$16,2,FALSE),0) | K34: =IF(J34=0,0,I34/J34) | L34: =K34 | M34: Exact company email match
A35: annemie@WearCheckRS.com | B35: Annemie Willer | C35: RS | D35: WC319 | E35: Matched | F35: No | G35: Microsoft 365 E3 | H35: Likely billable | I35: =IFERROR(VLOOKUP(G35,SKU_Cost_Input!$A$2:$E$16,4,FALSE),0) | J35: =IFERROR(VLOOKUP(G35,SKU_Cost_Input!$A$2:$E$16,2,FALSE),0) | K35: =IF(J35=0,0,I35/J35) | L35: =K35 | M35: Exact company email match | N35: Review: E3 may be downgradeable to E1 or Business Basic
A36: annemie@WearCheckRS.com | B36: Annemie Willer | C36: RS | D36: WC319 | E36: Matched | F36: No | G36: Microsoft Fabric (Free) | H36: Likely free / trial | I36: =IFERROR(VLOOKUP(G36,SKU_Cost_Input!$A$2:$E$16,4,FALSE),0) | J36: =IFERROR(VLOOKUP(G36,SKU_Cost_Input!$A$2:$E$16,2,FALSE),0) | K36: =IF(J36=0,0,I36/J36) | L36: =K36 | M36: Exact company email match
A37: annemie@WearCheckRS.com | B37: Annemie Willer | C37: RS | D37: WC319 | E37: Matched | F37: No | G37: Microsoft Power Automate Free | H37: Likely free / trial | I37: =IFERROR(VLOOKUP(G37,SKU_Cost_Input!$A$2:$E$16,4,FALSE),0) | J37: =IFERROR(VLOOKUP(G37,SKU_Cost_Input!$A$2:$E$16,2,FALSE),0) | K37: =IF(J37=0,0,I37/J37) | L37: =K37 | M37: Exact company email match
A38: Antonio.Ehrke@WearCheckRS.com | B38: Antonio Ehrke | C38: AFS | D38: WC503 | E38: Matched | F38: No | G38: Microsoft Defender for Office 365 (Plan 2) | H38: Likely billable | I38: =IFERROR(VLOOKUP(G38,SKU_Cost_Input!$A$2:$E$16,4,FALSE),0) | J38: =IFERROR(VLOOKUP(G38,SKU_Cost_Input!$A$2:$E$16,2,FALSE),0) | K38: =IF(J38=0,0,I38/J38) | L38: =K38 | M38: Exact company email match
A39: Antonio.Ehrke@WearCheckRS.com | B39: Antonio Ehrke | C39: AFS | D39: WC503 | E39: Matched | F39: No | G39: Microsoft 365 Business Standard | H39: Likely billable | I39: =IFERROR(VLOOKUP(G39,SKU_Cost_Input!$A$2:$E$16,4,FALSE),0) | J39: =IFERROR(VLOOKUP(G39,SKU_Cost_Input!$A$2:$E$16,2,FALSE),0) | K39: =IF(J39=0,0,I39/J39) | L39: =K39 | M39: Exact company email match | N39: Review: Business Standard — consider Business Basic if sufficient
A40: Armindo@WearCheckRS.com | B40: Armindo Mucacho | C40: Mozambique | D40: Unknown | E40: Matched | F40: No | G40: Microsoft Defender for Office 365 (Plan 2) | H40: Likely billable | I40: =IFERROR(VLOOKUP(G40,SKU_Cost_Input!$A$2:$E$16,4,FALSE),0) | J40: =IFERROR(VLOOKUP(G40,SKU_Cost_Input!$A$2:$E$16,2,FALSE),0) | K40: =IF(J40=0,0,I40/J40) | L40: =K40 | M40: Exact company email match
A41: Armindo@WearCheckRS.com | B41: Armindo Mucacho | C41: Mozambique | D41: Unknown | E41: Matched | F41: No | G41: Microsoft Fabric (Free) | H41: Likely free / trial | I41: =IFERROR(VLOOKUP(G41,SKU_Cost_Input!$A$2:$E$16,4,FALSE),0) | J41: =IFERROR(VLOOKUP(G41,SKU_Cost_Input!$A$2:$E$16,2,FALSE),0) | K41: =IF(J41=0,0,I41/J41) | L41: =K41 | M41: Exact company email match
A42: Armindo@WearCheckRS.com | B42: Armindo Mucacho | C42: Mozambique | D42: Unknown | E42: Matched | F42: No | G42: Microsoft 365 Business Standard | H42: Likely billable | I42: =IFERROR(VLOOKUP(G42,SKU_Cost_Input!$A$2:$E$16,4,FALSE),0) | J42: =IFERROR(VLOOKUP(G42,SKU_Cost_Input!$A$2:$E$16,2,FALSE),0) | K42: =IF(J42=0,0,I42/J42) | L42: =K42 | M42: Exact company email match | N42: Review: Business Standard — consider Business Basic if sufficient
A43: Arnold@WearCheckRS.com | B43: Arnold van Zyl | C43: AFS | D43: WC526 | E43: Matched | F43: No | G43: Microsoft Defender for Office 365 (Plan 2) | H43: Likely billable | I43: =IFERROR(VLOOKUP(G43,SKU_Cost_Input!$A$2:$E$16,4,FALSE),0) | J43: =IFERROR(VLOOKUP(G43,SKU_Cost_Input!$A$2:$E$16,2,FALSE),0) | K43: =IF(J43=0,0,I43/J43) | L43: =K43 | M43: Exact company email match
A44: Arnold@WearCheckRS.com | B44: Arnold van Zyl | C44: AFS | D44: WC526 | E44: Matched | F44: No | G44: Microsoft 365 Business Standard | H44: Likely billable | I44: =IFERROR(VLOOKUP(G44,SKU_Cost_Input!$A$2:$E$16,4,FALSE),0) | J44: =IFERROR(VLOOKUP(G44,SKU_Cost_Input!$A$2:$E$16,2,FALSE),0) | K44: =IF(J44=0,0,I44/J44) | L44: =K44 | M44: Exact company email match | N44: Review: Business Standard — consider Business Basic if sufficient
A45: Aubrey@WearCheckRS.com | B45: Aubrey Tshabalala | C45: RS | D45: WEC114 | E45: Matched | F45: No | G45: Microsoft Defender for Office 365 (Plan 2) | H45: Likely billable | I45: =IFERROR(VLOOKUP(G45,SKU_Cost_Input!$A$2:$E$16,4,FALSE),0) | J45: =IFERROR(VLOOKUP(G45,SKU_Cost_Input!$A$2:$E$16,2,FALSE),0) | K45: =IF(J45=0,0,I45/J45) | L45: =K45 | M45: Exact company email match
A46: Aubrey@WearCheckRS.com | B46: Aubrey Tshabalala | C46: RS | D46: WEC114 | E46: Matched | F46: No | G46: Microsoft 365 Business Standard | H46: Likely billable | I46: =IFERROR(VLOOKUP(G46,SKU_Cost_Input!$A$2:$E$16,4,FALSE),0) | J46: =IFERROR(VLOOKUP(G46,SKU_Cost_Input!$A$2:$E$16,2,FALSE),0) | K46: =IF(J46=0,0,I46/J46) | L46: =K46 | M46: Exact company email match | N46: Review: Business Standard — consider Business Basic if sufficient
A47: lopi@WearCheckRS.com | B47: Bernard Lopi Molangoane | C47: RS | D47: WC269 | E47: Matched | F47: No | G47: Microsoft Defender for Office 365 (Plan 2) | H47: Likely billable | I47: =IFERROR(VLOOKUP(G47,SKU_Cost_Input!$A$2:$E$16,4,FALSE),0) | J47: =IFERROR(VLOOKUP(G47,SKU_Cost_Input!$A$2:$E$16,2,FALSE),0) | K47: =IF(J47=0,0,I47/J47) | L47: =K47 | M47: Matched via exact name
A48: lopi@WearCheckRS.com | B48: Bernard Lopi Molangoane | C48: RS | D48: WC269 | E48: Matched | F48: No | G48: Microsoft 365 Business Standard | H48: Likely billable | I48: =IFERROR(VLOOKUP(G48,SKU_Cost_Input!$A$2:$E$16,4,FALSE),0) | J48: =IFERROR(VLOOKUP(G48,SKU_Cost_Input!$A$2:$E$16,2,FALSE),0) | K48: =IF(J48=0,0,I48/J48) | L48: =K48 | M48: Matched via exact name | N48: Review: Business Standard — consider Business Basic if sufficient
A49: betty@WearCheckRS.com | B49: Betty Monyepao | C49: RS | D49: WC465 | E49: Matched | F49: No | G49: Microsoft Defender for Office 365 (Plan 2) | H49: Likely billable | I49: =IFERROR(VLOOKUP(G49,SKU_Cost_Input!$A$2:$E$16,4,FALSE),0) | J49: =IFERROR(VLOOKUP(G49,SKU_Cost_Input!$A$2:$E$16,2,FALSE),0) | K49: =IF(J49=0,0,I49/J49) | L49: =K49 | M49: Exact company email match
A50: betty@WearCheckRS.com | B50: Betty Monyepao | C50: RS | D50: WC465 | E50: Matched | F50: No | G50: Microsoft 365 Business Standard | H50: Likely billable | I50: =IFERROR(VLOOKUP(G50,SKU_Cost_Input!$A$2:$E$16,4,FALSE),0) | J50: =IFERROR(VLOOKUP(G50,SKU_Cost_Input!$A$2:$E$16,2,FALSE),0) | K50: =IF(J50=0,0,I50/J50) | L50: =K50 | M50: Exact company email match | N50: Review: Business Standard — consider Business Basic if sufficient
A51: Bianka@WearCheckRS.com | B51: Bianka De Beer | C51: RS | D51: WEC142 | E51: Matched | F51: No | G51: Microsoft Power Automate Free | H51: Likely free / trial | I51: =IFERROR(VLOOKUP(G51,SKU_Cost_Input!$A$2:$E$16,4,FALSE),0) | J51: =IFERROR(VLOOKUP(G51,SKU_Cost_Input!$A$2:$E$16,2,FALSE),0) | K51: =IF(J51=0,0,I51/J51) | L51: =K51 | M51: Exact company email match
A52: Bianka@WearCheckRS.com | B52: Bianka De Beer | C52: RS | D52: WEC142 | E52: Matched | F52: No | G52: Microsoft Power Apps Plan 2 Trial | H52: Likely free / trial | I52: =IFERROR(VLOOKUP(G52,SKU_Cost_Input!$A$2:$E$16,4,FALSE),0) | J52: =IFERROR(VLOOKUP(G52,SKU_Cost_Input!$A$2:$E$16,2,FALSE),0) | K52: =IF(J52=0,0,I52/J52) | L52: =K52 | M52: Exact company email match
A53: Bianka@WearCheckRS.com | B53: Bianka De Beer | C53: RS | D53: WEC142 | E53: Matched | F53: No | G53: Microsoft Fabric (Free) | H53: Likely free / trial | I53: =IFERROR(VLOOKUP(G53,SKU_Cost_Input!$A$2:$E$16,4,FALSE),0) | J53: =IFERROR(VLOOKUP(G53,SKU_Cost_Input!$A$2:$E$16,2,FALSE),0) | K53: =IF(J53=0,0,I53/J53) | L53: =K53 | M53: Exact company email match
A54: Bianka@WearCheckRS.com | B54: Bianka De Beer | C54: RS | D54: WEC142 | E54: Matched | F54: No | G54: Microsoft Copilot Studio Viral Trial | H54: Likely free / trial | I54: =IFERROR(VLOOKUP(G54,SKU_Cost_Input!$A$2:$E$16,4,FALSE),0) | J54: =IFERROR(VLOOKUP(G54,SKU_Cost_Input!$A$2:$E$16,2,FALSE),0) | K54: =IF(J54=0,0,I54/J54) | L54: =K54 | M54: Exact company email match
A55: Bianka@WearCheckRS.com | B55: Bianka De Beer | C55: RS | D55: WEC142 | E55: Matched | F55: No | G55: Microsoft Power Apps for Developer | H55: Likely billable | I55: =IFERROR(VLOOKUP(G55,SKU_Cost_Input!$A$2:$E$16,4,FALSE),0) | J55: =IFERROR(VLOOKUP(G55,SKU_Cost_Input!$A$2:$E$16,2,FALSE),0) | K55: =IF(J55=0,0,I55/J55) | L55: =K55 | M55: Exact company email match
A56: Bianka@WearCheckRS.com | B56: Bianka De Beer | C56: RS | D56: WEC142 | E56: Matched | F56: No | G56: Power Pages vTrial for Makers | H56: Likely free / trial | I56: =IFERROR(VLOOKUP(G56,SKU_Cost_Input!$A$2:$E$16,4,FALSE),0) | J56: =IFERROR(VLOOKUP(G56,SKU_Cost_Input!$A$2:$E$16,2,FALSE),0) | K56: =IF(J56=0,0,I56/J56) | L56: =K56 | M56: Exact company email match
A57: Bianka@WearCheckRS.com | B57: Bianka De Beer | C57: RS | D57: WEC142 | E57: Matched | F57: No | G57: Microsoft Defender for Office 365 (Plan 2) | H57: Likely billable | I57: =IFERROR(VLOOKUP(G57,SKU_Cost_Input!$A$2:$E$16,4,FALSE),0) | J57: =IFERROR(VLOOKUP(G57,SKU_Cost_Input!$A$2:$E$16,2,FALSE),0) | K57: =IF(J57=0,0,I57/J57) | L57: =K57 | M57: Exact company email match
A58: Bianka@WearCheckRS.com | B58: Bianka De Beer | C58: RS | D58: WEC142 | E58: Matched | F58: No | G58: Dynamics 365 Customer Insights Self-Service | H58: Likely billable | I58: =IFERROR(VLOOKUP(G58,SKU_Cost_Input!$A$2:$E$16,4,FALSE),0) | J58: =IFERROR(VLOOKUP(G58,SKU_Cost_Input!$A$2:$E$16,2,FALSE),0) | K58: =IF(J58=0,0,I58/J58) | L58: =K58 | M58: Exact company email match
A59: Bianka@WearCheckRS.com | B59: Bianka De Beer | C59: RS | D59: WEC142 | E59: Matched | F59: No | G59: Microsoft 365 Business Premium | H59: Likely billable | I59: =IFERROR(VLOOKUP(G59,SKU_Cost_Input!$A$2:$E$16,4,FALSE),0) | J59: =IFERROR(VLOOKUP(G59,SKU_Cost_Input!$A$2:$E$16,2,FALSE),0) | K59: =IF(J59=0,0,I59/J59) | L59: =K59 | M59: Exact company email match | N59: Review: Business Premium — consider Business Basic/Standard
A60: Boitumelo@WearCheckRS.com | B60: Boitumelo Makgamatha | C60: RS | E60: Confirmed | F60: No | G60: Microsoft Defender for Office 365 (Plan 2) | H60: Likely billable | I60: =IFERROR(VLOOKUP(G60,SKU_Cost_Input!$A$2:$E$16,4,FALSE),0) | J60: =IFERROR(VLOOKUP(G60,SKU_Cost_Input!$A$2:$E$16,2,FALSE),0) | K60: =IF(J60=0,0,I60/J60) | L60: =K60 | M60: User now added to employee master (reviewed)
A61: Boitumelo@WearCheckRS.com | B61: Boitumelo Makgamatha | C61: RS | E61: Confirmed | F61: No | G61: Microsoft 365 Business Standard | H61: Likely billable | I61: =IFERROR(VLOOKUP(G61,SKU_Cost_Input!$A$2:$E$16,4,FALSE),0) | J61: =IFERROR(VLOOKUP(G61,SKU_Cost_Input!$A$2:$E$16,2,FALSE),0) | K61: =IF(J61=0,0,I61/J61) | L61: =K61 | M61: User now added to employee master (reviewed) | N61: Review: Business Standard — consider Business Basic if sufficient
A62: chicco@WearCheckRS.com | B62: Chicco Tivane | C62: RS | D62: WC380 | E62: Matched | F62: No | G62: Microsoft Defender for Office 365 (Plan 2) | H62: Likely billable | I62: =IFERROR(VLOOKUP(G62,SKU_Cost_Input!$A$2:$E$16,4,FALSE),0) | J62: =IFERROR(VLOOKUP(G62,SKU_Cost_Input!$A$2:$E$16,2,FALSE),0) | K62: =IF(J62=0,0,I62/J62) | L62: =K62 | M62: Exact company email match
A63: chicco@WearCheckRS.com | B63: Chicco Tivane | C63: RS | D63: WC380 | E63: Matched | F63: No | G63: Microsoft 365 Business Standard | H63: Likely billable | I63: =IFERROR(VLOOKUP(G63,SKU_Cost_Input!$A$2:$E$16,4,FALSE),0) | J63: =IFERROR(VLOOKUP(G63,SKU_Cost_Input!$A$2:$E$16,2,FALSE),0) | K63: =IF(J63=0,0,I63/J63) | L63: =K63 | M63: Exact company email match | N63: Review: Business Standard — consider Business Basic if sufficient
A64: ChrisM@wearcheckrs.com | B64: Chris Mostert | C64: RS | D64: WEC100 | E64: Matched | F64: No | G64: Microsoft Defender for Office 365 (Plan 2) | H64: Likely billable | I64: =IFERROR(VLOOKUP(G64,SKU_Cost_Input!$A$2:$E$16,4,FALSE),0) | J64: =IFERROR(VLOOKUP(G64,SKU_Cost_Input!$A$2:$E$16,2,FALSE),0) | K64: =IF(J64=0,0,I64/J64) | L64: =K64 | M64: Exact company email match
A65: ChrisM@wearcheckrs.com | B65: Chris Mostert | C65: RS | D65: WEC100 | E65: Matched | F65: No | G65: Microsoft 365 Business Standard | H65: Likely billable | I65: =IFERROR(VLOOKUP(G65,SKU_Cost_Input!$A$2:$E$16,4,FALSE),0) | J65: =IFERROR(VLOOKUP(G65,SKU_Cost_Input!$A$2:$E$16,2,FALSE),0) | K65: =IF(J65=0,0,I65/J65) | L65: =K65 | M65: Exact company email match | N65: Review: Business Standard — consider Business Basic if sufficient
A66: Christene@WearCheckRS.com | B66: Christene Fourie | C66: RS | E66: Confirmed | F66: No | G66: Microsoft Defender for Office 365 (Plan 2) | H66: Likely billable | I66: =IFERROR(VLOOKUP(G66,SKU_Cost_Input!$A$2:$E$16,4,FALSE),0) | J66: =IFERROR(VLOOKUP(G66,SKU_Cost_Input!$A$2:$E$16,2,FALSE),0) | K66: =IF(J66=0,0,I66/J66) | L66: =K66 | M66: Confirmed email alias match to chrstene@wearcheckrs.com (reviewed)
A67: Christene@WearCheckRS.com | B67: Christene Fourie | C67: RS | E67: Confirmed | F67: No | G67: Microsoft Power Automate Free | H67: Likely free / trial | I67: =IFERROR(VLOOKUP(G67,SKU_Cost_Input!$A$2:$E$16,4,FALSE),0) | J67: =IFERROR(VLOOKUP(G67,SKU_Cost_Input!$A$2:$E$16,2,FALSE),0) | K67: =IF(J67=0,0,I67/J67) | L67: =K67 | M67: Confirmed email alias match to chrstene@wearcheckrs.com (reviewed)
A68: Christene@WearCheckRS.com | B68: Christene Fourie | C68: RS | E68: Confirmed | F68: No | G68: Microsoft 365 Business Standard | H68: Likely billable | I68: =IFERROR(VLOOKUP(G68,SKU_Cost_Input!$A$2:$E$16,4,FALSE),0) | J68: =IFERROR(VLOOKUP(G68,SKU_Cost_Input!$A$2:$E$16,2,FALSE),0) | K68: =IF(J68=0,0,I68/J68) | L68: =K68 | M68: Confirmed email alias match to chrstene@wearcheckrs.com (reviewed) | N68: Review: Business Standard — consider Business Basic if sufficient
A69: Christian@WearCheckRS.com | B69: Christian Geel | C69: RS | E69: Ex-Employee | F69: No | G69: Microsoft Fabric (Free) | H69: Likely free / trial | I69: =IFERROR(VLOOKUP(G69,SKU_Cost_Input!$A$2:$E$16,4,FALSE),0) | J69: =IFERROR(VLOOKUP(G69,SKU_Cost_Input!$A$2:$E$16,2,FALSE),0) | K69: =IF(J69=0,0,I69/J69) | L69: =K69 | M69: No longer an employee. FLAG: Remove licence.
A70: Christian@WearCheckRS.com | B70: Christian Geel | C70: RS | E70: Ex-Employee | F70: No | G70: Microsoft Power Automate Free | H70: Likely free / trial | I70: =IFERROR(VLOOKUP(G70,SKU_Cost_Input!$A$2:$E$16,4,FALSE),0) | J70: =IFERROR(VLOOKUP(G70,SKU_Cost_Input!$A$2:$E$16,2,FALSE),0) | K70: =IF(J70=0,0,I70/J70) | L70: =K70 | M70: No longer an employee. FLAG: Remove licence.
A71: christie.samancor@WearCheckRS.com | B71: Christie | C71: RS | E71: Management Review | F71: Yes | G71: Microsoft Fabric (Free) | H71: Likely free / trial | I71: =IFERROR(VLOOKUP(G71,SKU_Cost_Input!$A$2:$E$16,4,FALSE),0) | J71: =IFERROR(VLOOKUP(G71,SKU_Cost_Input!$A$2:$E$16,2,FALSE),0) | K71: =IF(J71=0,0,I71/J71) | L71: =K71 | M71: Not an employee — has free Fabric licence only. Flagged for management review.
A72: cj@WearCheckRS.com | B72: CJ Woller | C72: RS | D72: WEC120 | E72: Matched | F72: No | G72: Microsoft Defender for Office 365 (Plan 2) | H72: Likely billable | I72: =IFERROR(VLOOKUP(G72,SKU_Cost_Input!$A$2:$E$16,4,FALSE),0) | J72: =IFERROR(VLOOKUP(G72,SKU_Cost_Input!$A$2:$E$16,2,FALSE),0) | K72: =IF(J72=0,0,I72/J72) | L72: =K72 | M72: Exact company email match
A73: cj@WearCheckRS.com | B73: CJ Woller | C73: RS | D73: WEC120 | E73: Matched | F73: No | G73: Microsoft Power Automate Free | H73: Likely free / trial | I73: =IFERROR(VLOOKUP(G73,SKU_Cost_Input!$A$2:$E$16,4,FALSE),0) | J73: =IFERROR(VLOOKUP(G73,SKU_Cost_Input!$A$2:$E$16,2,FALSE),0) | K73: =IF(J73=0,0,I73/J73) | L73: =K73 | M73: Exact company email match
A74: cj@WearCheckRS.com | B74: CJ Woller | C74: RS | D74: WEC120 | E74: Matched | F74: No | G74: Microsoft 365 Business Standard | H74: Likely billable | I74: =IFERROR(VLOOKUP(G74,SKU_Cost_Input!$A$2:$E$16,4,FALSE),0) | J74: =IFERROR(VLOOKUP(G74,SKU_Cost_Input!$A$2:$E$16,2,FALSE),0) | K74: =IF(J74=0,0,I74/J74) | L74: =K74 | M74: Exact company email match | N74: Review: Business Standard — consider Business Basic if sufficient
A75: colleen.pyper@WearCheckRS.com | B75: Colleen Pyper | C75: AFS | D75: WC486 | E75: Matched | F75: No | G75: Microsoft Defender for Office 365 (Plan 2) | H75: Likely billable | I75: =IFERROR(VLOOKUP(G75,SKU_Cost_Input!$A$2:$E$16,4,FALSE),0) | J75: =IFERROR(VLOOKUP(G75,SKU_Cost_Input!$A$2:$E$16,2,FALSE),0) | K75: =IF(J75=0,0,I75/J75) | L75: =K75 | M75: Exact company email match
A76: colleen.pyper@WearCheckRS.com | B76: Colleen Pyper | C76: AFS | D76: WC486 | E76: Matched | F76: No | G76: Microsoft Power Automate Free | H76: Likely free / trial | I76: =IFERROR(VLOOKUP(G76,SKU_Cost_Input!$A$2:$E$16,4,FALSE),0) | J76: =IFERROR(VLOOKUP(G76,SKU_Cost_Input!$A$2:$E$16,2,FALSE),0) | K76: =IF(J76=0,0,I76/J76) | L76: =K76 | M76: Exact company email match
A77: colleen.pyper@WearCheckRS.com | B77: Colleen Pyper | C77: AFS | D77: WC486 | E77: Matched | F77: No | G77: Microsoft 365 Business Standard | H77: Likely billable | I77: =IFERROR(VLOOKUP(G77,SKU_Cost_Input!$A$2:$E$16,4,FALSE),0) | J77: =IFERROR(VLOOKUP(G77,SKU_Cost_Input!$A$2:$E$16,2,FALSE),0) | K77: =IF(J77=0,0,I77/J77) | L77: =K77 | M77: Exact company email match | N77: Review: Business Standard — consider Business Basic if sufficient
A78: daniel@WearCheckRS.com | B78: Daniel Molapo | C78: RS | D78: WC402 | E78: Matched | F78: No | G78: Microsoft Defender for Office 365 (Plan 2) | H78: Likely billable | I78: =IFERROR(VLOOKUP(G78,SKU_Cost_Input!$A$2:$E$16,4,FALSE),0) | J78: =IFERROR(VLOOKUP(G78,SKU_Cost_Input!$A$2:$E$16,2,FALSE),0) | K78: =IF(J78=0,0,I78/J78) | L78: =K78 | M78: Exact company email match
A79: daniel@WearCheckRS.com | B79: Daniel Molapo | C79: RS | D79: WC402 | E79: Matched | F79: No | G79: Microsoft 365 E3 | H79: Likely billable | I79: =IFERROR(VLOOKUP(G79,SKU_Cost_Input!$A$2:$E$16,4,FALSE),0) | J79: =IFERROR(VLOOKUP(G79,SKU_Cost_Input!$A$2:$E$16,2,FALSE),0) | K79: =IF(J79=0,0,I79/J79) | L79: =K79 | M79: Exact company email match | N79: Review: E3 may be downgradeable to E1 or Business Basic
A80: daniel@WearCheckRS.com | B80: Daniel Molapo | C80: RS | D80: WC402 | E80: Matched | F80: No | G80: Microsoft Fabric (Free) | H80: Likely free / trial | I80: =IFERROR(VLOOKUP(G80,SKU_Cost_Input!$A$2:$E$16,4,FALSE),0) | J80: =IFERROR(VLOOKUP(G80,SKU_Cost_Input!$A$2:$E$16,2,FALSE),0) | K80: =IF(J80=0,0,I80/J80) | L80: =K80 | M80: Exact company email match
A81: daniel@WearCheckRS.com | B81: Daniel Molapo | C81: RS | D81: WC402 | E81: Matched | F81: No | G81: Microsoft Power Automate Free | H81: Likely free / trial | I81: =IFERROR(VLOOKUP(G81,SKU_Cost_Input!$A$2:$E$16,4,FALSE),0) | J81: =IFERROR(VLOOKUP(G81,SKU_Cost_Input!$A$2:$E$16,2,FALSE),0) | K81: =IF(J81=0,0,I81/J81) | L81: =K81 | M81: Exact company email match
A82: DavidL@WearCheckRS.com | B82: David Lipange | C82: Mozambique | D82: Unknown | E82: Matched | F82: No | G82: Microsoft Defender for Office 365 (Plan 2) | H82: Likely billable | I82: =IFERROR(VLOOKUP(G82,SKU_Cost_Input!$A$2:$E$16,4,FALSE),0) | J82: =IFERROR(VLOOKUP(G82,SKU_Cost_Input!$A$2:$E$16,2,FALSE),0) | K82: =IF(J82=0,0,I82/J82) | L82: =K82 | M82: Exact company email match
A83: DavidL@WearCheckRS.com | B83: David Lipange | C83: Mozambique | D83: Unknown | E83: Matched | F83: No | G83: Microsoft Fabric (Free) | H83: Likely free / trial | I83: =IFERROR(VLOOKUP(G83,SKU_Cost_Input!$A$2:$E$16,4,FALSE),0) | J83: =IFERROR(VLOOKUP(G83,SKU_Cost_Input!$A$2:$E$16,2,FALSE),0) | K83: =IF(J83=0,0,I83/J83) | L83: =K83 | M83: Exact company email match
A84: DavidL@WearCheckRS.com | B84: David Lipange | C84: Mozambique | D84: Unknown | E84: Matched | F84: No | G84: Microsoft 365 Business Standard | H84: Likely billable | I84: =IFERROR(VLOOKUP(G84,SKU_Cost_Input!$A$2:$E$16,4,FALSE),0) | J84: =IFERROR(VLOOKUP(G84,SKU_Cost_Input!$A$2:$E$16,2,FALSE),0) | K84: =IF(J84=0,0,I84/J84) | L84: =K84 | M84: Exact company email match | N84: Review: Business Standard — consider Business Basic if sufficient
A85: David@WearCheckRS.com | B85: David Viljoen | C85: RS | D85: WEC081 | E85: Matched | F85: No | G85: Microsoft Defender for Office 365 (Plan 2) | H85: Likely billable | I85: =IFERROR(VLOOKUP(G85,SKU_Cost_Input!$A$2:$E$16,4,FALSE),0) | J85: =IFERROR(VLOOKUP(G85,SKU_Cost_Input!$A$2:$E$16,2,FALSE),0) | K85: =IF(J85=0,0,I85/J85) | L85: =K85 | M85: Exact company email match
A86: David@WearCheckRS.com | B86: David Viljoen | C86: RS | D86: WEC081 | E86: Matched | F86: No | G86: Microsoft Fabric (Free) | H86: Likely free / trial | I86: =IFERROR(VLOOKUP(G86,SKU_Cost_Input!$A$2:$E$16,4,FALSE),0) | J86: =IFERROR(VLOOKUP(G86,SKU_Cost_Input!$A$2:$E$16,2,FALSE),0) | K86: =IF(J86=0,0,I86/J86) | L86: =K86 | M86: Exact company email match
A87: David@WearCheckRS.com | B87: David Viljoen | C87: RS | D87: WEC081 | E87: Matched | F87: No | G87: Microsoft 365 Business Standard | H87: Likely billable | I87: =IFERROR(VLOOKUP(G87,SKU_Cost_Input!$A$2:$E$16,4,FALSE),0) | J87: =IFERROR(VLOOKUP(G87,SKU_Cost_Input!$A$2:$E$16,2,FALSE),0) | K87: =IF(J87=0,0,I87/J87) | L87: =K87 | M87: Exact company email match | N87: Review: Business Standard — consider Business Basic if sufficient
A88: David@WearCheckRS.com | B88: David Viljoen | C88: RS | D88: WEC081 | E88: Matched | F88: No | G88: Microsoft Power Automate Free | H88: Likely free / trial | I88: =IFERROR(VLOOKUP(G88,SKU_Cost_Input!$A$2:$E$16,4,FALSE),0) | J88: =IFERROR(VLOOKUP(G88,SKU_Cost_Input!$A$2:$E$16,2,FALSE),0) | K88: =IF(J88=0,0,I88/J88) | L88: =K88 | M88: Exact company email match
A89: Deon@WearCheckRS.com | B89: Deon Gaarkeuken | C89: RS | D89: WC358 | E89: Matched | F89: No | G89: Microsoft Defender for Office 365 (Plan 2) | H89: Likely billable | I89: =IFERROR(VLOOKUP(G89,SKU_Cost_Input!$A$2:$E$16,4,FALSE),0) | J89: =IFERROR(VLOOKUP(G89,SKU_Cost_Input!$A$2:$E$16,2,FALSE),0) | K89: =IF(J89=0,0,I89/J89) | L89: =K89 | M89: Exact company email match
A90: Deon@WearCheckRS.com | B90: Deon Gaarkeuken | C90: RS | D90: WC358 | E90: Matched | F90: No | G90: Power BI Premium Per User | H90: Likely billable | I90: =IFERROR(VLOOKUP(G90,SKU_Cost_Input!$A$2:$E$16,4,FALSE),0) | J90: =IFERROR(VLOOKUP(G90,SKU_Cost_Input!$A$2:$E$16,2,FALSE),0) | K90: =IF(J90=0,0,I90/J90) | L90: =K90 | M90: Exact company email match
A91: Deon@WearCheckRS.com | B91: Deon Gaarkeuken | C91: RS | D91: WC358 | E91: Matched | F91: No | G91: Microsoft 365 E3 | H91: Likely billable | I91: =IFERROR(VLOOKUP(G91,SKU_Cost_Input!$A$2:$E$16,4,FALSE),0) | J91: =IFERROR(VLOOKUP(G91,SKU_Cost_Input!$A$2:$E$16,2,FALSE),0) | K91: =IF(J91=0,0,I91/J91) | L91: =K91 | M91: Exact company email match | N91: Review: E3 may be downgradeable to E1 or Business Basic
A92: Deon@WearCheckRS.com | B92: Deon Gaarkeuken | C92: RS | D92: WC358 | E92: Matched | F92: No | G92: Microsoft Fabric (Free) | H92: Likely free / trial | I92: =IFERROR(VLOOKUP(G92,SKU_Cost_Input!$A$2:$E$16,4,FALSE),0) | J92: =IFERROR(VLOOKUP(G92,SKU_Cost_Input!$A$2:$E$16,2,FALSE),0) | K92: =IF(J92=0,0,I92/J92) | L92: =K92 | M92: Exact company email match
A93: Deon@WearCheckRS.com | B93: Deon Gaarkeuken | C93: RS | D93: WC358 | E93: Matched | F93: No | G93: Microsoft Power Automate Free | H93: Likely free / trial | I93: =IFERROR(VLOOKUP(G93,SKU_Cost_Input!$A$2:$E$16,4,FALSE),0) | J93: =IFERROR(VLOOKUP(G93,SKU_Cost_Input!$A$2:$E$16,2,FALSE),0) | K93: =IF(J93=0,0,I93/J93) | L93: =K93 | M93: Exact company email match
A94: desmond@WearCheckRS.com | B94: Desmond Ngomane | C94: RS | D94: WEC086 | E94: Matched | F94: No | G94: Microsoft Defender for Office 365 (Plan 2) | H94: Likely billable | I94: =IFERROR(VLOOKUP(G94,SKU_Cost_Input!$A$2:$E$16,4,FALSE),0) | J94: =IFERROR(VLOOKUP(G94,SKU_Cost_Input!$A$2:$E$16,2,FALSE),0) | K94: =IF(J94=0,0,I94/J94) | L94: =K94 | M94: Exact company email match
A95: desmond@WearCheckRS.com | B95: Desmond Ngomane | C95: RS | D95: WEC086 | E95: Matched | F95: No | G95: Microsoft Fabric (Free) | H95: Likely free / trial | I95: =IFERROR(VLOOKUP(G95,SKU_Cost_Input!$A$2:$E$16,4,FALSE),0) | J95: =IFERROR(VLOOKUP(G95,SKU_Cost_Input!$A$2:$E$16,2,FALSE),0) | K95: =IF(J95=0,0,I95/J95) | L95: =K95 | M95: Exact company email match
A96: desmond@WearCheckRS.com | B96: Desmond Ngomane | C96: RS | D96: WEC086 | E96: Matched | F96: No | G96: Microsoft 365 Business Standard | H96: Likely billable | I96: =IFERROR(VLOOKUP(G96,SKU_Cost_Input!$A$2:$E$16,4,FALSE),0) | J96: =IFERROR(VLOOKUP(G96,SKU_Cost_Input!$A$2:$E$16,2,FALSE),0) | K96: =IF(J96=0,0,I96/J96) | L96: =K96 | M96: Exact company email match | N96: Review: Business Standard — consider Business Basic if sufficient
A97: dian@WearCheckRS.com | B97: Dian Leff | C97: Namibia | D97: WCN008 | E97: Matched | F97: No | G97: Microsoft Defender for Office 365 (Plan 2) | H97: Likely billable | I97: =IFERROR(VLOOKUP(G97,SKU_Cost_Input!$A$2:$E$16,4,FALSE),0) | J97: =IFERROR(VLOOKUP(G97,SKU_Cost_Input!$A$2:$E$16,2,FALSE),0) | K97: =IF(J97=0,0,I97/J97) | L97: =K97 | M97: Exact company email match
A98: dian@WearCheckRS.com | B98: Dian Leff | C98: Namibia | D98: WCN008 | E98: Matched | F98: No | G98: Microsoft 365 Business Standard | H98: Likely billable | I98: =IFERROR(VLOOKUP(G98,SKU_Cost_Input!$A$2:$E$16,4,FALSE),0) | J98: =IFERROR(VLOOKUP(G98,SKU_Cost_Input!$A$2:$E$16,2,FALSE),0) | K98: =IF(J98=0,0,I98/J98) | L98: =K98 | M98: Exact company email match | N98: Review: Business Standard — consider Business Basic if sufficient
A99: douglas@WearCheckRS.com | B99: Douglas Prout-Jones | C99: RS | D99: WEC119 | E99: Matched | F99: No | G99: Microsoft Defender for Office 365 (Plan 2) | H99: Likely billable | I99: =IFERROR(VLOOKUP(G99,SKU_Cost_Input!$A$2:$E$16,4,FALSE),0) | J99: =IFERROR(VLOOKUP(G99,SKU_Cost_Input!$A$2:$E$16,2,FALSE),0) | K99: =IF(J99=0,0,I99/J99) | L99: =K99 | M99: Exact company email match
A100: douglas@WearCheckRS.com | B100: Douglas Prout-Jones | C100: RS | D100: WEC119 | E100: Matched | F100: No | G100: Microsoft Power Automate Free | H100: Likely free / trial | I100: =IFERROR(VLOOKUP(G100,SKU_Cost_Input!$A$2:$E$16,4,FALSE),0) | J100: =IFERROR(VLOOKUP(G100,SKU_Cost_Input!$A$2:$E$16,2,FALSE),0) | K100: =IF(J100=0,0,I100/J100) | L100: =K100 | M100: Exact company email match
...

Sheet Allocation_Pivot
A1: Clean Allocation Table: Division x SKU
A2: Cost values update automatically from SKU_Cost_Input
A4: Division | B4: SKU | C4: Users | D4: Allocated Cost
A5: RS | B5: Microsoft Defender for Office 365 (Plan 2) | C5: =COUNTIFS(Allocation_Detail!$C$2:$C$406,A5,Allocation_Detail!$G$2:$G$406,B5) | D5: =SUMIFS(Allocation_Detail!$L$2:$L$406,Allocation_Detail!$C$2:$C$406,A5,Allocation_Detail!$G$2:$G$406,B5)
A6: RS | B6: Microsoft 365 Business Standard | C6: =COUNTIFS(Allocation_Detail!$C$2:$C$406,A6,Allocation_Detail!$G$2:$G$406,B6) | D6: =SUMIFS(Allocation_Detail!$L$2:$L$406,Allocation_Detail!$C$2:$C$406,A6,Allocation_Detail!$G$2:$G$406,B6)
A7: RS | B7: Microsoft Power Automate Free | C7: =COUNTIFS(Allocation_Detail!$C$2:$C$406,A7,Allocation_Detail!$G$2:$G$406,B7) | D7: =SUMIFS(Allocation_Detail!$L$2:$L$406,Allocation_Detail!$C$2:$C$406,A7,Allocation_Detail!$G$2:$G$406,B7)
A8: RS | B8: Microsoft Fabric (Free) | C8: =COUNTIFS(Allocation_Detail!$C$2:$C$406,A8,Allocation_Detail!$G$2:$G$406,B8) | D8: =SUMIFS(Allocation_Detail!$L$2:$L$406,Allocation_Detail!$C$2:$C$406,A8,Allocation_Detail!$G$2:$G$406,B8)
A9: RS | B9: Microsoft 365 Business Premium | C9: =COUNTIFS(Allocation_Detail!$C$2:$C$406,A9,Allocation_Detail!$G$2:$G$406,B9) | D9: =SUMIFS(Allocation_Detail!$L$2:$L$406,Allocation_Detail!$C$2:$C$406,A9,Allocation_Detail!$G$2:$G$406,B9)
A10: RS | B10: Microsoft 365 E3 | C10: =COUNTIFS(Allocation_Detail!$C$2:$C$406,A10,Allocation_Detail!$G$2:$G$406,B10) | D10: =SUMIFS(Allocation_Detail!$L$2:$L$406,Allocation_Detail!$C$2:$C$406,A10,Allocation_Detail!$G$2:$G$406,B10)
A11: RS | B11: Microsoft Copilot Studio Viral Trial | C11: =COUNTIFS(Allocation_Detail!$C$2:$C$406,A11,Allocation_Detail!$G$2:$G$406,B11) | D11: =SUMIFS(Allocation_Detail!$L$2:$L$406,Allocation_Detail!$C$2:$C$406,A11,Allocation_Detail!$G$2:$G$406,B11)
A12: RS | B12: Microsoft Power Apps Plan 2 Trial | C12: =COUNTIFS(Allocation_Detail!$C$2:$C$406,A12,Allocation_Detail!$G$2:$G$406,B12) | D12: =SUMIFS(Allocation_Detail!$L$2:$L$406,Allocation_Detail!$C$2:$C$406,A12,Allocation_Detail!$G$2:$G$406,B12)
A13: RS | B13: Microsoft Power Apps for Developer | C13: =COUNTIFS(Allocation_Detail!$C$2:$C$406,A13,Allocation_Detail!$G$2:$G$406,B13) | D13: =SUMIFS(Allocation_Detail!$L$2:$L$406,Allocation_Detail!$C$2:$C$406,A13,Allocation_Detail!$G$2:$G$406,B13)
A14: RS | B14: Power BI Premium Per User | C14: =COUNTIFS(Allocation_Detail!$C$2:$C$406,A14,Allocation_Detail!$G$2:$G$406,B14) | D14: =SUMIFS(Allocation_Detail!$L$2:$L$406,Allocation_Detail!$C$2:$C$406,A14,Allocation_Detail!$G$2:$G$406,B14)
A15: RS | B15: Power Pages vTrial for Makers | C15: =COUNTIFS(Allocation_Detail!$C$2:$C$406,A15,Allocation_Detail!$G$2:$G$406,B15) | D15: =SUMIFS(Allocation_Detail!$L$2:$L$406,Allocation_Detail!$C$2:$C$406,A15,Allocation_Detail!$G$2:$G$406,B15)
A16: RS | B16: Exchange Online (Plan 1) | C16: =COUNTIFS(Allocation_Detail!$C$2:$C$406,A16,Allocation_Detail!$G$2:$G$406,B16) | D16: =SUMIFS(Allocation_Detail!$L$2:$L$406,Allocation_Detail!$C$2:$C$406,A16,Allocation_Detail!$G$2:$G$406,B16)
... A64: Mozambique | B64: Power Automate per user plan | C64: =COUNTIFS(Allocation_Detail!$C$2:$C$406,A64,Allocation_Detail!$G$2:$G$406,B64) | D64: =SUMIFS(Allocation_Detail!$L$2:$L$406,Allocation_Detail!$C$2:$C$406,A64,Allocation_Detail!$G$2:$G$406,B64)
A65: TOTAL | C65: =SUM(C5:C64) | D65: =SUM(D5:D64)

Sheet Division_Summary
A1: Microsoft License Allocation Summary
A2: =Invoice_Input!B4
A3: Enter monthly invoice amounts on SKU_Cost_Input. Values update automatically.
A5: KPI | B5: Value
A6: Billing Period | B6: =Invoice_Input!B4
A7: Licensed accounts in export | B7: 147
A8: Matched to cost centre (High) | B8: =COUNTIF(User_Match!$H$2:$H$148,"High")
A9: Accounts needing review | B9: =COUNTIF(User_Match!$I$2:$I$148,"Yes")
A10: Invoice Total (excl VAT) | B10: =Invoice_Input!B11
A11: VAT Amount | B11: =SKU_Cost_Input!F17
A12: Invoice Total (incl VAT) | B12: =Invoice_Input!B9
A13: Allocated Total (excl VAT) | B13: =SKU_Cost_Input!D17
A14: Reconciliation Status | B14: =Invoice_Input!B19
A15: SKU Qty Discrepancies (Invoice vs Admin) | B15: 5
A16: Total Tenant Accounts (CSV) | B16: 842
A17: Licensed Users (CSV) | B17: 147
A18: Unlicensed Accounts | B18: 641
A19: Soft-Deleted Accounts | B19: 54
A20: Unassigned Paid Licences (total) | B20: 7
A21: Wasted Monthly Spend (excl VAT) | B21: 1994.21
A22: COITE Queries Raised | B22: 6
A23: Ex-Employee Licences (remove) | B23: =COUNTIF(User_Match!$J$2:$J$148,"Ex-Employee")
A24: Contractor Licences | B24: =COUNTIF(User_Match!$J$2:$J$148,"Contractor")
A27: Division | B27: Licensed Accounts | C27: Review Accounts | D27: SKU Assignments | E27: Allocated Monthly Cost (excl VAT) | F27: % of Total Cost
A28: RS | B28: =COUNTIF(User_Match!$F$2:$F$148,A28) | C28: =COUNTIFS(User_Match!$F$2:$F$148,A28,User_Match!$I$2:$I$148,"Yes") | D28: =COUNTIF(Allocation_Detail!$C$2:$C$406,A28) | E28: =SUMIF(Allocation_Detail!$C$2:$C$406,A28,Allocation_Detail!$L$2:$L$406) | F28: =IF(E32=0,0,E28/E32)
A29: AFS | B29: =COUNTIF(User_Match!$F$2:$F$148,A29) | C29: =COUNTIFS(User_Match!$F$2:$F$148,A29,User_Match!$I$2:$I$148,"Yes") | D29: =COUNTIF(Allocation_Detail!$C$2:$C$406,A29) | E29: =SUMIF(Allocation_Detail!$C$2:$C$406,A29,Allocation_Detail!$L$2:$L$406) | F29: =IF(E32=0,0,E29/E32)
A30: Namibia | B30: =COUNTIF(User_Match!$F$2:$F$148,A30) | C30: =COUNTIFS(User_Match!$F$2:$F$148,A30,User_Match!$I$2:$I$148,"Yes") | D30: =COUNTIF(Allocation_Detail!$C$2:$C$406,A30) | E30: =SUMIF(Allocation_Detail!$C$2:$C$406,A30,Allocation_Detail!$L$2:$L$406) | F30: =IF(E32=0,0,E30/E32)
A31: Mozambique | B31: =COUNTIF(User_Match!$F$2:$F$148,A31) | C31: =COUNTIFS(User_Match!$F$2:$F$148,A31,User_Match!$I$2:$I$148,"Yes") | D31: =COUNTIF(Allocation_Detail!$C$2:$C$406,A31) | E31: =SUMIF(Allocation_Detail!$C$2:$C$406,A31,Allocation_Detail!$L$2:$L$406) | F31: =IF(E32=0,0,E31/E32)
A32: TOTAL | B32: =SUM(B28:B31) | C32: =SUM(C28:C31) | D32: =SUM(D28:D31) | E32: =SUM(E28:E31) | F32: =IF(E32=0,0,E32/E32)
A35: SKU Cost Breakdown
A36: SKU | B36: Active Users | C36: Invoice Amount (excl VAT) | D36: Unit Cost Per User | E36: VAT Amount | F36: Total incl VAT
A37: Microsoft Defender for Office 365 (Plan 2) | B37: =SKU_Cost_Input!B2 | C37: =SKU_Cost_Input!D2 | D37: =SKU_Cost_Input!E2 | E37: =SKU_Cost_Input!F2 | F37: =SKU_Cost_Input!G2
A38: Microsoft 365 Business Standard | B38: =SKU_Cost_Input!B3 | C38: =SKU_Cost_Input!D3 | D38: =SKU_Cost_Input!E3 | E38: =SKU_Cost_Input!F3 | F38: =SKU_Cost_Input!G3
A39: Microsoft Power Automate Free | B39: =SKU_Cost_Input!B4 | C39: =SKU_Cost_Input!D4 | D39: =SKU_Cost_Input!E4 | E39: =SKU_Cost_Input!F4 | F39: =SKU_Cost_Input!G4
A40: Microsoft Fabric (Free) | B40: =SKU_Cost_Input!B5 | C40: =SKU_Cost_Input!D5 | D40: =SKU_Cost_Input!E5 | E40: =SKU_Cost_Input!F5 | F40: =SKU_Cost_Input!G5
A41: Microsoft 365 Business Premium | B41: =SKU_Cost_Input!B6 | C41: =SKU_Cost_Input!D6 | D41: =SKU_Cost_Input!E6 | E41: =SKU_Cost_Input!F6 | F41: =SKU_Cost_Input!G6
A42: Microsoft 365 E3 | B42: =SKU_Cost_Input!B7 | C42: =SKU_Cost_Input!D7 | D42: =SKU_Cost_Input!E7 | E42: =SKU_Cost_Input!F7 | F42: =SKU_Cost_Input!G7
A43: Microsoft Copilot Studio Viral Trial | B43: =SKU_Cost_Input!B8 | C43: =SKU_Cost_Input!D8 | D43: =SKU_Cost_Input!E8 | E43: =SKU_Cost_Input!F8 | F43: =SKU_Cost_Input!G8
A44: Microsoft Power Apps Plan 2 Trial | B44: =SKU_Cost_Input!B9 | C44: =SKU_Cost_Input!D9 | D44: =SKU_Cost_Input!E9 | E44: =SKU_Cost_Input!F9 | F44: =SKU_Cost_Input!G9
A45: Microsoft Power Apps for Developer | B45: =SKU_Cost_Input!B10 | C45: =SKU_Cost_Input!D10 | D45: =SKU_Cost_Input!E10 | E45: =SKU_Cost_Input!F10 | F45: =SKU_Cost_Input!G10
A46: Power BI Premium Per User | B46: =SKU_Cost_Input!B11 | C46: =SKU_Cost_Input!D11 | D46: =SKU_Cost_Input!E11 | E46: =SKU_Cost_Input!F11 | F46: =SKU_Cost_Input!G11
A47: Power Pages vTrial for Makers | B47: =SKU_Cost_Input!B12 | C47: =SKU_Cost_Input!D12 | D47: =SKU_Cost_Input!E12 | E47: =SKU_Cost_Input!F12 | F47: =SKU_Cost_Input!G12
A48: Exchange Online (Plan 1) | B48: =SKU_Cost_Input!B13 | C48: =SKU_Cost_Input!D13 | D48: =SKU_Cost_Input!E13 | E48: =SKU_Cost_Input!F13 | F48: =SKU_Cost_Input!G13
... A51: Power Automate per user plan | B51: =SKU_Cost_Input!B16 | C51: =SKU_Cost_Input!D16 | D51: =SKU_Cost_Input!E16 | E51: =SKU_Cost_Input!F16 | F51: =SKU_Cost_Input!G16
A53: Quantity Discrepancy: Invoice vs Admin Export
A54: These SKUs have different quantities on the invoice vs the Admin Centre export. Rectify before finalising.
A55: SKU | B55: Admin Users | C55: Invoice Qty | D55: Variance | E55: Impact | F55: Action Required
A56: Microsoft 365 Business Standard | B56: 100 | C56: 97 | D56: 3 | E56: Admin has 3 more — cost per user diluted below invoiced unit price | F56: Likely added after billing date. Will appear on next invoice.
A57: Microsoft 365 Business Premium | B57: 21 | C57: 23 | D57: -2 | E57: Invoice bills 2 more than admin — paying for removed user(s) | F57: User(s) removed after billing. Confirm with COITE/Microsoft.
A58: Microsoft 365 E3 | B58: 14 | C58: 15 | D58: -1 | E58: Invoice bills 1 more than admin — paying for removed user(s) | F58: User(s) removed after billing. Confirm with COITE/Microsoft.
A59: Power BI Premium Per User | B59: 6 | C59: 7 | D59: -1 | E59: Invoice bills 1 more than admin — paying for removed user(s) | F59: User(s) removed after billing. Confirm with COITE/Microsoft.
A60: Power Apps per app plan (1 app or website) | B60: 0 | C60: 3 | D60: -3 | E60: Invoice bills 3 more than admin — paying for removed user(s) | F60: User(s) removed after billing. Confirm with COITE/Microsoft.
A63: Audit Trail & Controls
A64: All costs trace: Microsoft Invoice (Invoice_Input) → SKU line items (SKU_Cost_Input) → Licensed Users (License_Raw) → Employee Mapping (User_Match) → Allocation (Allocation_Detail)
A65: Reconciliation: SKU excl-VAT total MUST equal invoice excl-VAT total. Any variance is flagged FAIL on Invoice_Input and above KPIs.
A66: VAT: Applied at total level via Invoice_Input rate. Individual SKU amounts are entered EXCLUDING VAT.
A67: Exchange Rate: If invoice is in USD, convert using the rate on Invoice_Input before entering SKU amounts in ZAR.
A68: Proration: Model uses a snapshot of users active at invoice date. Prorated amounts should be reflected in invoice line items.
A69: Unmatched users temporarily assigned to RS and flagged on Review_Queue for Finance confirmation.

Sheet Licence_Cleanup
A1: Licences Flagged for Removal / Management Review
A2: These users are no longer employees, are contractors, or need management review. Action: remove or reassign licences.
A4: Display Name | B4: Email | C4: User Status | D4: Licences Held | E4: Licence Count | F4: Est. Monthly Cost (excl VAT) | G4: Reason / Note | H4: Action Required
A5: Adri Ludick Old | B5: Adri.ludick@WearCheckRS.com | C5: Ex-Employee | D5: Microsoft Defender for Office 365 (Plan 2)+Microsoft Power Automate Free+Microsoft 365 Business Standard | E5: 3 | F5: =SUMIF(Allocation_Detail!$A$2:$A$406,B5,Allocation_Detail!$L$2:$L$406) | G5: Old account — new email A.Ludick@WearCheckRS.com is active. FLAG: Remove this licence. | H5: REMOVE LICENCE — no longer an employee
A6: Christian Geel | B6: Christian@WearCheckRS.com | C6: Ex-Employee | D6: Microsoft Fabric (Free)+Microsoft Power Automate Free | E6: 2 | F6: =SUMIF(Allocation_Detail!$A$2:$A$406,B6,Allocation_Detail!$L$2:$L$406) | G6: No longer an employee. FLAG: Remove licence. | H6: REMOVE LICENCE — no longer an employee
A7: Gladwin Sekharume | B7: GladwinS@WearCheckRS.com | C7: Ex-Employee | D7: Microsoft Defender for Office 365 (Plan 2)+Microsoft 365 Business Standard | E7: 2 | F7: =SUMIF(Allocation_Detail!$A$2:$A$406,B7,Allocation_Detail!$L$2:$L$406) | G7: No longer an employee. FLAG: Remove licence. | H7: REMOVE LICENCE — no longer an employee
A8: Ivan Langa | B8: Ivan@WearCheckRS.com | C8: Ex-Employee | D8: Microsoft Defender for Office 365 (Plan 2)+Microsoft Fabric (Free)+Microsoft 365 Business Standard | E8: 3 | F8: =SUMIF(Allocation_Detail!$A$2:$A$406,B8,Allocation_Detail!$L$2:$L$406) | G8: No longer an employee. FLAG: Remove licence. | H8: REMOVE LICENCE — no longer an employee
A9: Kenneth Moremi | B9: kenneth@WearCheckRS.com | C9: Ex-Employee | D9: Microsoft Defender for Office 365 (Plan 2)+Microsoft 365 Business Standard | E9: 2 | F9: =SUMIF(Allocation_Detail!$A$2:$A$406,B9,Allocation_Detail!$L$2:$L$406) | G9: No longer an employee. FLAG: Remove licence. | H9: REMOVE LICENCE — no longer an employee
A10: Kevin Jonker | B10: kevinj@WearCheckRS.com | C10: Ex-Employee | D10: Microsoft Fabric (Free)+Microsoft Power Automate Free | E10: 2 | F10: =SUMIF(Allocation_Detail!$A$2:$A$406,B10,Allocation_Detail!$L$2:$L$406) | G10: No longer an employee. FLAG: Remove licence. | H10: REMOVE LICENCE — no longer an employee
A11: Mandiso Muchanga | B11: Mandiso@WearCheckRS.com | C11: Ex-Employee | D11: Microsoft Defender for Office 365 (Plan 2)+Microsoft 365 Business Standard | E11: 2 | F11: =SUMIF(Allocation_Detail!$A$2:$A$406,B11,Allocation_Detail!$L$2:$L$406) | G11: No longer an employee. FLAG: Remove licence. | H11: REMOVE LICENCE — no longer an employee
A12: Martin Prinsloo | B12: martin.prinsloo@WearCheckRS.com | C12: Ex-Employee | D12: Microsoft Fabric (Free) | E12: 1 | F12: =SUMIF(Allocation_Detail!$A$2:$A$406,B12,Allocation_Detail!$L$2:$L$406) | G12: No longer an employee. FLAG: Remove licence. | H12: REMOVE LICENCE — no longer an employee
A13: Peter | B13: Peter@WearCheckRS.com | C13: Ex-Employee | D13: Microsoft 365 Business Standard | E13: 1 | F13: =SUMIF(Allocation_Detail!$A$2:$A$406,B13,Allocation_Detail!$L$2:$L$406) | G13: No longer an employee. FLAG: Remove licence. | H13: REMOVE LICENCE — no longer an employee
A14: Thabang Mathumba | B14: thabang@WearCheckRS.com | C14: Ex-Employee | D14: Microsoft Defender for Office 365 (Plan 2)+Microsoft 365 Business Standard | E14: 2 | F14: =SUMIF(Allocation_Detail!$A$2:$A$406,B14,Allocation_Detail!$L$2:$L$406) | G14: No longer an employee. FLAG: Remove licence. | H14: REMOVE LICENCE — no longer an employee
A15: Tumelo | B15: tumelo.samancor@WearCheckRS.com | C15: Ex-Employee | D15: Microsoft Fabric (Free) | E15: 1 | F15: =SUMIF(Allocation_Detail!$A$2:$A$406,B15,Allocation_Detail!$L$2:$L$406) | G15: No longer an employee. FLAG: Remove licence. | H15: REMOVE LICENCE — no longer an employee
A16: Lea Bodenstein | B16: Lea@WearCheckRS.com | C16: Contractor | D16: Microsoft 365 Business Premium+Microsoft Defender for Office 365 (Plan 2)+Microsoft Fabric (Free) | E16: 3 | F16: =SUMIF(Allocation_Detail!$A$2:$A$406,B16,Allocation_Detail!$L$2:$L$406) | G16: Not an employee — contractor. Licence allocated to RS. | H16: Review: keep licence or remove (contractor)
... A19: Christie | B19: christie.samancor@WearCheckRS.com | C19: Management Review | D19: Microsoft Fabric (Free) | E19: 1 | F19: =SUMIF(Allocation_Detail!$A$2:$A$406,B19,Allocation_Detail!$L$2:$L$406) | G19: Not an employee — has free Fabric licence only. Flagged for management review. | H19: Escalate to management for decision
A21: Summary
A22: Ex-Employees (remove licence) | B22: 11
A23: Contractors (review) | B23: 3
A24: Management Review | B24: 1
A25: Total flagged accounts | B25: 15
A27: Potential Monthly Savings (excl VAT) | B27: =SUM(F5:F19)

Sheet Review_Queue
A1: Licensed Display Name | B1: Licensed Email | C1: Assigned Division | D1: Matched Employee Name | E1: Candidate Employee Email | F1: Employee Number | G1: Confidence | H1: Review Type | I1: User Status | J1: Mapping Note | K1: Licenses Raw | L1: Action Required
A2: Christie | B2: christie.samancor@WearCheckRS.com | C2: RS | G2: Low | H2: Management Review | I2: Management Review | J2: Not an employee — has free Fabric licence only. Flagged for management review. | K2: Microsoft Fabric (Free) | L2: Confirm division or update User_Match
A5: DUPLICATE ACCOUNTS DETECTED
A6: The following employees have multiple licensed email accounts. Consider consolidating.
A7: Employee Number | B7: Employee Name | C7: Email 1 | D7: Email 2 | E7: Email 3 | F7: Action
A8: WC277 | B8: Louis Robert Peacock | C8: louis@WearCheckRS.com | D8: Louis_Zoho@WearCheckRS.com | F8: Review: consolidate to single account
A9: WC253 | B9: Philippus Jacobus Wilhelmus (Philip) Schutte | C9: philip@WearCheckRS.com | D9: Philip_Zoho@WearCheckRS.com | F9: Review: consolidate to single account

Sheet Admin_CSV_Snapshot
A1: Microsoft Admin Centre Export — Snapshot 30 March 2026
A2: Source: users_2026_03_30 11_05_42.csv | 842 total accounts | 147 licensed | 641 unlicensed | 54 soft-deleted
A4: Display Name | B4: User Principal Name | C4: First Name | D4: Last Name | E4: Department | F4: Title | G4: Usage Location | H4: Created | I4: Blocked | J4: Licences | K4: SKU Count
A5: Admin | B5: admin@WearCheckRS.com | C5: EDWARD FREDERICK | D5: PIETERSE | G5: ZA | H5: 2022-04-19 13:21:34Z | I5: No | J5: Microsoft Defender for Office 365 (Plan 2)+Microsoft Fabric (Free)+Microsoft 365 E3 | K5: 3
A6: Adri Ludick | B6: A.Ludick@WearCheckRS.com | C6: Adri | D6: Ludick | E6: ARC - AFS | F6: Manager | G6: ZA | H6: 2024-02-23 10:26:05Z | I6: No | J6: Microsoft 365 Business Premium+Microsoft Copilot Studio Viral Trial+Microsoft Defender for Office 365 (Plan 2)+Microsoft Power Automate Free | K6: 4
A7: Adri Ludick Old | B7: Adri.ludick@WearCheckRS.com | C7: Adri Old | D7: Ludick | G7: ZA | H7: 2021-12-02 10:20:18Z | I7: No | J7: Microsoft Defender for Office 365 (Plan 2)+Microsoft Power Automate Free+Microsoft 365 Business Standard | K7: 3
A8: Adriaan Bouwer | B8: adriaanb@WearCheckRS.com | C8: Adriaan | D8: Bouwer | F8: Sales Rep | G8: ZA | H8: 2022-05-16 09:32:22Z | I8: No | J8: Microsoft Defender for Office 365 (Plan 2)+Microsoft Power Automate Free+Microsoft 365 Business Standard+Microsoft Fabric (Free) | K8: 4
A9: AFS Application | B9: afs_app@WearCheckRS.com | C9: AFS | D9: Application | G9: ZA | H9: 2025-09-18 14:02:45Z | I9: No | J9: Microsoft Power Automate Free+Exchange Online (Plan 1) | K9: 2
A10: Alex Outram | B10: Alex@WearCheckRS.com | C10: Alex | D10: Outram | G10: ZA | H10: 2022-03-14 20:53:59Z | I10: No | J10: Microsoft Defender for Office 365 (Plan 2)+Microsoft Power Automate Free+Microsoft Fabric (Free)+Microsoft 365 Business Standard | K10: 4
A11: Allan Stuurman | B11: Allan@WearCheckRS.com | C11: Allan | D11: Stuurman | G11: ZA | H11: 2024-02-04 21:45:08Z | I11: No | J11: Microsoft Defender for Office 365 (Plan 2)+Microsoft 365 Business Standard | K11: 2
A12: Andrew Robb | B12: Andrew@wearcheckrs.com | C12: Andrew | D12: Robb | E12: RS | G12: ZA | H12: 2021-10-18 07:01:23Z | I12: No | J12: Microsoft 365 Business Premium+Microsoft Defender for Office 365 (Plan 2)+Microsoft Fabric (Free) | K12: 3
A13: Annah Modutwane | B13: annahm@WearCheckRS.com | C13: Annah | D13: Modutwane | G13: ZA | H13: 2022-08-31 11:37:36Z | I13: No | J13: Microsoft Defender for Office 365 (Plan 2)+Microsoft Power Automate Free+Microsoft Fabric (Free)+Microsoft 365 Business Standard | K13: 4
A14: Annemie Willer | B14: annemie@WearCheckRS.com | C14: Annemie | D14: Willer | E14: Reliability Solutions | F14: Operations Manager | G14: ZA | H14: 2018-06-27 17:29:12Z | I14: No | J14: Microsoft Defender for Office 365 (Plan 2)+Power BI Premium Per User+Microsoft Copilot Studio Viral Trial+Microsoft Power Apps Plan 2 Trial+Microsoft 365 E3+Microsoft Fabric (Free)+Microsoft Power Automate Free | K14: 7
A15: Antonio Ehrke | B15: Antonio.Ehrke@WearCheckRS.com | C15: Antonio | D15: Ehrke | G15: ZA | H15: 2025-02-20 16:41:33Z | I15: No | J15: Microsoft Defender for Office 365 (Plan 2)+Microsoft 365 Business Standard | K15: 2
A16: Armindo Mucacho | B16: Armindo@WearCheckRS.com | C16: Armindo | D16: Mucacho | E16: RS | F16: Site Supervisor | G16: ZA | H16: 2021-11-30 14:30:48Z | I16: No | J16: Microsoft Defender for Office 365 (Plan 2)+Microsoft Fabric (Free)+Microsoft 365 Business Standard | K16: 3
A17: Arnold van Zyl | B17: Arnold@WearCheckRS.com | C17: Arnold | D17: van Zyl | G17: ZA | H17: 2025-02-20 16:47:14Z | I17: No | J17: Microsoft Defender for Office 365 (Plan 2)+Microsoft 365 Business Standard | K17: 2
A18: Aubrey Tshabalala | B18: Aubrey@WearCheckRS.com | C18: Aubrey | D18: Tshabalala | G18: ZA | H18: 2024-07-04 08:52:32Z | I18: No | J18: Microsoft Defender for Office 365 (Plan 2)+Microsoft 365 Business Standard | K18: 2
A19: Bernard Lopi Molangoane | B19: lopi@WearCheckRS.com | C19: Bernard Lopi | D19: Molangoane | G19: ZA | H19: 2022-05-16 09:38:45Z | I19: No | J19: Microsoft Defender for Office 365 (Plan 2)+Microsoft 365 Business Standard | K19: 2
A20: Betty Monyepao | B20: betty@WearCheckRS.com | C20: Betty | D20: Monyepao | G20: ZA | H20: 2022-05-16 11:02:31Z | I20: No | J20: Microsoft Defender for Office 365 (Plan 2)+Microsoft 365 Business Standard | K20: 2
A21: Bianka De Beer | B21: Bianka@WearCheckRS.com | C21: Bianka | D21: De Beer | F21: Administrator | G21: ZA | H21: 2026-02-03 18:11:54Z | I21: No | J21: Microsoft Power Automate Free+Microsoft Power Apps Plan 2 Trial+Microsoft Fabric (Free)+Microsoft Copilot Studio Viral Trial+Microsoft Power Apps for Developer+Power Pages vTrial for Makers+Microsoft Defender for Office 365 (Plan 2)+Dynamics 365 Customer Insights Self-Service+Microsoft 365 Business Premium | K21: 9
A22: Boitumelo Makgamatha | B22: Boitumelo@WearCheckRS.com | C22: Boitumelo | D22: Makgamatha | G22: ZA | H22: 2022-02-10 14:39:01Z | I22: No | J22: Microsoft Defender for Office 365 (Plan 2)+Microsoft 365 Business Standard | K22: 2
A23: Chicco Tivane | B23: chicco@WearCheckRS.com | C23: Chicco | D23: Tivane | G23: ZA | H23: 2022-05-16 09:41:08Z | I23: No | J23: Microsoft Defender for Office 365 (Plan 2)+Microsoft 365 Business Standard | K23: 2
A24: Chris Mostert | B24: ChrisM@wearcheckrs.com | C24: Chris | D24: Mostert | E24: Reliability Solutions | F24: Analyst | G24: ZA | H24: 2022-03-03 00:28:52Z | I24: No | J24: Microsoft Defender for Office 365 (Plan 2)+Microsoft 365 Business Standard | K24: 2
A25: Christene Fourie | B25: Christene@WearCheckRS.com | C25: Christene | D25: Fourie | E25: RS AND AFS | F25: Administrator Logistics | G25: ZA | H25: 2020-10-31 13:31:54Z | I25: No | J25: Microsoft Defender for Office 365 (Plan 2)+Microsoft Power Automate Free+Microsoft 365 Business Standard | K25: 3
A26: Christian Geel | B26: Christian@WearCheckRS.com | C26: Christian | D26: Geel | E26: ARC | F26: Data Collector | G26: ZA | H26: 2022-05-05 07:19:08Z | I26: No | J26: Microsoft Fabric (Free)+Microsoft Power Automate Free | K26: 2
A27: Christie | B27: christie.samancor@WearCheckRS.com | G27: ZA | H27: 2025-02-21 11:32:15Z | I27: No | J27: Microsoft Fabric (Free) | K27: 1
A28: CJ Woller | B28: cj@WearCheckRS.com | C28: CJ | D28: Woller | G28: ZA | H28: 2023-06-05 10:23:31Z | I28: No | J28: Microsoft Defender for Office 365 (Plan 2)+Microsoft Power Automate Free+Microsoft 365 Business Standard | K28: 3
A29: Colleen Pyper | B29: colleen.pyper@WearCheckRS.com | C29: Colleen | D29: Pyper | G29: ZA | H29: 2023-02-17 07:23:03Z | I29: No | J29: Microsoft Defender for Office 365 (Plan 2)+Microsoft Power Automate Free+Microsoft 365 Business Standard | K29: 3
A30: Daniel Molapo | B30: daniel@WearCheckRS.com | C30: Daniel | D30: Molapo | E30: ARC | G30: ZA | H30: 2022-05-17 10:33:08Z | I30: No | J30: Microsoft Defender for Office 365 (Plan 2)+Microsoft 365 E3+Microsoft Fabric (Free)+Microsoft Power Automate Free | K30: 4
A31: David Lipange | B31: DavidL@WearCheckRS.com | C31: David | D31: Lipange | E31: RS | F31: CM Technician | G31: ZA | H31: 2021-11-30 14:38:01Z | I31: No | J31: Microsoft Defender for Office 365 (Plan 2)+Microsoft Fabric (Free)+Microsoft 365 Business Standard | K31: 3
A32: David Viljoen | B32: David@WearCheckRS.com | C32: David | D32: Viljoen | E32: RS | F32: Technician | G32: ZA | H32: 2020-12-02 08:11:06Z | I32: No | J32: Microsoft Defender for Office 365 (Plan 2)+Microsoft Fabric (Free)+Microsoft 365 Business Standard+Microsoft Power Automate Free | K32: 4
A33: Deon Gaarkeuken | B33: Deon@WearCheckRS.com | C33: Deon | D33: Gaarkeuken | E33: RS | F33: Senior Technician | G33: ZA | H33: 2020-08-31 08:17:29Z | I33: No | J33: Microsoft Defender for Office 365 (Plan 2)+Power BI Premium Per User+Microsoft 365 E3+Microsoft Fabric (Free)+Microsoft Power Automate Free | K33: 5
A34: Desmond Ngomane | B34: desmond@WearCheckRS.com | C34: Desmond | D34: Ngomane | G34: ZA | H34: 2022-05-17 10:21:51Z | I34: No | J34: Microsoft Defender for Office 365 (Plan 2)+Microsoft Fabric (Free)+Microsoft 365 Business Standard | K34: 3
A35: Dian Leff | B35: dian@WearCheckRS.com | C35: Dian | D35: Leff | G35: ZA | H35: 2024-06-11 08:23:06Z | I35: No | J35: Microsoft Defender for Office 365 (Plan 2)+Microsoft 365 Business Standard | K35: 2
A36: Douglas Prout-Jones | B36: douglas@WearCheckRS.com | C36: Douglas | D36: Prout-Jones | G36: ZA | H36: 2023-06-05 10:24:22Z | I36: No | J36: Microsoft Defender for Office 365 (Plan 2)+Microsoft Power Automate Free+Microsoft 365 Business Standard | K36: 3
A37: Eben Prinsloo | B37: eben@WearCheckRS.com | C37: Eben | D37: Prinsloo | G37: ZA | H37: 2023-11-07 13:02:11Z | I37: No | J37: Microsoft Defender for Office 365 (Plan 2)+Microsoft 365 Business Standard+Microsoft Fabric (Free) | K37: 3
A38: Edward Pieterse Jnr | B38: edwardfp@WearCheckRS.com | C38: Edward | D38: Pieterse Jnr | E38: Reliability Solutions Services | F38: Operations Manager | G38: ZA | H38: 2020-06-15 21:43:44Z | I38: No | J38: Microsoft Defender for Office 365 (Plan 2)+Microsoft Power Apps for Developer+Microsoft 365 E3+Microsoft Fabric (Free)+Microsoft Power Automate Free | K38: 5
A39: Edward Pieterse Snr | B39: epieterse@wearcheckrs.com | C39: Edward Snr | D39: Pieterse | F39: Reliability Specialist | G39: ZA | H39: 2021-05-25 17:39:48Z | I39: No | J39: Microsoft 365 Business Premium+Microsoft Defender for Office 365 (Plan 2)+Microsoft Power Automate Free+Microsoft Fabric (Free) | K39: 4
A40: Edwin Gibbons | B40: edwin@WearCheckRS.com | C40: Edwin | D40: Gibbons | G40: ZA | H40: 2025-07-24 07:20:48Z | I40: No | J40: Microsoft Defender for Office 365 (Plan 2)+Microsoft 365 Business Standard | K40: 2
A41: Ethel Mienie | B41: ethel.mienie@WearCheckRS.com | C41: Ethel | D41: Mienie | G41: ZA | H41: 2023-02-17 07:21:10Z | I41: No | J41: Microsoft Defender for Office 365 (Plan 2)+Microsoft 365 Business Standard | K41: 2
A42: Eugene Scheepers | B42: eugene@WearCheckRS.com | C42: Eugene | D42: Scheepers | G42: ZA | H42: 2022-05-16 09:51:35Z | I42: No | J42: Microsoft Defender for Office 365 (Plan 2)+Microsoft 365 Business Standard | K42: 2
A43: Evert Viljoen | B43: Evert@WearCheckRS.com | C43: Evert | D43: Viljoen | E43: NDT | G43: ZA | H43: 2026-01-23 10:26:53Z | I43: No | J43: Microsoft Defender for Office 365 (Plan 2)+Microsoft 365 Business Premium | K43: 2
A44: FLIRIRVM1 | B44: flirirvm1@WearCheckRS.com | C44: FLIRIRVM1 | E44: Reliability Solutions | G44: ZA | H44: 2021-11-26 09:16:55Z | I44: No | J44: Microsoft Defender for Office 365 (Plan 2)+Microsoft 365 Business Standard | K44: 2
A45: flirirvm2 | B45: flirirvm2@WearCheckRS.com | G45: ZA | H45: 2021-11-30 06:51:41Z | I45: No | J45: Microsoft Defender for Office 365 (Plan 2)+Microsoft Fabric (Free)+Microsoft 365 Business Standard | K45: 3
A46: flirirvm3 | B46: flirirvm3@WearCheckRS.com | G46: ZA | H46: 2021-11-30 06:53:49Z | I46: No | J46: Microsoft Defender for Office 365 (Plan 2)+Microsoft Fabric (Free)+Microsoft 365 Business Standard | K46: 3
A47: Francios Pretorius | B47: franciosp@WearCheckRS.com | C47: Francios | D47: Pretorius | G47: ZA | H47: 2022-05-26 10:06:43Z | I47: No | J47: Microsoft Defender for Office 365 (Plan 2)+Microsoft Power Automate Free+Microsoft 365 Business Standard | K47: 3
A48: Francois Pienaar | B48: FrancoisP@WearCheckRS.com | C48: Francois | D48: Pienaar | E48: RS | F48: Analyst | G48: ZA | H48: 2022-05-05 07:26:03Z | I48: No | J48: Microsoft Defender for Office 365 (Plan 2)+Microsoft Fabric (Free)+Microsoft 365 Business Standard+Microsoft Power Automate Free | K48: 4
A49: Francois van Eden | B49: francoisve@wearcheckrs.com | C49: Francois | D49: van Eden | G49: ZA | H49: 2021-07-08 05:52:30Z | I49: No | J49: Microsoft 365 Business Premium+Microsoft Defender for Office 365 (Plan 2)+Microsoft Fabric (Free)+Microsoft Power Automate Free | K49: 4
A50: Freddy-Ben Gariseb | B50: Freddy-Ben@WearCheckRS.com | C50: Freddy-Ben | D50: Gariseb | G50: ZA | H50: 2023-02-19 17:54:29Z | I50: No | J50: Microsoft Defender for Office 365 (Plan 2)+Microsoft 365 Business Standard | K50: 2
A51: Gabriel | B51: Gabriel@WearCheckRS.com | C51: Gabriel | D51: Nuunyango | E51: ARC | F51: Reliability Technologist | G51: NA | H51: 2023-09-06 19:20:35Z | I51: No | J51: Microsoft Defender for Office 365 (Plan 2)+Microsoft Fabric (Free)+Microsoft 365 Business Standard | K51: 3
A52: Gladwin Sekharume | B52: GladwinS@WearCheckRS.com | C52: Gladwin | D52: Sekharume | G52: ZA | H52: 2024-06-04 10:08:00Z | I52: No | J52: Microsoft Defender for Office 365 (Plan 2)+Microsoft 365 Business Standard | K52: 2
A53: Godfrey Boikhutso | B53: Godfrey@WearCheckRS.com | C53: Godfrey | D53: Boikhutso | E53: TC | G53: ZA | H53: 2026-01-23 10:24:22Z | I53: No | J53: Microsoft Defender for Office 365 (Plan 2)+Microsoft 365 Business Premium | K53: 2
A54: Gustav Lourens | B54: gustav@WearCheckRS.com | C54: Gustav | D54: Lourens | G54: ZA | H54: 2022-05-16 09:54:09Z | I54: No | J54: Microsoft Defender for Office 365 (Plan 2)+Microsoft 365 Business Standard | K54: 2
A55: Hannest Koegelenberg | B55: hannest@WearCheckRS.com | C55: Hannest | D55: Koegelenberg | G55: ZA | H55: 2022-05-16 09:55:02Z | I55: No | J55: Microsoft Defender for Office 365 (Plan 2)+Microsoft 365 Business Standard | K55: 2
A56: Hein Coetzer | B56: heinc@WearCheckRS.com | C56: Hein | D56: Coetzer | G56: ZA | H56: 2021-05-25 18:10:51Z | I56: No | J56: Microsoft Defender for Office 365 (Plan 2)+Microsoft 365 Business Standard | K56: 2
A57: Heinrich Kusel | B57: Heinrich@WearCheckRS.com | C57: Heinrich | D57: Kusel | G57: ZA | H57: 2025-01-13 10:00:12Z | I57: No | J57: Microsoft Defender for Office 365 (Plan 2)+Microsoft 365 Business Standard | K57: 2
A58: Henry Mherekumombe | B58: Henry@WearCheckRS.com | C58: Henry | D58: Mherekumombe | E58: RS | F58: NDT Technician | G58: ZA | H58: 2021-10-27 08:18:56Z | I58: No | J58: Microsoft Defender for Office 365 (Plan 2)+Microsoft Power Automate Free+Microsoft 365 Business Standard | K58: 3
A59: Isac Zacarias | B59: Isac@WearCheckRS.com | C59: Isac | D59: Zacarias | E59: RS | F59: CM Technician | G59: ZA | H59: 2021-11-30 14:34:34Z | I59: No | J59: Microsoft Defender for Office 365 (Plan 2)+Microsoft Fabric (Free)+Microsoft 365 Business Standard | K59: 3
A60: Ivan Langa | B60: Ivan@WearCheckRS.com | C60: Ivan | D60: Langa | E60: RS | F60: CM Technician | G60: ZA | H60: 2021-11-30 14:36:17Z | I60: No | J60: Microsoft Defender for Office 365 (Plan 2)+Microsoft Fabric (Free)+Microsoft 365 Business Standard | K60: 3
A61: Jaco De Beer | B61: jacodb@WearCheckRS.com | C61: Jaco | D61: De Beer | G61: ZA | H61: 2022-05-17 10:28:39Z | I61: No | J61: Microsoft Defender for Office 365 (Plan 2)+Microsoft 365 Business Standard | K61: 2
A62: Jaco Venter | B62: JacoV@WearCheckRS.com | C62: Jaco | D62: Venter | E62: NDT | G62: ZA | H62: 2026-01-23 10:25:39Z | I62: No | J62: Microsoft Defender for Office 365 (Plan 2)+Microsoft 365 Business Premium | K62: 2
A63: Jaco Willer | B63: jaco@wearcheckrs.com | C63: Jaco | D63: Willer | E63: RS | G63: ZA | H63: 2021-05-25 18:10:51Z | I63: No | J63: Microsoft 365 Business Premium+Microsoft Defender for Office 365 (Plan 2)+Microsoft Power Automate Free | K63: 3
A64: James Tshabalala | B64: james@WearCheckRS.com | C64: James | D64: Tshabalala | G64: ZA | H64: 2022-05-16 09:58:15Z | I64: No | J64: Microsoft Defender for Office 365 (Plan 2)+Microsoft Power Automate Free+Microsoft Fabric (Free)+Microsoft 365 Business Standard | K64: 4
A65: Jean-Jacques | B65: jj@WearCheckRS.com | C65: Jaen-Jacques | D65: De Beer | E65: Remote Center | G65: ZA | H65: 2025-08-06 10:23:02Z | I65: No | J65: Microsoft 365 Business Premium+Microsoft Power Automate Free+Microsoft Fabric (Free)+Microsoft Defender for Office 365 (Plan 2) | K65: 4
A66: Jean Pierre Du Plessis | B66: Jean-Pierre@WearCheckRS.com | C66: Jean Pierre | D66: Du Plessis | E66: TC Department | F66: Machinery Inspector | G66: ZA | H66: 2025-12-04 10:18:18Z | I66: No | J66: Microsoft 365 Business Standard+Microsoft Defender for Office 365 (Plan 2) | K66: 2
A67: Joe Kies | B67: Joe@WearCheckRS.com | C67: Joe | D67: Kies | G67: ZA | H67: 2026-01-23 10:21:55Z | I67: No | J67: Microsoft Power Automate Free+Microsoft 365 Business Standard+Microsoft Power Apps Plan 2 Trial+Microsoft Fabric (Free)+Microsoft Copilot Studio Viral Trial+Microsoft Power Apps for Developer+Power Pages vTrial for Makers+Microsoft Defender for Office 365 (Plan 2)+Dynamics 365 Customer Insights Self-Service | K67: 9
A68: Johan Bekker | B68: JohanB@WearCheckRS.com | C68: Johan | D68: Bekker | G68: ZA | H68: 2024-05-23 04:40:52Z | I68: No | J68: Microsoft Defender for Office 365 (Plan 2)+Microsoft Power Automate Free+Microsoft 365 Business Standard | K68: 3
A69: Johan Rossouw | B69: JohanR@WearCheckRS.com | C69: Johan | D69: Rossouw | G69: ZA | H69: 2025-02-20 16:33:48Z | I69: No | J69: Microsoft Defender for Office 365 (Plan 2)+Microsoft 365 Business Standard | K69: 2
A70: Johan Stols | B70: Johan.Stols@WearCheckRS.com | C70: Johan | D70: Stols | G70: ZA | H70: 2022-01-24 14:51:24Z | I70: No | J70: Microsoft Defender for Office 365 (Plan 2)+Microsoft Power Automate Free+Microsoft 365 Business Standard | K70: 3
A71: Johandre Oosthuizen | B71: johandre@WearCheckRS.com | C71: Johandre | D71: Oosthuizen | G71: ZA | H71: 2022-05-16 10:03:03Z | I71: No | J71: Microsoft Defender for Office 365 (Plan 2)+Microsoft 365 Business Standard | K71: 2
A72: jordanlionmasters | B72: jordanlionmasters_gmail.com#EXT#@wearcheckrs.onmicrosoft.com | G72: ZA | H72: 2024-06-14 10:32:59Z | I72: No | J72: Microsoft Fabric (Free) | K72: 1
A73: Kenneth Moremi | B73: kenneth@WearCheckRS.com | C73: Kenneth | D73: Moremi | G73: ZA | H73: 2022-02-10 14:40:22Z | I73: No | J73: Microsoft Defender for Office 365 (Plan 2)+Microsoft 365 Business Standard | K73: 2
A74: Kevin Henwood | B74: Kevin@WearCheckRS.com | C74: Kevin | D74: Henwood | G74: ZA | H74: 2025-02-11 13:42:56Z | I74: No | J74: Microsoft Defender for Office 365 (Plan 2)+Microsoft 365 Business Standard | K74: 2
A75: Kevin Jonker | B75: kevinj@WearCheckRS.com | C75: Kevin | D75: Jonker | E75: RS North West | G75: ZA | H75: 2021-04-15 16:14:21Z | I75: No | J75: Microsoft Fabric (Free)+Microsoft Power Automate Free | K75: 2
A76: Khotso Mosala | B76: Khotso@WearCheckRS.com | C76: Khotso | D76: Mosala | G76: ZA | H76: 2025-02-20 16:35:29Z | I76: No | J76: Microsoft Defender for Office 365 (Plan 2)+Microsoft 365 Business Standard | K76: 2
A77: Landus Walters | B77: Landus@WearCheckRS.com | C77: Landus | D77: Walters | G77: ZA | H77: 2025-02-20 16:46:06Z | I77: No | J77: Microsoft Defender for Office 365 (Plan 2)+Microsoft 365 Business Standard | K77: 2
A78: Lea Bodenstein | B78: Lea@WearCheckRS.com | C78: Lea | D78: Bodenstein | G78: ZA | H78: 2023-03-15 12:34:41Z | I78: No | J78: Microsoft 365 Business Premium+Microsoft Defender for Office 365 (Plan 2)+Microsoft Fabric (Free) | K78: 3
A79: Leon Coetzee | B79: leon@WearCheckRS.com | C79: Leon | D79: Coetzee | G79: ZA | H79: 2022-05-16 10:12:10Z | I79: No | J79: Microsoft Defender for Office 365 (Plan 2)+Microsoft Power Automate Free+Microsoft 365 Business Standard | K79: 3
A80: Lesego Khuthwane | B80: Lesego@WearCheckRS.com | C80: Lesego | D80: Khuthwane | E80: Remote Centre | F80: Remote Centre Administrator | G80: ZA | H80: 2024-04-04 07:23:25Z | I80: No | J80: Microsoft 365 E3+Power BI Premium Per User+Microsoft Defender for Office 365 (Plan 2)+Microsoft Power Apps for Developer+Power Pages vTrial for Makers+Microsoft Fabric (Free)+Microsoft Power Apps Plan 2 Trial+Microsoft Copilot Studio Viral Trial+Microsoft Power Automate Free | K80: 9
A81: Lloyd Ngobeni | B81: Lloyd@WearCheckRS.com | C81: Lloyd | D81: Ngobeni | E81: RS | F81: NDT Technician | G81: ZA | H81: 2021-10-27 08:21:15Z | I81: No | J81: Microsoft Defender for Office 365 (Plan 2)+Microsoft Power Automate Free+Microsoft 365 Business Standard | K81: 3
A82: Londolani Managa | B82: LondolaniM@WearCheckRS.com | C82: Londolani | D82: Managa | E82: Wearcheck ARC | G82: ZA | H82: 2024-06-04 10:01:22Z | I82: No | J82: Microsoft Defender for Office 365 (Plan 2)+Microsoft 365 Business Standard | K82: 2
A83: Lorraine Mokgethi | B83: Lorraine@WearCheckRS.com | C83: Lorraine | D83: Mokgethi | E83: NDT | G83: ZA | H83: 2026-01-23 10:27:51Z | I83: No | J83: Microsoft Defender for Office 365 (Plan 2)+Microsoft 365 Business Premium | K83: 2
A84: Louis Peacock | B84: louis@WearCheckRS.com | C84: Louis | D84: Peacock | E84: WearCheck Reliability Solutions | F84: Technical Manager | G84: ZA | H84: 2019-03-07 15:25:18Z | I84: No | J84: Microsoft Defender for Office 365 (Plan 2)+Power BI Premium Per User+Microsoft 365 E3+Microsoft Power Automate Free | K84: 4
A85: Louis Zoho | B85: Louis_Zoho@WearCheckRS.com | C85: Louis | F85: Technical Manager | G85: ZA | H85: 2025-08-21 12:49:57Z | I85: No | J85: Microsoft 365 Business Standard | K85: 1
A86: Lubby Lubis | B86: lubby@WearCheckRS.com | C86: Lubby | D86: Lubis | E86: ARC | G86: ZA | H86: 2023-06-05 08:41:09Z | I86: No | J86: Microsoft Defender for Office 365 (Plan 2)+Microsoft 365 Business Standard | K86: 2
A87: Lucas Luus | B87: lucas@WearCheckRS.com | C87: Lucas | D87: Luus | G87: ZA | H87: 2022-05-16 10:12:59Z | I87: No | J87: Microsoft Defender for Office 365 (Plan 2)+Microsoft 365 Business Standard | K87: 2
A88: Mandé Coetzee | B88: Mande@WearCheckRS.com | C88: Mandé | D88: Coetzee | E88: ARC | F88: Administrator | G88: ZA | H88: 2023-07-13 11:47:34Z | I88: No | J88: Microsoft Defender for Office 365 (Plan 2)+Microsoft Fabric (Free)+Microsoft Power Automate Free+Microsoft 365 E3 | K88: 4
A89: Mandiso Muchanga | B89: Mandiso@WearCheckRS.com | C89: Mandiso | D89: Muchanga | G89: ZA | H89: 2024-10-21 08:37:26Z | I89: No | J89: Microsoft Defender for Office 365 (Plan 2)+Microsoft 365 Business Standard | K89: 2
A90: Marcel Schoeman | B90: Marcel@WearCheckRS.com | C90: Marcel | D90: Schoeman | G90: ZA | H90: 2021-09-01 13:17:37Z | I90: No | J90: Microsoft 365 Business Premium+Microsoft Defender for Office 365 (Plan 2)+Microsoft Fabric (Free) | K90: 3
A91: Mariette Du Rand | B91: mariette@WearCheckRS.com | C91: Mariette | D91: Du Rand | G91: ZA | H91: 2022-05-16 10:14:48Z | I91: No | J91: Microsoft 365 Business Premium+Microsoft Defender for Office 365 (Plan 2) | K91: 2
A92: Marshall Rasimphi | B92: marshallr@WearCheckRS.com | C92: Marshall | D92: Rasimphi | E92: RS North West | G92: ZA | H92: 2021-04-15 16:16:04Z | I92: No | J92: Microsoft Defender for Office 365 (Plan 2)+Microsoft 365 Business Standard | K92: 2
A93: Marthinus Admin Account | B93: marthinus_admin@wearcheckrs.com | C93: Marthinus | D93: Steenkamp | G93: ZA | H93: 2022-12-10 11:06:43Z | I93: No | J93: Microsoft Power Automate Free+Microsoft Fabric (Free) | K93: 2
A94: Marthinus Steenkamp | B94: Marthinus@WearCheckRS.com | C94: Marthinus | D94: Steenkamp | G94: ZA | H94: 2020-11-11 14:51:25Z | I94: No | J94: Microsoft Defender for Office 365 (Plan 2)+Microsoft 365 E3+Microsoft Fabric (Free) | K94: 3
A95: Martiens Van Aarde | B95: martiens@WearCheckRS.com | C95: Martiens | D95: Van Aarde | G95: ZA | H95: 2022-02-10 14:37:09Z | I95: No | J95: Microsoft Power Automate Free+Microsoft Defender for Office 365 (Plan 2)+Microsoft 365 Business Standard | K95: 3
A96: Martin Prinsloo | B96: martin.prinsloo@WearCheckRS.com | G96: ZA | H96: 2025-06-05 08:30:20Z | I96: No | J96: Microsoft Fabric (Free) | K96: 1
A97: Megan Salzwedel | B97: Megan@wearcheckrs.com | C97: Megan | D97: Salzwedel | E97: GP Consult | F97: SAP User | G97: ZA | H97: 2021-10-19 10:02:18Z | I97: No | J97: Microsoft 365 Business Premium+Microsoft Defender for Office 365 (Plan 2)+Microsoft Power Apps Plan 2 Trial+Microsoft Fabric (Free)+Microsoft Power Automate Free | K97: 5
A98: Mervyn Gibbons | B98: Mervyn@WearCheckRS.com | C98: Mervyn | D98: Gibbons | E98: TC | G98: ZA | H98: 2026-01-23 10:23:12Z | I98: No | J98: Microsoft Power Automate Free+Microsoft 365 Business Standard+Microsoft Power Apps Plan 2 Trial+Microsoft Fabric (Free)+Microsoft Copilot Studio Viral Trial+Microsoft Power Apps for Developer+Power Pages vTrial for Makers+Microsoft Defender for Office 365 (Plan 2)+Dynamics 365 Customer Insights Self-Service | K98: 9
A99: Meshack Nxumalo | B99: meshack@WearCheckRS.com | C99: Meshack | D99: Nxumalo | G99: ZA | H99: 2022-05-16 10:50:15Z | I99: No | J99: Microsoft Defender for Office 365 (Plan 2)+Microsoft 365 Business Standard | K99: 2
A100: Micheal Masemola | B100: michealm@WearCheckRS.com | C100: Micheal | D100: Masemola | G100: ZA | H100: 2022-05-16 11:01:48Z | I100: No | J100: Microsoft Defender for Office 365 (Plan 2)+Microsoft 365 Business Standard | K100: 2
A101: Micheal Pretorius | B101: micheal@WearCheckRS.com | C101: Micheal | D101: Pretorius | G101: ZA | H101: 2022-05-16 11:01:01Z | I101: No | J101: Microsoft Defender for Office 365 (Plan 2)+Microsoft Power Automate Free+Microsoft 365 Business Standard | K101: 3
...

Sheet COITE_Query
A1: COITE Licence Discrepancy Query — INV-0303
A2: Discrepancies between COITE invoice quantities and Microsoft Admin Centre tenant data. Raise with COITE for resolution.
A3: Both the original admin export and the CSV snapshot (30 Mar 2026) show IDENTICAL user counts — the mismatch is between COITE billing and the actual tenant.
A5: # | B5: SKU | C5: Invoice Qty (Purchased) | D5: Tenant Assigned | E5: Purchased but Unassigned | F5: Unit Price (ZAR excl VAT) | G5: Monthly Cost of Unassigned (ZAR) | H5: Query / Action | I5: Status
A6: 1 | B6: Microsoft 365 Business Premium | C6: 23 | D6: 21 | E6: 2 | F6: 368.68 | G6: 737.36 | H6: Invoice bills 2 licence(s) not assigned in tenant. Are these reserved/pending? If not needed, reduce subscription count to save R737.36/month. | I6: OPEN
A7: 2 | B7: Microsoft 365 Business Standard | C7: 97 | D7: 100 | E7: -3 | F7: 209.55 | G7: 0 | H7: Tenant has 3 more user(s) assigned than invoiced. Were these added after the billing date? Expect them on next invoice. | I7: OPEN
A8: 3 | B8: Microsoft 365 E3 | C8: 15 | D8: 14 | E8: 1 | F8: 603.29 | G8: 603.29 | H8: Invoice bills 1 licence(s) not assigned in tenant. Are these reserved/pending? If not needed, reduce subscription count to save R603.29/month. | I8: OPEN
A9: 4 | B9: Power Apps per app plan (1 app or website) | C9: 3 | D9: 0 | E9: 3 | F9: 83.79 | G9: 251.37 | H9: Billed on invoice (3 licences) but NO users have this SKU in the tenant. Is this a tenant-level subscription or assigned elsewhere? If not needed, cancel to save R251.37/month. | I9: OPEN
A10: 5 | B10: Power BI Premium Per User | C10: 7 | D10: 6 | E10: 1 | F10: 402.19 | G10: 402.19 | H10: Invoice bills 1 licence(s) not assigned in tenant. Are these reserved/pending? If not needed, reduce subscription count to save R402.19/month. | I10: OPEN
A11: 6 | B11: Adri Ludick Old account (adri.ludick@wearcheckrs.com) | C11: N/A | D11: 1 user | E11: N/A | F11: N/A | G11: See Licence_Cleanup | H11: Old/duplicate account still has Business Standard + Defender licences. New account A.Ludick@WearCheckRS.com is active. Remove licences from old account. | I11: OPEN
A14: Summary
A15: Total queries raised | B15: 6
A16: Total unassigned licence cost (ZAR/month excl VAT) | B16: 1994.21
A17: Data sources verified | B17: Admin Export + CSV Snapshot (30 Mar 2026) — IDENTICAL counts
A18: Invoice reference | B18: INV-0303
A19: Invoice date | B19: 25/03/2026
