Workbook

Sheet Read Me
A1: Microsoft License Allocation Workbook - March 2026
A2: Purpose
A3: Allocate Microsoft license invoice costs by cost centre using SKU-level allocation (Option B).
A4: How to use
A5: 1. Update the Monthly Invoice Amount column on SKU_Cost_Input from the monthly Microsoft invoice.
A6: 2. Review Review_Queue and resolve any low-confidence or unassigned accounts.
A7: 3. Division_Summary will update automatically once invoice amounts are entered.
A8: 4. Keep a month-end copy of the file for audit trail and future trend charts.
A9: Assumptions used in this build
A10: - Shared/generic/service accounts are defaulted to RS, per your instruction.
A11: - Namibia and Mozambique are treated as separate cost centres.
A12: - AFS is taken from Employee Master Department 2 = AFS unless Site says Namibia/Mozambique.
... A17: Accounts needing review: 23

Sheet Division_Summary
A1: Microsoft License Allocation Summary
A2: Enter monthly invoice amounts on SKU_Cost_Input. Cost values here will update automatically.
A4: KPI | B4: Value
A5: Licensed accounts in export | B5: 147
A6: Mapped to a cost centre | B6: =COUNTIF(User_Match!$F$2:$F$148,"<>Unassigned - Review") -> 129
A7: Accounts needing review | B7: =COUNTIF(User_Match!$L$2:$L$148,"Yes") -> 23
A10: Division | B10: Licensed Accounts | C10: Review Accounts | D10: SKU Assignments | E10: Allocated Monthly Cost | F10: % of Allocated Cost
A11: RS | B11: =COUNTIF(User_Match!$F$2:$F$148,A11) -> 94 | C11: =COUNTIFS(User_Match!$F$2:$F$148,A11,User_Match!$L$2:$L$148,"Yes") -> 0 | D11: =COUNTIF(Allocation_Detail!$C$2:$C$406,A11) -> 271 | E11: =SUMIF(Allocation_Detail!$C$2:$C$406,A11,Allocation_Detail!$L$2:$L$406) -> 0 | F11: =IF($E$16=0,0,E11/$E$16) -> 0
A12: AFS | B12: =COUNTIF(User_Match!$F$2:$F$148,A12) -> 25 | C12: =COUNTIFS(User_Match!$F$2:$F$148,A12,User_Match!$L$2:$L$148,"Yes") -> 5 | D12: =COUNTIF(Allocation_Detail!$C$2:$C$406,A12) -> 67 | E12: =SUMIF(Allocation_Detail!$C$2:$C$406,A12,Allocation_Detail!$L$2:$L$406) -> 0 | F12: =IF($E$16=0,0,E12/$E$16) -> 0
A13: Namibia | B13: =COUNTIF(User_Match!$F$2:$F$148,A13) -> 4 | C13: =COUNTIFS(User_Match!$F$2:$F$148,A13,User_Match!$L$2:$L$148,"Yes") -> 0 | D13: =COUNTIF(Allocation_Detail!$C$2:$C$406,A13) -> 10 | E13: =SUMIF(Allocation_Detail!$C$2:$C$406,A13,Allocation_Detail!$L$2:$L$406) -> 0 | F13: =IF($E$16=0,0,E13/$E$16) -> 0
A14: Mozambique | B14: =COUNTIF(User_Match!$F$2:$F$148,A14) -> 6 | C14: =COUNTIFS(User_Match!$F$2:$F$148,A14,User_Match!$L$2:$L$148,"Yes") -> 0 | D14: =COUNTIF(Allocation_Detail!$C$2:$C$406,A14) -> 17 | E14: =SUMIF(Allocation_Detail!$C$2:$C$406,A14,Allocation_Detail!$L$2:$L$406) -> 0 | F14: =IF($E$16=0,0,E14/$E$16) -> 0
A15: Unassigned - Review | B15: =COUNTIF(User_Match!$F$2:$F$148,A15) -> 18 | C15: =COUNTIFS(User_Match!$F$2:$F$148,A15,User_Match!$L$2:$L$148,"Yes") -> 18 | D15: =COUNTIF(Allocation_Detail!$C$2:$C$406,A15) -> 40 | E15: =SUMIF(Allocation_Detail!$C$2:$C$406,A15,Allocation_Detail!$L$2:$L$406) -> 0 | F15: =IF($E$16=0,0,E15/$E$16) -> 0
A16: Total | B16: =SUM(B11:B15) -> 147 | C16: =SUM(C11:C15) -> 23 | D16: =SUM(D11:D15) -> 405 | E16: =SUM(E11:E15) -> 0 | F16: =IF($E$16=0,0,E16/$E$16) -> 0
A19: Top SKU | B19: Users | C19: Invoice Amount | D19: Unit Cost
A20: Microsoft Defender for Office 365 (Plan 2) | B20: 130 | C20: =SKU_Cost_Input!D2 -> 0 | D20: =SKU_Cost_Input!E2 -> 0
A21: Microsoft 365 Business Standard | B21: 100 | C21: =SKU_Cost_Input!D3 -> 0 | D21: =SKU_Cost_Input!E3 -> 0
A22: Microsoft Power Automate Free | B22: 52 | C22: =SKU_Cost_Input!D4 -> 0 | D22: =SKU_Cost_Input!E4 -> 0
A23: Microsoft Fabric (Free) | B23: 50 | C23: =SKU_Cost_Input!D5 -> 0 | D23: =SKU_Cost_Input!E5 -> 0
A24: Microsoft 365 Business Premium | B24: 21 | C24: =SKU_Cost_Input!D6 -> 0 | D24: =SKU_Cost_Input!E6 -> 0
A25: Microsoft 365 E3 | B25: 14 | C25: =SKU_Cost_Input!D7 -> 0 | D25: =SKU_Cost_Input!E7 -> 0
H35: Division | I35: Allocated Monthly Cost
H36: RS | I36: =E11 -> 0
H37: AFS | I37: =E12 -> 0
H38: Namibia | I38: =E13 -> 0
H39: Mozambique | I39: =E14 -> 0
H40: Unassigned - Review | I40: =E15 -> 0

Sheet SKU_Cost_Input
A1: SKU | B1: Active Users | C1: Billing Hint | D1: Monthly Invoice Amount (input) | E1: Unit Cost | F1: Notes
A2: Microsoft Defender for Office 365 (Plan 2) | B2: 130 | C2: Review invoice | D2: 0 | E2: =IF(B2=0,0,D2/B2) -> 0 | F2: Enter the monthly invoice amount for this SKU if it appears on the invoice
A3: Microsoft 365 Business Standard | B3: 100 | C3: Likely billable | D3: 0 | E3: =IF(B3=0,0,D3/B3) -> 0 | F3: Enter the monthly invoice amount for this SKU if it appears on the invoice
A4: Microsoft Power Automate Free | B4: 52 | C4: Likely free / trial | D4: 0 | E4: =IF(B4=0,0,D4/B4) -> 0 | F4: Enter the monthly invoice amount for this SKU if it appears on the invoice
A5: Microsoft Fabric (Free) | B5: 50 | C5: Likely free / trial | D5: 0 | E5: =IF(B5=0,0,D5/B5) -> 0 | F5: Enter the monthly invoice amount for this SKU if it appears on the invoice
A6: Microsoft 365 Business Premium | B6: 21 | C6: Likely billable | D6: 0 | E6: =IF(B6=0,0,D6/B6) -> 0 | F6: Enter the monthly invoice amount for this SKU if it appears on the invoice
A7: Microsoft 365 E3 | B7: 14 | C7: Likely billable | D7: 0 | E7: =IF(B7=0,0,D7/B7) -> 0 | F7: Enter the monthly invoice amount for this SKU if it appears on the invoice
A8: Microsoft Copilot Studio Viral Trial | B8: 7 | C8: Likely free / trial | D8: 0 | E8: =IF(B8=0,0,D8/B8) -> 0 | F8: Enter the monthly invoice amount for this SKU if it appears on the invoice
A9: Microsoft Power Apps Plan 2 Trial | B9: 6 | C9: Likely free / trial | D9: 0 | E9: =IF(B9=0,0,D9/B9) -> 0 | F9: Enter the monthly invoice amount for this SKU if it appears on the invoice
A10: Microsoft Power Apps for Developer | B10: 6 | C10: Review invoice | D10: 0 | E10: =IF(B10=0,0,D10/B10) -> 0 | F10: Enter the monthly invoice amount for this SKU if it appears on the invoice
A11: Power BI Premium Per User | B11: 6 | C11: Likely billable | D11: 0 | E11: =IF(B11=0,0,D11/B11) -> 0 | F11: Enter the monthly invoice amount for this SKU if it appears on the invoice
A12: Power Pages vTrial for Makers | B12: 5 | C12: Likely free / trial | D12: 0 | E12: =IF(B12=0,0,D12/B12) -> 0 | F12: Enter the monthly invoice amount for this SKU if it appears on the invoice
A13: Exchange Online (Plan 1) | B13: 4 | C13: Likely billable | D13: 0 | E13: =IF(B13=0,0,D13/B13) -> 0 | F13: Enter the monthly invoice amount for this SKU if it appears on the invoice
... A15: Power Automate per user plan | B15: 1 | C15: Likely billable | D15: 0 | E15: =IF(B15=0,0,D15/B15) -> 0 | F15: Enter the monthly invoice amount for this SKU if it appears on the invoice

Sheet User_Match
A1: Licensed Display Name | B1: Licensed Email | C1: Matched Employee Name | D1: Candidate Employee Email | E1: Employee Number | F1: Division | G1: Department Group | H1: Site | I1: Contact Number | J1: Match Status | K1: Confidence | L1: Review Required | M1: Mapping Note | N1: License SKU Count | O1: All Licenses Raw
A2: Antonio Ehrke | B2: Antonio.Ehrke@WearCheckRS.com | C2: Antonio Ehrke | D2: antonio.ehrke@wearcheckrs.com | E2: WC503 | F2: AFS | G2: AFS | I2: 0834695668 | J2: Matched | K2: High | L2: No | M2: Exact company email match | N2: 2 | O2: Microsoft Defender for Office 365 (Plan 2)+Microsoft 365 Business Standard
A3: Arnold van Zyl | B3: Arnold@WearCheckRS.com | C3: Arnoldus Johannes van Zyl | D3: Arnold@WearCheckRS.com | E3: WC526 | F3: AFS | G3: AFS | I3: 067412 1369 | J3: Matched | K3: High | L3: No | M3: Exact company email match | N3: 2 | O3: Microsoft Defender for Office 365 (Plan 2)+Microsoft 365 Business Standard
A4: Colleen Pyper | B4: colleen.pyper@WearCheckRS.com | C4: Colleen Pyper | D4: colleen.pyper@WearCheckRS.com | E4: WC486 | F4: AFS | G4: AFS | I4: 0662916811 | J4: Matched | K4: High | L4: No | M4: Exact company email match | N4: 3 | O4: Microsoft Defender for Office 365 (Plan 2)+Microsoft Power Automate Free+Microsoft 365 Business Standard
A5: Edwin Gibbons | B5: edwin@WearCheckRS.com | C5: Edwin Ashley Gibbons | D5: edwin@wearcheckrs.com | E5: WEC138 | F5: AFS | G5: AFS | I5: 0725336075 | J5: Matched | K5: High | L5: No | M5: Exact company email match | N5: 2 | O5: Microsoft Defender for Office 365 (Plan 2)+Microsoft 365 Business Standard
A6: Ethel Mienie | B6: ethel.mienie@WearCheckRS.com | C6: Ethel Mienie | D6: ethel.mienie@WearCheckRS.com | E6: WC488 | F6: AFS | G6: AFS | I6: 0660215452 | J6: Matched | K6: High | L6: No | M6: Exact company email match | N6: 2 | O6: Microsoft Defender for Office 365 (Plan 2)+Microsoft 365 Business Standard
A7: Evert Viljoen | B7: Evert@WearCheckRS.com | C7: Evert Viljoen | D7: evertv@wearcheck.co.za | E7: WC497 | F7: AFS | G7: AFS | I7: 0795284219 | J7: Matched | K7: Medium | L7: No | M7: Matched via exact name | N7: 2 | O7: Microsoft Defender for Office 365 (Plan 2)+Microsoft 365 Business Premium
A8: Godfrey Boikhutso | B8: Godfrey@WearCheckRS.com | C8: Godfrey Boikhutso | D8: godfreyb@wearcheck.co.za | E8: WC510 | F8: AFS | G8: AFS | I8: 0718609242 | J8: Matched | K8: Medium | L8: No | M8: Matched via exact name | N8: 2 | O8: Microsoft Defender for Office 365 (Plan 2)+Microsoft 365 Business Premium
A9: Jaco Venter | B9: JacoV@WearCheckRS.com | C9: Jacobus Frederick Venter | D9: jacov@wearcheck.co.za | E9: WC493 | F9: AFS | G9: AFS | I9: 0834009604 | J9: Matched | K9: Medium | L9: No | M9: Matched via email alias/local-part | N9: 2 | O9: Microsoft Defender for Office 365 (Plan 2)+Microsoft 365 Business Premium
A10: Johan Bekker | B10: JohanB@WearCheckRS.com | C10: Johan Bekker | D10: JohanB@wearcheckRS.com | E10: WC645 | F10: AFS | G10: AFS | I10: 0675951633 | J10: Matched | K10: High | L10: No | M10: Exact company email match | N10: 3 | O10: Microsoft Defender for Office 365 (Plan 2)+Microsoft Power Automate Free+Microsoft 365 Business Standard
A11: Johan Rossouw | B11: JohanR@WearCheckRS.com | C11: Johan Rossouw | D11: johanr@wearcheckrs.com | E11: WC491 | F11: AFS | G11: AFS | I11: 0829274240 | J11: Matched | K11: High | L11: No | M11: Exact company email match | N11: 2 | O11: Microsoft Defender for Office 365 (Plan 2)+Microsoft 365 Business Standard
A12: Khotso Mosala | B12: Khotso@WearCheckRS.com | C12: Khotso Thabo Mosala | D12: khotso@wearcheckrs.com | E12: WC482 | F12: AFS | G12: AFS | I12: 0823321905 | J12: Matched | K12: High | L12: No | M12: Exact company email match | N12: 2 | O12: Microsoft Defender for Office 365 (Plan 2)+Microsoft 365 Business Standard
A13: Landus Walters | B13: Landus@WearCheckRS.com | C13: Norman Landus Walters | D13: Landus@wearcheckrs.com | E13: WC509 | F13: AFS | G13: AFS | I13: 076 385 2151 | J13: Matched | K13: High | L13: No | M13: Exact company email match | N13: 2 | O13: Microsoft Defender for Office 365 (Plan 2)+Microsoft 365 Business Standard
... A20: Teresa Venter | B20: teresa.venter@WearCheckRS.com | C20: Teresa Venter | D20: teresa.venter@wearcheckRS.com | E20: WC487 | F20: AFS | G20: AFS | I20: 0662916929 | J20: Matched | K20: High | L20: No | M20: Exact company email match | N20: 3 | O20: Microsoft Defender for Office 365 (Plan 2)+Microsoft Power Automate Free+Microsoft 365 Business Standard
A21: Jean Pierre Du Plessis | B21: Jean-Pierre@WearCheckRS.com | C21: Jean Pierre du Plessis | F21: AFS | G21: AFS | I21: 0602033229 | J21: Matched | K21: Low | L21: Yes | M21: Matched via exact name | N21: 2 | O21: Microsoft 365 Business Standard+Microsoft Defender for Office 365 (Plan 2)
A22: Joe Kies | B22: Joe@WearCheckRS.com | C22: Joseph Benjamin Kies | D22: josephk@wearcheck.co.za | E22: WC531 | F22: AFS | G22: AFS | I22: 0674121368 | J22: Matched | K22: Low | L22: Yes | M22: Matched via manual alias/name rule | N22: 9 | O22: Microsoft Power Automate Free+Microsoft 365 Business Standard+Microsoft Power Apps Plan 2 Trial+Microsoft Fabric (Free)+Microsoft Copilot Studio Viral Trial+Microsoft Power Apps for Developer+Power Pages vTrial for Makers+Microsoft Defender for Office 365 (Plan 2)+Dynamics 365 Customer Insights Self-Service
A23: Johan Stols | B23: Johan.Stols@WearCheckRS.com | C23: Johannes Gideon Francios Stols | D23: Johans@wearcheckrs.com | E23: WC508 | F23: AFS | G23: AFS | I23: 0832943748 | J23: Matched | K23: Low | L23: Yes | M23: Matched via manual alias/name rule | N23: 3 | O23: Microsoft Defender for Office 365 (Plan 2)+Microsoft Power Automate Free+Microsoft 365 Business Standard
A24: Lorraine Mokgethi | B24: Lorraine@WearCheckRS.com | C24: Lorraine Lerato Mokgethi | D24: lorrainem@wearcheck.co.za | E24: WC495 | F24: AFS | G24: AFS | I24: 786 672 158 | J24: Matched | K24: Low | L24: Yes | M24: Matched via close email alias + surname | N24: 2 | O24: Microsoft Defender for Office 365 (Plan 2)+Microsoft 365 Business Premium
A25: Mervyn Gibbons | B25: Mervyn@WearCheckRS.com | C25: Mervyn Thomas Gibbons | D25: mervyng@wearcheck.co.za | E25: WC536 | F25: AFS | G25: AFS | I25: 0674193633 | J25: Matched | K25: Low | L25: Yes | M25: Matched via close email alias + surname | N25: 9 | O25: Microsoft Power Automate Free+Microsoft 365 Business Standard+Microsoft Power Apps Plan 2 Trial+Microsoft Fabric (Free)+Microsoft Copilot Studio Viral Trial+Microsoft Power Apps for Developer+Power Pages vTrial for Makers+Microsoft Defender for Office 365 (Plan 2)+Dynamics 365 Customer Insights Self-Service
A26: Armindo Mucacho | B26: Armindo@WearCheckRS.com | C26: Armindo Muchacho | D26: armindo@wearcheckrs.com | E26: Unknown | F26: Mozambique | G26: WearCheck | H26: Mozambique | I26: 258848349643 | J26: Matched | K26: High | L26: No | M26: Exact company email match | N26: 3 | O26: Microsoft Defender for Office 365 (Plan 2)+Microsoft Fabric (Free)+Microsoft 365 Business Standard
A27: David Lipange | B27: DavidL@WearCheckRS.com | C27: David Lipague | D27: davidl@wearcheckrs.com | E27: Unknown | F27: Mozambique | G27: WearCheck | H27: Mozambique | I27: 258847817888 | J27: Matched | K27: High | L27: No | M27: Exact company email match | N27: 3 | O27: Microsoft Defender for Office 365 (Plan 2)+Microsoft Fabric (Free)+Microsoft 365 Business Standard
A28: Isac Zacarias | B28: Isac@WearCheckRS.com | C28: Isac Zacarias | D28: isac@wearcheckrs.com | E28: Unknown | F28: Mozambique | G28: WearCheck | H28: Mozambique | I28: 258849439848 | J28: Matched | K28: High | L28: No | M28: Exact company email match | N28: 3 | O28: Microsoft Defender for Office 365 (Plan 2)+Microsoft Fabric (Free)+Microsoft 365 Business Standard
A29: Muhamad Ikram Hanif | B29: Muhamad@WearCheckRS.com | C29: Muhamad Hanif | D29: Muhamad@wearcheckRS.com | E29: Unknown | F29: Mozambique | G29: WearCheck | H29: Mozambique | I29: 258878054903 | J29: Matched | K29: High | L29: No | M29: Exact company email match | N29: 3 | O29: Microsoft Defender for Office 365 (Plan 2)+Microsoft Fabric (Free)+Microsoft 365 Business Standard
A30: Placido Maculuve | B30: Placido@WearCheckRS.com | C30: Placido Maculuve | D30: Placido@wearcheckrs.com | E30: Unknown | F30: Mozambique | G30: WearCheck | H30: Mozambique | I30: 258845070300 | J30: Matched | K30: High | L30: No | M30: Exact company email match | N30: 3 | O30: Microsoft Defender for Office 365 (Plan 2)+Microsoft Fabric (Free)+Microsoft 365 Business Standard
A31: Riaan Du Plooy | B31: RiaanDP@WearCheckRS.com | C31: Adriaan Johannes du Plooy | D31: Riaandp@wearcheckRS.com | E31: WC591 | F31: Mozambique | G31: WearCheck | H31: Mozambique | I31: 0835965562 | J31: Matched | K31: High | L31: No | M31: Exact company email match | N31: 2 | O31: Microsoft 365 Business Premium+Microsoft Defender for Office 365 (Plan 2)
A32: Dian Leff | B32: dian@WearCheckRS.com | C32: Dian Leff | D32: dian@wearcheckrs.com | E32: WCN008 | F32: Namibia | G32: WearCheck | H32: Namibia | I32: 0817614612 | J32: Matched | K32: High | L32: No | M32: Exact company email match | N32: 2 | O32: Microsoft Defender for Office 365 (Plan 2)+Microsoft 365 Business Standard
A33: Freddy-Ben Gariseb | B33: Freddy-Ben@WearCheckRS.com | C33: Freddy-Ben Gariseb | D33: Freddy-Ben@wearcheckRS.com | E33: WCN004 | F33: Namibia | G33: WearCheck | H33: Namibia | I33: 264813707010 | J33: Matched | K33: High | L33: No | M33: Exact company email match | N33: 2 | O33: Microsoft Defender for Office 365 (Plan 2)+Microsoft 365 Business Standard
A34: Gabriel | B34: Gabriel@WearCheckRS.com | C34: Gabriel Shikongo Nuunyango | D34: gabriel@wearcheckrs.com | E34: WCN007 | F34: Namibia | G34: WearCheck | H34: Namibia | I34: +264 81 364 5524 | J34: Matched | K34: High | L34: No | M34: Exact company email match | N34: 3 | O34: Microsoft Defender for Office 365 (Plan 2)+Microsoft Fabric (Free)+Microsoft 365 Business Standard
A35: Rohan Willer | B35: rohan@WearCheckRS.com | C35: Hermanus Johannes Willer | D35: rohan@wearcheckrs.com | E35: WC381 | F35: Namibia | G35: WearCheck | H35: Namibia | I35: 0812165890 | J35: Matched | K35: High | L35: No | M35: Exact company email match | N35: 3 | O35: Microsoft 365 Business Premium+Microsoft Defender for Office 365 (Plan 2)+Microsoft Power Automate Free
A36: AFS Application | B36: afs_app@WearCheckRS.com | F36: AFS | J36: Mapped by rule | K36: High | L36: No | M36: Generic/shared/service account defaulted to RS per instruction | N36: 2 | O36: Microsoft Power Automate Free+Exchange Online (Plan 1)
A37: Admin | B37: admin@WearCheckRS.com | F37: RS | J37: Mapped by rule | K37: High | L37: No | M37: Generic/shared/service account defaulted to RS per instruction | N37: 3 | O37: Microsoft Defender for Office 365 (Plan 2)+Microsoft Fabric (Free)+Microsoft 365 E3
A38: Adri Ludick | B38: A.Ludick@WearCheckRS.com | C38: Adri Ludick | D38: a.ludick@wearcheckRS.com | E38: WC492 | F38: RS | G38: GP Consult | I38: 0832816896 | J38: Matched | K38: High | L38: No | M38: Exact company email match | N38: 4 | O38: Microsoft 365 Business Premium+Microsoft Copilot Studio Viral Trial+Microsoft Defender for Office 365 (Plan 2)+Microsoft Power Automate Free
A39: Adriaan Bouwer | B39: adriaanb@WearCheckRS.com | C39: Adriaan Pertus Johannes Bouwer | D39: adriaanb@wearcheckrs.com | E39: WC383 | F39: RS | G39: WearCheck | H39: KwaZulu Natal | I39: 0608498504 | J39: Matched | K39: High | L39: No | M39: Exact company email match | N39: 4 | O39: Microsoft Defender for Office 365 (Plan 2)+Microsoft Power Automate Free+Microsoft 365 Business Standard+Microsoft Fabric (Free)
A40: Alex Outram | B40: Alex@WearCheckRS.com | C40: Alexander Outram | D40: alex@wearcheckrs.com | E40: WEC105 | F40: RS | G40: GP Consult | H40: RBMR and PMR | I40: 0662213616 / 0720164289 | J40: Matched | K40: High | L40: No | M40: Exact company email match | N40: 4 | O40: Microsoft Defender for Office 365 (Plan 2)+Microsoft Power Automate Free+Microsoft Fabric (Free)+Microsoft 365 Business Standard
A41: Allan Stuurman | B41: Allan@WearCheckRS.com | C41: Allan Stuurman | D41: allan@wearcheckrs.com | E41: WEC123 | F41: RS | G41: GP Consult | H41: Samancor - ECM Tweefontein | I41: 0799121301 | J41: Matched | K41: High | L41: No | M41: Exact company email match | N41: 2 | O41: Microsoft Defender for Office 365 (Plan 2)+Microsoft 365 Business Standard
A42: Andrew Robb | B42: Andrew@wearcheckrs.com | C42: Andrew John Walker Robb | D42: andrew@wearcheckRS.com | E42: WEC103 | F42: RS | G42: GP Consult | H42: Remote Centre | I42: 0636504444 | J42: Matched | K42: High | L42: No | M42: Exact company email match | N42: 3 | O42: Microsoft 365 Business Premium+Microsoft Defender for Office 365 (Plan 2)+Microsoft Fabric (Free)
A43: Annah Modutwane | B43: annahm@WearCheckRS.com | C43: Annah Seipone Modutwane | D43: annahm@wearcheckrs.com | E43: WC484 | F43: RS | G43: WearCheck | H43: Valterra - Mototolo | I43: 0833579812 | J43: Matched | K43: High | L43: No | M43: Exact company email match | N43: 4 | O43: Microsoft Defender for Office 365 (Plan 2)+Microsoft Power Automate Free+Microsoft Fabric (Free)+Microsoft 365 Business Standard
A44: Annemie Willer | B44: annemie@WearCheckRS.com | C44: Annemie Willer | D44: annemie@wearcheckrs.com | E44: WC319 | F44: RS | G44: WearCheck | H44: Longmeadow H/O | I44: 0716096197 | J44: Matched | K44: High | L44: No | M44: Exact company email match | N44: 7 | O44: Microsoft Defender for Office 365 (Plan 2)+Power BI Premium Per User+Microsoft Copilot Studio Viral Trial+Microsoft Power Apps Plan 2 Trial+Microsoft 365 E3+Microsoft Fabric (Free)+Microsoft Power Automate Free
A45: Aubrey Tshabalala | B45: Aubrey@WearCheckRS.com | C45: Aubrey Tshabalala | D45: aubrey@wearcheckRS.com | E45: WEC114 | F45: RS | G45: GP Consult | H45: Valterra - Mototolo | I45: 0824871527 | J45: Matched | K45: High | L45: No | M45: Exact company email match | N45: 2 | O45: Microsoft Defender for Office 365 (Plan 2)+Microsoft 365 Business Standard
A46: Bernard Lopi Molangoane | B46: lopi@WearCheckRS.com | C46: Bernard Lopi Molangoane | D46: lopim@wearcheck.co.za | E46: WC269 | F46: RS | G46: WearCheck | H46: Valterra - Mototolo | I46: 0636888886 | J46: Matched | K46: Medium | L46: No | M46: Matched via exact name | N46: 2 | O46: Microsoft Defender for Office 365 (Plan 2)+Microsoft 365 Business Standard
A47: Betty Monyepao | B47: betty@WearCheckRS.com | C47: Mmatapa Betty Monyepao | D47: betty@wearcheckrs.com | E47: WC465 | F47: RS | G47: WearCheck | H47: Valterra - Mototolo | I47: 0768125164 | J47: Matched | K47: High | L47: No | M47: Exact company email match | N47: 2 | O47: Microsoft Defender for Office 365 (Plan 2)+Microsoft 365 Business Standard
A48: Bianka De Beer | B48: Bianka@WearCheckRS.com | C48: Bianka de Beer | D48: Bianka@WearCheckRS.com | E48: WEC142 | F48: RS | G48: GP Consult | H48: Longmeadow H/O | I48: 0740317981 | J48: Matched | K48: High | L48: No | M48: Exact company email match | N48: 9 | O48: Microsoft Power Automate Free+Microsoft Power Apps Plan 2 Trial+Microsoft Fabric (Free)+Microsoft Copilot Studio Viral Trial+Microsoft Power Apps for Developer+Power Pages vTrial for Makers+Microsoft Defender for Office 365 (Plan 2)+Dynamics 365 Customer Insights Self-Service+Microsoft 365 Business Premium
A49: CJ Woller | B49: cj@WearCheckRS.com | C49: CJ Woller | D49: cj@wearcheckrs.com | E49: WEC120 | F49: RS | G49: GP Consult | H49: RBMR and PMR | I49: 0835965562 | J49: Matched | K49: High | L49: No | M49: Exact company email match | N49: 3 | O49: Microsoft Defender for Office 365 (Plan 2)+Microsoft Power Automate Free+Microsoft 365 Business Standard
A50: Chicco Tivane | B50: chicco@WearCheckRS.com | C50: Chicco Fransisco Tivane | D50: chicco@wearcheckrs.com | E50: WC380 | F50: RS | G50: WearCheck | H50: Steelpoort | I50: 0818190051 | J50: Matched | K50: High | L50: No | M50: Exact company email match | N50: 2 | O50: Microsoft Defender for Office 365 (Plan 2)+Microsoft 365 Business Standard
... A60: Eugene Scheepers | B60: eugene@WearCheckRS.com | C60: Eugene Scheepers | D60: eugene@wearcheckrs.com | E60: WEC090 | F60: RS | G60: GP Consult | H60: Neopak - Rosslyn | I60: 0790542385 | J60: Matched | K60: High | L60: No | M60: Exact company email match | N60: 2 | O60: Microsoft Defender for Office 365 (Plan 2)+Microsoft 365 Business Standard
A61: FLIRIRVM1 | B61: flirirvm1@WearCheckRS.com | F61: RS | J61: Mapped by rule | K61: High | L61: No | M61: Generic/shared/service account defaulted to RS per instruction | N61: 2 | O61: Microsoft Defender for Office 365 (Plan 2)+Microsoft 365 Business Standard
A62: Francios Pretorius | B62: franciosp@WearCheckRS.com | C62: Michael Francios Pretorius | D62: Franciosp@wearcheckRS.com | E62: WEC080 | F62: RS | G62: GP Consult | H62: Neopak - Rosslyn | I62: 0832773047 | J62: Matched | K62: High | L62: No | M62: Exact company email match | N62: 3 | O62: Microsoft Defender for Office 365 (Plan 2)+Microsoft Power Automate Free+Microsoft 365 Business Standard
A63: Francois Pienaar | B63: FrancoisP@WearCheckRS.com | C63: Jozua Francois Joubert Pienaar | D63: francoisp@wearcheckrs.com | E63: WEC111 | F63: RS | G63: GP Consult | H63: KwaZulu Natal - Hillside | I63: 0785618579 | J63: Matched | K63: High | L63: No | M63: Exact company email match | N63: 4 | O63: Microsoft Defender for Office 365 (Plan 2)+Microsoft Fabric (Free)+Microsoft 365 Business Standard+Microsoft Power Automate Free
A64: Francois van Eden | B64: francoisve@wearcheckrs.com | C64: Francois Jacobus van Eeden | D64: francoisve@wearcheckrs.com | E64: WC287 | F64: RS | G64: WearCheck | H64: Remote Centre | I64: 0828023072 | J64: Matched | K64: High | L64: No | M64: Exact company email match | N64: 4 | O64: Microsoft 365 Business Premium+Microsoft Defender for Office 365 (Plan 2)+Microsoft Fabric (Free)+Microsoft Power Automate Free
A65: Gustav Lourens | B65: gustav@WearCheckRS.com | C65: Gustav Lourens | D65: gustav@wearcheckrs.com | E65: WC270 | F65: RS | G65: WearCheck | H65: Springs | I65: 0829057631 | J65: Matched | K65: High | L65: No | M65: Exact company email match | N65: 2 | O65: Microsoft Defender for Office 365 (Plan 2)+Microsoft 365 Business Standard
A66: Hannest Koegelenberg | B66: hannest@WearCheckRS.com | C66: Hannest Koegelenberg | D66: hannest@wearcheckrs.com | E66: WEC047 | F66: RS | G66: GP Consult | H66: Springs | I66: 0823832542 | J66: Matched | K66: High | L66: No | M66: Exact company email match | N66: 2 | O66: Microsoft Defender for Office 365 (Plan 2)+Microsoft 365 Business Standard
A67: Hein Coetzer | B67: heinc@WearCheckRS.com | C67: Hein Coetzer | D67: heinc@wearcheckrs.com | E67: WEC129 | F67: RS | G67: GP Consult | H67: Samancor - TAS | I67: 0828887419 | J67: Matched | K67: High | L67: No | M67: Exact company email match | N67: 2 | O67: Microsoft Defender for Office 365 (Plan 2)+Microsoft 365 Business Standard
A68: Heinrich Kusel | B68: Heinrich@WearCheckRS.com | C68: Fritz Kusel | D68: heinrich@wearcheckrs.com | E68: WEC134 | F68: RS | G68: GP Consult | I68: 0796959474 | J68: Matched | K68: High | L68: No | M68: Exact company email match | N68: 2 | O68: Microsoft Defender for Office 365 (Plan 2)+Microsoft 365 Business Standard
A69: Henry Mherekumombe | B69: Henry@WearCheckRS.com | C69: Henry Mherekumombe | D69: henry@wearcheckrs.com | E69: WEC098 | F69: RS | G69: GP Consult | I69: 0664844117 | J69: Matched | K69: High | L69: No | M69: Exact company email match | N69: 3 | O69: Microsoft Defender for Office 365 (Plan 2)+Microsoft Power Automate Free+Microsoft 365 Business Standard
A70: Jaco De Beer | B70: jacodb@WearCheckRS.com | C70: Theunis Gerhardus Jacobus de Beer | D70: jacodb@wearcheckrs.com | E70: WEC097 | F70: RS | G70: GP Consult | H70: Roamer | I70: 0715236313 | J70: Matched | K70: High | L70: No | M70: Exact company email match | N70: 2 | O70: Microsoft Defender for Office 365 (Plan 2)+Microsoft 365 Business Standard
A71: Jaco Willer | B71: jaco@wearcheckrs.com | C71: Jacobus Johannes Willer | D71: jaco@wearcheckrs.com | E71: WC352 | F71: RS | G71: WearCheck | H71: Longmeadow H/O | I71: 0762681425 | J71: Matched | K71: High | L71: No | M71: Exact company email match | N71: 3 | O71: Microsoft 365 Business Premium+Microsoft Defender for Office 365 (Plan 2)+Microsoft Power Automate Free
A72: James Tshabalala | B72: james@WearCheckRS.com | C72: James Papayito Tshabalala | D72: james@WearCheckRS.com | E72: WC236 | F72: RS | G72: WearCheck | H72: Valterra - Mototolo | I72: 0662479987 | J72: Matched | K72: High | L72: No | M72: Exact company email match | N72: 4 | O72: Microsoft Defender for Office 365 (Plan 2)+Microsoft Power Automate Free+Microsoft Fabric (Free)+Microsoft 365 Business Standard
A73: Jean-Jacques | B73: jj@WearCheckRS.com | C73: Jean Jacques de Beer | D73: jj@wearcheckrs.com | E73: WEC137 | F73: RS | G73: GP Consult | H73: Remote Centre | I73: 0676700396 | J73: Matched | K73: High | L73: No | M73: Exact company email match | N73: 4 | O73: Microsoft 365 Business Premium+Microsoft Power Automate Free+Microsoft Fabric (Free)+Microsoft Defender for Office 365 (Plan 2)
A74: Johandre Oosthuizen | B74: johandre@WearCheckRS.com | C74: Johannes Andréas Oosthuizen | D74: johandre@wearcheckrs.com | E74: WEC089 | F74: RS | G74: GP Consult | H74: Samancor - Mooinooi | I74: 0834373969 | J74: Matched | K74: High | L74: No | M74: Exact company email match | N74: 2 | O74: Microsoft Defender for Office 365 (Plan 2)+Microsoft 365 Business Standard
A75: Kevin Henwood | B75: Kevin@WearCheckRS.com | C75: Kevin Henwood | D75: kevin@wearcheckrs.com | E75: WEC135 | F75: RS | G75: GP Consult | I75: 0829072077 | J75: Matched | K75: High | L75: No | M75: Exact company email match | N75: 2 | O75: Microsoft Defender for Office 365 (Plan 2)+Microsoft 365 Business Standard
A76: Leon Coetzee | B76: leon@WearCheckRS.com | C76: Leon Coetzee | D76: Leon@wearcheckrs.com | E76: WC455 | F76: RS | G76: WearCheck | H76: Steelpoort | I76: 0832881463 | J76: Matched | K76: High | L76: No | M76: Exact company email match | N76: 3 | O76: Microsoft Defender for Office 365 (Plan 2)+Microsoft Power Automate Free+Microsoft 365 Business Standard
A77: Lesego Khuthwane | B77: Lesego@WearCheckRS.com | C77: Lesego Khuthwane | D77: Lesego@WearCheckRS.com | E77: WEC126 | F77: RS | G77: GP Consult | H77: Longmeadow H/O | I77: 0849892260 | J77: Matched | K77: High | L77: No | M77: Exact company email match | N77: 9 | O77: Microsoft 365 E3+Power BI Premium Per User+Microsoft Defender for Office 365 (Plan 2)+Microsoft Power Apps for Developer+Power Pages vTrial for Makers+Microsoft Fabric (Free)+Microsoft Power Apps Plan 2 Trial+Microsoft Copilot Studio Viral Trial+Microsoft Power Automate Free
A78: Lloyd Ngobeni | B78: Lloyd@WearCheckRS.com | C78: Lloyd Ngobeni | D78: lloyd@wearcheckrs.com | E78: WEC099 | F78: RS | G78: GP Consult | H78: Valterra - Waterval | I78: 0664844084 | J78: Matched | K78: High | L78: No | M78: Exact company email match | N78: 3 | O78: Microsoft Defender for Office 365 (Plan 2)+Microsoft Power Automate Free+Microsoft 365 Business Standard
A79: Londolani Managa | B79: LondolaniM@WearCheckRS.com | C79: Londolani Managa | D79: londolanim@wearcheckrs.com | E79: WC648 | F79: RS | G79: WearCheck | H79: Samancor - MFC | I79: 0711682839 | J79: Matched | K79: High | L79: No | M79: Exact company email match | N79: 2 | O79: Microsoft Defender for Office 365 (Plan 2)+Microsoft 365 Business Standard
A80: Louis Peacock | B80: louis@WearCheckRS.com | C80: Louis Robert Peacock | D80: louis@wearcheckrs.com | E80: WC277 | F80: RS | G80: WearCheck | H80: Longmeadow H/O | J80: Matched | K80: High | L80: No | M80: Exact company email match | N80: 4 | O80: Microsoft Defender for Office 365 (Plan 2)+Power BI Premium Per User+Microsoft 365 E3+Microsoft Power Automate Free
A81: Louis Zoho | B81: Louis_Zoho@WearCheckRS.com | C81: Louis Robert Peacock | D81: louis@wearcheckrs.com | E81: WC277 | F81: RS | G81: WearCheck | H81: Longmeadow H/O | J81: Matched | K81: Medium | L81: No | M81: Matched via email alias/local-part | N81: 1 | O81: Microsoft 365 Business Standard
A82: Lubby Lubis | B82: lubby@WearCheckRS.com | C82: Labby Jeffrey Lubis | D82: lubby@wearcheckrs.com | E82: WEC118 | F82: RS | G82: GP Consult | H82: Samancor - Doornbosch | I82: 0796915943 | J82: Matched | K82: High | L82: No | M82: Exact company email match | N82: 2 | O82: Microsoft Defender for Office 365 (Plan 2)+Microsoft 365 Business Standard
A83: Lucas Luus | B83: lucas@WearCheckRS.com | C83: Lucas Johannes Bartel Luus | D83: lucas@wearcheckrs.com | E83: WEC068 | F83: RS | G83: GP Consult | H83: Kathu | I83: 0763455962 | J83: Matched | K83: High | L83: No | M83: Exact company email match | N83: 2 | O83: Microsoft Defender for Office 365 (Plan 2)+Microsoft 365 Business Standard
A84: Mandé Coetzee | B84: Mande@WearCheckRS.com | C84: Mandé Coetzee | D84: mande@wearcheckrs.com | E84: WEC116 | F84: RS | G84: GP Consult | H84: Longmeadow H/O | I84: 079 128 9133 | J84: Matched | K84: High | L84: No | M84: Exact company email match | N84: 4 | O84: Microsoft Defender for Office 365 (Plan 2)+Microsoft Fabric (Free)+Microsoft Power Automate Free+Microsoft 365 E3
A85: Marcel Schoeman | B85: Marcel@WearCheckRS.com | C85: Marcel Schoeman | D85: marcel@wearcheckrs.com | E85: WEC102 | F85: RS | G85: GP Consult | H85: Roamer | I85: 0767946353 | J85: Matched | K85: High | L85: No | M85: Exact company email match | N85: 3 | O85: Microsoft 365 Business Premium+Microsoft Defender for Office 365 (Plan 2)+Microsoft Fabric (Free)
A86: Mariette Du Rand | B86: mariette@WearCheckRS.com | C86: Mariette du Rand | D86: mariette@wearcheckrs.com | E86: WEC109 | F86: RS | G86: GP Consult | H86: Longmeadow H/O | I86: 0837835814 | J86: Matched | K86: High | L86: No | M86: Exact company email match | N86: 2 | O86: Microsoft 365 Business Premium+Microsoft Defender for Office 365 (Plan 2)
A87: Marshall Rasimphi | B87: marshallr@WearCheckRS.com | C87: Ailwel Marshall Rasimphi | D87: marshallr@wearcheckrs.com | E87: WEC094 | F87: RS | G87: GP Consult | H87: Valterra - Waterval | I87: 0768219444 | J87: Matched | K87: High | L87: No | M87: Exact company email match | N87: 2 | O87: Microsoft Defender for Office 365 (Plan 2)+Microsoft 365 Business Standard
A88: Marthinus Admin Account | B88: marthinus_admin@wearcheckrs.com | F88: RS | J88: Mapped by rule | K88: High | L88: No | M88: Generic/shared/service account defaulted to RS per instruction | N88: 2 | O88: Microsoft Power Automate Free+Microsoft Fabric (Free)
A89: Martiens Van Aarde | B89: martiens@WearCheckRS.com | C89: Marthinus Jacobus van Aarde | D89: martiens@wearcheckrs.com | E89: WEC106 | F89: RS | G89: GP Consult | H89: Eskom - Matimba | I89: 0834550909 | J89: Matched | K89: High | L89: No | M89: Exact company email match | N89: 3 | O89: Microsoft Power Automate Free+Microsoft Defender for Office 365 (Plan 2)+Microsoft 365 Business Standard
A90: Megan Salzwedel | B90: Megan@wearcheckrs.com | C90: Megan Salzwedel | D90: megan@wearcheckrs.com | E90: WEC104 | F90: RS | G90: GP Consult | H90: Longmeadow H/O | I90: 0720591125 | J90: Matched | K90: High | L90: No | M90: Exact company email match | N90: 5 | O90: Microsoft 365 Business Premium+Microsoft Defender for Office 365 (Plan 2)+Microsoft Power Apps Plan 2 Trial+Microsoft Fabric (Free)+Microsoft Power Automate Free
A91: Meshack Nxumalo | B91: meshack@WearCheckRS.com | C91: Meshack Welcome Nxumalo | D91: meshack@wearcheckrs.com | E91: WEC088 | F91: RS | G91: GP Consult | H91: KwaZulu Natal | I91: 0638165404 | J91: Matched | K91: High | L91: No | M91: Exact company email match | N91: 2 | O91: Microsoft Defender for Office 365 (Plan 2)+Microsoft 365 Business Standard
A92: Micheal Masemola | B92: michealm@WearCheckRS.com | C92: Seporo Micheal Masemola | D92: michealm@wearcheckrs.com | E92: WC291 | F92: RS | G92: WearCheck | H92: Valterra - Mototolo | I92: 0820828925 | J92: Matched | K92: High | L92: No | M92: Exact company email match | N92: 2 | O92: Microsoft Defender for Office 365 (Plan 2)+Microsoft 365 Business Standard
A93: Micheal Pretorius | B93: micheal@WearCheckRS.com | C93: Micheal Francios Pretorius | D93: micheal@wearcheckrs.com | E93: WEC076 | F93: RS | G93: GP Consult | H93: RBMR and PMR | I93: 0828864900 | J93: Matched | K93: High | L93: No | M93: Exact company email match | N93: 3 | O93: Microsoft Defender for Office 365 (Plan 2)+Microsoft Power Automate Free+Microsoft 365 Business Standard
A94: Morne Alberts | B94: mornea@wearcheckrs.com | C94: Mórne Alberts | D94: mornea@wearcheckrs.com | E94: WC361 | F94: RS | G94: WearCheck | H94: Remote Centre | I94: 0810132168 | J94: Matched | K94: High | L94: No | M94: Exact company email match | N94: 3 | O94: Microsoft 365 Business Premium+Microsoft Defender for Office 365 (Plan 2)+Microsoft Fabric (Free)
A95: Nadhira Bux | B95: Nadhira@WearCheckRS.com | C95: Nadhira Bux | D95: nadhira@wearcheckrs.com | E95: WEC113 | F95: RS | G95: GP Consult | H95: Longmeadow H/O | I95: 0625831366 | J95: Matched | K95: High | L95: No | M95: Exact company email match | N95: 7 | O95: Microsoft 365 Business Premium+Microsoft Defender for Office 365 (Plan 2)+Microsoft Power Apps for Developer+Power Pages vTrial for Makers+Microsoft Copilot Studio Viral Trial+Microsoft Power Automate Free+Microsoft Fabric (Free)
A96: No Reply | B96: noreply@WearCheckRS.com | F96: RS | J96: Mapped by rule | K96: High | L96: No | M96: Generic/shared/service account defaulted to RS per instruction | N96: 2 | O96: Microsoft Defender for Office 365 (Plan 2)+Microsoft 365 Business Standard
A97: Nomvula Mkhize | B97: NomvulaM@WearCheckRS.com | C97: Nomvula Mkhize | D97: nomvulam@wearcheckrs.com | E97: WC651 | F97: RS | G97: WearCheck | H97: Samancor - MFC | I97: 0747023211 | J97: Matched | K97: High | L97: No | M97: Exact company email match | N97: 2 | O97: Microsoft Defender for Office 365 (Plan 2)+Microsoft 365 Business Standard
A98: Passwell Mashoeou | B98: passwell@WearCheckRS.com | C98: Putaneng Paswell Mashoeu | D98: passwell@wearcheckrs.com | E98: WC348 | F98: RS | G98: WearCheck | H98: Valterra - Mototolo | I98: 06364888867 | J98: Matched | K98: High | L98: No | M98: Exact company email match | N98: 2 | O98: Microsoft Defender for Office 365 (Plan 2)+Microsoft 365 Business Standard
A99: Peet Peacock | B99: Peet@WearCheckRS.com | C99: Petrus Johannes Peacock | D99: Peet@wearcheckrs.com | E99: WC520 | F99: RS | G99: WearCheck | I99: 0716700710 | J99: Matched | K99: High | L99: No | M99: Exact company email match | N99: 2 | O99: Microsoft Defender for Office 365 (Plan 2)+Microsoft 365 E3
A100: Percy Hall | B100: Percy@WearCheckRS.com | C100: Percy Hall | D100: percy@wearcheckrs.com | E100: WEC115 | F100: RS | G100: GP Consult | H100: Seriti - Khutala | I100: 0826828862 / 0827307344 | J100: Matched | K100: High | L100: No | M100: Exact company email match | N100: 2 | O100: Microsoft Defender for Office 365 (Plan 2)+Microsoft 365 Business Standard
A101: Permission Melele | B101: permission@WearCheckRS.com | C101: Katishi Permission Malele | D101: permission@wearcheckrs.com | E101: WC393 | F101: RS | G101: WearCheck | H101: Valterra - Mototolo | I101: 606314865 | J101: Matched | K101: High | L101: No | M101: Exact company email match | N101: 2 | O101: Microsoft Defender for Office 365 (Plan 2)+Microsoft 365 Business Standard
A102: Philip Schutte | B102: philip@WearCheckRS.com | C102: Philippus Jacobus Wilhelmus (Philip) Schutte | D102: philip@wearcheckrs.com | E102: WC253 | F102: RS | G102: WearCheck | H102: Longmeadow H/O | I102: 0769829774 | J102: Matched | K102: High | L102: No | M102: Exact company email match | N102: 4 | O102: Microsoft Defender for Office 365 (Plan 2)+Microsoft Fabric (Free)+Microsoft 365 E3+Microsoft Power Automate Free
A103: Philip Zoho | B103: Philip_Zoho@WearCheckRS.com | C103: Philippus Jacobus Wilhelmus (Philip) Schutte | D103: philip@wearcheckrs.com | E103: WC253 | F103: RS | G103: WearCheck | H103: Longmeadow H/O | I103: 0769829774 | J103: Matched | K103: Medium | L103: No | M103: Matched via email alias/local-part | N103: 1 | O103: Microsoft 365 Business Standard
A104: Power Bi Gateway Service Account | B104: srv_acc_pbi_gw@WearCheckRS.com | F104: RS | J104: Mapped by rule | K104: High | L104: No | M104: Generic/shared/service account defaulted to RS per instruction | N104: 3 | O104: Microsoft Power Automate Free+Power BI Premium Per User+Exchange Online (Plan 1)
A105: Printer Account | B105: printer@WearCheckRS.com | F105: RS | J105: Mapped by rule | K105: High | L105: No | M105: Generic/shared/service account defaulted to RS per instruction | N105: 1 | O105: Exchange Online (Plan 1)
A106: Rakcal Balaram | B106: rakcal@WearCheckRS.com | C106: Rakcal Monroe Balaram | D106: rakcal@wearcheckrs.com | E106: WEC074 | F106: RS | G106: GP Consult | H106: KwaZulu Natal - Tronox | I106: 0749705467 | J106: Matched | K106: High | L106: No | M106: Exact company email match | N106: 2 | O106: Microsoft Defender for Office 365 (Plan 2)+Microsoft 365 Business Standard
A107: Reinier Kalp | B107: reinierk@wearcheckrs.com | C107: Reinier Kalp | D107: reinierk@wearcheckrs.com | E107: WC382 | F107: RS | G107: WearCheck | H107: Remote Centre | I107: 0810132176 | J107: Matched | K107: High | L107: No | M107: Exact company email match | N107: 4 | O107: Microsoft 365 Business Premium+Microsoft Defender for Office 365 (Plan 2)+Microsoft Power Automate Free+Microsoft Fabric (Free)
A108: Remote Analysis Centre Admin | B108: rac.admin@WearCheckRS.com | F108: RS | J108: Mapped by rule | K108: High | L108: No | M108: Generic/shared/service account defaulted to RS per instruction | N108: 2 | O108: Microsoft Defender for Office 365 (Plan 2)+Microsoft 365 E3
A109: Riaan De Beer | B109: RiaandB@WearCheckRS.com | C109: Riaan de Beer | D109: riaandb@wearcheckrs.com | E109: WC363 | F109: RS | G109: WearCheck | H109: Valterra - Waterval | I109: 0745880347 | J109: Matched | K109: High | L109: No | M109: Exact company email match | N109: 4 | O109: Microsoft Defender for Office 365 (Plan 2)+Microsoft Fabric (Free)+Microsoft 365 Business Standard+Microsoft Power Automate Free
A110: Rynhardt Meyer | B110: Rynhardt@WearCheckRS.com | C110: Rynhardt Meyer | D110: rynhardt@wearcheckrs.com | E110: WEC096 | F110: RS | G110: GP Consult | H110: Valterra - Waterval | I110: 0649557747 | J110: Matched | K110: High | L110: No | M110: Exact company email match | N110: 2 | O110: Microsoft Defender for Office 365 (Plan 2)+Microsoft 365 Business Standard
A111: Sergent Thlou | B111: sergent@WearCheckRS.com | C111: Sergant Sakhile Tlou | D111: sergent@wearcheckrs.com | E111: WC264 | F111: RS | G111: Wearcheck | H111: Roamer | I111: 0828827758 | J111: Matched | K111: High | L111: No | M111: Exact company email match | N111: 2 | O111: Microsoft Defender for Office 365 (Plan 2)+Microsoft 365 Business Standard
A112: Service Account SQL DB Mail | B112: srv_acc_sql_mail@WearCheckRS.com | F112: RS | J112: Mapped by rule | K112: High | L112: No | M112: Generic/shared/service account defaulted to RS per instruction | N112: 1 | O112: Exchange Online (Plan 1)
A113: Service Account SSRS | B113: srv_acc_ssrs@WearCheckRS.com | F113: RS | J113: Mapped by rule | K113: High | L113: No | M113: Generic/shared/service account defaulted to RS per instruction | N113: 2 | O113: Power Automate per user plan+Microsoft Power Automate Free
A114: Shaun Janse van Rensburg | B114: shaun@WearCheckRS.com | C114: Shaun Janse van Rensburg | D114: shaun@wearcheckrs.com | E114: WEC136 | F114: RS | G114: GP Consult | I114: 082 497 1146 | J114: Matched | K114: High | L114: No | M114: Exact company email match | N114: 2 | O114: Microsoft Defender for Office 365 (Plan 2)+Microsoft 365 Business Standard
A115: Shivon Alberts | B115: Shivon@WearCheckRS.com | C115: Shivon Chantelle Alberts | D115: shivon@wearcheckrs.com | E115: WEC130 | F115: RS | G115: GP Consult | H115: Longmeadow H/O | I115: 0793152710 | J115: Matched | K115: High | L115: No | M115: Exact company email match | N115: 3 | O115: Microsoft 365 Business Premium+Microsoft Defender for Office 365 (Plan 2)+Microsoft Fabric (Free)
...

Sheet Allocation_Detail
A1: Licensed Email | B1: Licensed Display Name | C1: Division | D1: Employee Number | E1: Match Status | F1: Review Required | G1: SKU | H1: Billing Hint | I1: Monthly Invoice Amount | J1: Active Users on SKU | K1: Unit Cost | L1: Allocated Cost | M1: Mapping Note
A2: Antonio.Ehrke@WearCheckRS.com | B2: Antonio Ehrke | C2: AFS | D2: WC503 | E2: Matched | F2: No | G2: Microsoft Defender for Office 365 (Plan 2) | H2: Review invoice | I2: =IFERROR(VLOOKUP(G2,SKU_Cost_Input!$A$2:$E$15,4,FALSE),0) -> 0 | J2: =IFERROR(VLOOKUP(G2,SKU_Cost_Input!$A$2:$E$15,2,FALSE),0) -> 130 | K2: =IF(J2=0,0,I2/J2) -> 0 | L2: =K2 -> 0 | M2: Exact company email match
A3: Antonio.Ehrke@WearCheckRS.com | B3: Antonio Ehrke | C3: AFS | D3: WC503 | E3: Matched | F3: No | G3: Microsoft 365 Business Standard | H3: Likely billable | I3: =IFERROR(VLOOKUP(G3,SKU_Cost_Input!$A$2:$E$15,4,FALSE),0) -> 0 | J3: =IFERROR(VLOOKUP(G3,SKU_Cost_Input!$A$2:$E$15,2,FALSE),0) -> 100 | K3: =IF(J3=0,0,I3/J3) -> 0 | L3: =K3 -> 0 | M3: Exact company email match
A4: Arnold@WearCheckRS.com | B4: Arnold van Zyl | C4: AFS | D4: WC526 | E4: Matched | F4: No | G4: Microsoft Defender for Office 365 (Plan 2) | H4: Review invoice | I4: =IFERROR(VLOOKUP(G4,SKU_Cost_Input!$A$2:$E$15,4,FALSE),0) -> 0 | J4: =IFERROR(VLOOKUP(G4,SKU_Cost_Input!$A$2:$E$15,2,FALSE),0) -> 130 | K4: =IF(J4=0,0,I4/J4) -> 0 | L4: =K4 -> 0 | M4: Exact company email match
A5: Arnold@WearCheckRS.com | B5: Arnold van Zyl | C5: AFS | D5: WC526 | E5: Matched | F5: No | G5: Microsoft 365 Business Standard | H5: Likely billable | I5: =IFERROR(VLOOKUP(G5,SKU_Cost_Input!$A$2:$E$15,4,FALSE),0) -> 0 | J5: =IFERROR(VLOOKUP(G5,SKU_Cost_Input!$A$2:$E$15,2,FALSE),0) -> 100 | K5: =IF(J5=0,0,I5/J5) -> 0 | L5: =K5 -> 0 | M5: Exact company email match
A6: colleen.pyper@WearCheckRS.com | B6: Colleen Pyper | C6: AFS | D6: WC486 | E6: Matched | F6: No | G6: Microsoft Defender for Office 365 (Plan 2) | H6: Review invoice | I6: =IFERROR(VLOOKUP(G6,SKU_Cost_Input!$A$2:$E$15,4,FALSE),0) -> 0 | J6: =IFERROR(VLOOKUP(G6,SKU_Cost_Input!$A$2:$E$15,2,FALSE),0) -> 130 | K6: =IF(J6=0,0,I6/J6) -> 0 | L6: =K6 -> 0 | M6: Exact company email match
A7: colleen.pyper@WearCheckRS.com | B7: Colleen Pyper | C7: AFS | D7: WC486 | E7: Matched | F7: No | G7: Microsoft Power Automate Free | H7: Likely free / trial | I7: =IFERROR(VLOOKUP(G7,SKU_Cost_Input!$A$2:$E$15,4,FALSE),0) -> 0 | J7: =IFERROR(VLOOKUP(G7,SKU_Cost_Input!$A$2:$E$15,2,FALSE),0) -> 52 | K7: =IF(J7=0,0,I7/J7) -> 0 | L7: =K7 -> 0 | M7: Exact company email match
A8: colleen.pyper@WearCheckRS.com | B8: Colleen Pyper | C8: AFS | D8: WC486 | E8: Matched | F8: No | G8: Microsoft 365 Business Standard | H8: Likely billable | I8: =IFERROR(VLOOKUP(G8,SKU_Cost_Input!$A$2:$E$15,4,FALSE),0) -> 0 | J8: =IFERROR(VLOOKUP(G8,SKU_Cost_Input!$A$2:$E$15,2,FALSE),0) -> 100 | K8: =IF(J8=0,0,I8/J8) -> 0 | L8: =K8 -> 0 | M8: Exact company email match
A9: edwin@WearCheckRS.com | B9: Edwin Gibbons | C9: AFS | D9: WEC138 | E9: Matched | F9: No | G9: Microsoft Defender for Office 365 (Plan 2) | H9: Review invoice | I9: =IFERROR(VLOOKUP(G9,SKU_Cost_Input!$A$2:$E$15,4,FALSE),0) -> 0 | J9: =IFERROR(VLOOKUP(G9,SKU_Cost_Input!$A$2:$E$15,2,FALSE),0) -> 130 | K9: =IF(J9=0,0,I9/J9) -> 0 | L9: =K9 -> 0 | M9: Exact company email match
A10: edwin@WearCheckRS.com | B10: Edwin Gibbons | C10: AFS | D10: WEC138 | E10: Matched | F10: No | G10: Microsoft 365 Business Standard | H10: Likely billable | I10: =IFERROR(VLOOKUP(G10,SKU_Cost_Input!$A$2:$E$15,4,FALSE),0) -> 0 | J10: =IFERROR(VLOOKUP(G10,SKU_Cost_Input!$A$2:$E$15,2,FALSE),0) -> 100 | K10: =IF(J10=0,0,I10/J10) -> 0 | L10: =K10 -> 0 | M10: Exact company email match
A11: ethel.mienie@WearCheckRS.com | B11: Ethel Mienie | C11: AFS | D11: WC488 | E11: Matched | F11: No | G11: Microsoft Defender for Office 365 (Plan 2) | H11: Review invoice | I11: =IFERROR(VLOOKUP(G11,SKU_Cost_Input!$A$2:$E$15,4,FALSE),0) -> 0 | J11: =IFERROR(VLOOKUP(G11,SKU_Cost_Input!$A$2:$E$15,2,FALSE),0) -> 130 | K11: =IF(J11=0,0,I11/J11) -> 0 | L11: =K11 -> 0 | M11: Exact company email match
A12: ethel.mienie@WearCheckRS.com | B12: Ethel Mienie | C12: AFS | D12: WC488 | E12: Matched | F12: No | G12: Microsoft 365 Business Standard | H12: Likely billable | I12: =IFERROR(VLOOKUP(G12,SKU_Cost_Input!$A$2:$E$15,4,FALSE),0) -> 0 | J12: =IFERROR(VLOOKUP(G12,SKU_Cost_Input!$A$2:$E$15,2,FALSE),0) -> 100 | K12: =IF(J12=0,0,I12/J12) -> 0 | L12: =K12 -> 0 | M12: Exact company email match
A13: Evert@WearCheckRS.com | B13: Evert Viljoen | C13: AFS | D13: WC497 | E13: Matched | F13: No | G13: Microsoft Defender for Office 365 (Plan 2) | H13: Review invoice | I13: =IFERROR(VLOOKUP(G13,SKU_Cost_Input!$A$2:$E$15,4,FALSE),0) -> 0 | J13: =IFERROR(VLOOKUP(G13,SKU_Cost_Input!$A$2:$E$15,2,FALSE),0) -> 130 | K13: =IF(J13=0,0,I13/J13) -> 0 | L13: =K13 -> 0 | M13: Matched via exact name
... A43: teresa.venter@WearCheckRS.com | B43: Teresa Venter | C43: AFS | D43: WC487 | E43: Matched | F43: No | G43: Microsoft 365 Business Standard | H43: Likely billable | I43: =IFERROR(VLOOKUP(G43,SKU_Cost_Input!$A$2:$E$15,4,FALSE),0) -> 0 | J43: =IFERROR(VLOOKUP(G43,SKU_Cost_Input!$A$2:$E$15,2,FALSE),0) -> 100 | K43: =IF(J43=0,0,I43/J43) -> 0 | L43: =K43 -> 0 | M43: Exact company email match
A44: Jean-Pierre@WearCheckRS.com | B44: Jean Pierre Du Plessis | C44: AFS | E44: Matched | F44: Yes | G44: Microsoft 365 Business Standard | H44: Likely billable | I44: =IFERROR(VLOOKUP(G44,SKU_Cost_Input!$A$2:$E$15,4,FALSE),0) -> 0 | J44: =IFERROR(VLOOKUP(G44,SKU_Cost_Input!$A$2:$E$15,2,FALSE),0) -> 100 | K44: =IF(J44=0,0,I44/J44) -> 0 | L44: =K44 -> 0 | M44: Matched via exact name
A45: Jean-Pierre@WearCheckRS.com | B45: Jean Pierre Du Plessis | C45: AFS | E45: Matched | F45: Yes | G45: Microsoft Defender for Office 365 (Plan 2) | H45: Review invoice | I45: =IFERROR(VLOOKUP(G45,SKU_Cost_Input!$A$2:$E$15,4,FALSE),0) -> 0 | J45: =IFERROR(VLOOKUP(G45,SKU_Cost_Input!$A$2:$E$15,2,FALSE),0) -> 130 | K45: =IF(J45=0,0,I45/J45) -> 0 | L45: =K45 -> 0 | M45: Matched via exact name
A46: Joe@WearCheckRS.com | B46: Joe Kies | C46: AFS | D46: WC531 | E46: Matched | F46: Yes | G46: Microsoft Power Automate Free | H46: Likely free / trial | I46: =IFERROR(VLOOKUP(G46,SKU_Cost_Input!$A$2:$E$15,4,FALSE),0) -> 0 | J46: =IFERROR(VLOOKUP(G46,SKU_Cost_Input!$A$2:$E$15,2,FALSE),0) -> 52 | K46: =IF(J46=0,0,I46/J46) -> 0 | L46: =K46 -> 0 | M46: Matched via manual alias/name rule
A47: Joe@WearCheckRS.com | B47: Joe Kies | C47: AFS | D47: WC531 | E47: Matched | F47: Yes | G47: Microsoft 365 Business Standard | H47: Likely billable | I47: =IFERROR(VLOOKUP(G47,SKU_Cost_Input!$A$2:$E$15,4,FALSE),0) -> 0 | J47: =IFERROR(VLOOKUP(G47,SKU_Cost_Input!$A$2:$E$15,2,FALSE),0) -> 100 | K47: =IF(J47=0,0,I47/J47) -> 0 | L47: =K47 -> 0 | M47: Matched via manual alias/name rule
A48: Joe@WearCheckRS.com | B48: Joe Kies | C48: AFS | D48: WC531 | E48: Matched | F48: Yes | G48: Microsoft Power Apps Plan 2 Trial | H48: Likely free / trial | I48: =IFERROR(VLOOKUP(G48,SKU_Cost_Input!$A$2:$E$15,4,FALSE),0) -> 0 | J48: =IFERROR(VLOOKUP(G48,SKU_Cost_Input!$A$2:$E$15,2,FALSE),0) -> 6 | K48: =IF(J48=0,0,I48/J48) -> 0 | L48: =K48 -> 0 | M48: Matched via manual alias/name rule
A49: Joe@WearCheckRS.com | B49: Joe Kies | C49: AFS | D49: WC531 | E49: Matched | F49: Yes | G49: Microsoft Fabric (Free) | H49: Likely free / trial | I49: =IFERROR(VLOOKUP(G49,SKU_Cost_Input!$A$2:$E$15,4,FALSE),0) -> 0 | J49: =IFERROR(VLOOKUP(G49,SKU_Cost_Input!$A$2:$E$15,2,FALSE),0) -> 50 | K49: =IF(J49=0,0,I49/J49) -> 0 | L49: =K49 -> 0 | M49: Matched via manual alias/name rule
A50: Joe@WearCheckRS.com | B50: Joe Kies | C50: AFS | D50: WC531 | E50: Matched | F50: Yes | G50: Microsoft Copilot Studio Viral Trial | H50: Likely free / trial | I50: =IFERROR(VLOOKUP(G50,SKU_Cost_Input!$A$2:$E$15,4,FALSE),0) -> 0 | J50: =IFERROR(VLOOKUP(G50,SKU_Cost_Input!$A$2:$E$15,2,FALSE),0) -> 7 | K50: =IF(J50=0,0,I50/J50) -> 0 | L50: =K50 -> 0 | M50: Matched via manual alias/name rule
A51: Joe@WearCheckRS.com | B51: Joe Kies | C51: AFS | D51: WC531 | E51: Matched | F51: Yes | G51: Microsoft Power Apps for Developer | H51: Review invoice | I51: =IFERROR(VLOOKUP(G51,SKU_Cost_Input!$A$2:$E$15,4,FALSE),0) -> 0 | J51: =IFERROR(VLOOKUP(G51,SKU_Cost_Input!$A$2:$E$15,2,FALSE),0) -> 6 | K51: =IF(J51=0,0,I51/J51) -> 0 | L51: =K51 -> 0 | M51: Matched via manual alias/name rule
A52: Joe@WearCheckRS.com | B52: Joe Kies | C52: AFS | D52: WC531 | E52: Matched | F52: Yes | G52: Power Pages vTrial for Makers | H52: Likely free / trial | I52: =IFERROR(VLOOKUP(G52,SKU_Cost_Input!$A$2:$E$15,4,FALSE),0) -> 0 | J52: =IFERROR(VLOOKUP(G52,SKU_Cost_Input!$A$2:$E$15,2,FALSE),0) -> 5 | K52: =IF(J52=0,0,I52/J52) -> 0 | L52: =K52 -> 0 | M52: Matched via manual alias/name rule
A53: Joe@WearCheckRS.com | B53: Joe Kies | C53: AFS | D53: WC531 | E53: Matched | F53: Yes | G53: Microsoft Defender for Office 365 (Plan 2) | H53: Review invoice | I53: =IFERROR(VLOOKUP(G53,SKU_Cost_Input!$A$2:$E$15,4,FALSE),0) -> 0 | J53: =IFERROR(VLOOKUP(G53,SKU_Cost_Input!$A$2:$E$15,2,FALSE),0) -> 130 | K53: =IF(J53=0,0,I53/J53) -> 0 | L53: =K53 -> 0 | M53: Matched via manual alias/name rule
A54: Joe@WearCheckRS.com | B54: Joe Kies | C54: AFS | D54: WC531 | E54: Matched | F54: Yes | G54: Dynamics 365 Customer Insights Self-Service | H54: Review invoice | I54: =IFERROR(VLOOKUP(G54,SKU_Cost_Input!$A$2:$E$15,4,FALSE),0) -> 0 | J54: =IFERROR(VLOOKUP(G54,SKU_Cost_Input!$A$2:$E$15,2,FALSE),0) -> 3 | K54: =IF(J54=0,0,I54/J54) -> 0 | L54: =K54 -> 0 | M54: Matched via manual alias/name rule
A55: Johan.Stols@WearCheckRS.com | B55: Johan Stols | C55: AFS | D55: WC508 | E55: Matched | F55: Yes | G55: Microsoft Defender for Office 365 (Plan 2) | H55: Review invoice | I55: =IFERROR(VLOOKUP(G55,SKU_Cost_Input!$A$2:$E$15,4,FALSE),0) -> 0 | J55: =IFERROR(VLOOKUP(G55,SKU_Cost_Input!$A$2:$E$15,2,FALSE),0) -> 130 | K55: =IF(J55=0,0,I55/J55) -> 0 | L55: =K55 -> 0 | M55: Matched via manual alias/name rule
A56: Johan.Stols@WearCheckRS.com | B56: Johan Stols | C56: AFS | D56: WC508 | E56: Matched | F56: Yes | G56: Microsoft Power Automate Free | H56: Likely free / trial | I56: =IFERROR(VLOOKUP(G56,SKU_Cost_Input!$A$2:$E$15,4,FALSE),0) -> 0 | J56: =IFERROR(VLOOKUP(G56,SKU_Cost_Input!$A$2:$E$15,2,FALSE),0) -> 52 | K56: =IF(J56=0,0,I56/J56) -> 0 | L56: =K56 -> 0 | M56: Matched via manual alias/name rule
A57: Johan.Stols@WearCheckRS.com | B57: Johan Stols | C57: AFS | D57: WC508 | E57: Matched | F57: Yes | G57: Microsoft 365 Business Standard | H57: Likely billable | I57: =IFERROR(VLOOKUP(G57,SKU_Cost_Input!$A$2:$E$15,4,FALSE),0) -> 0 | J57: =IFERROR(VLOOKUP(G57,SKU_Cost_Input!$A$2:$E$15,2,FALSE),0) -> 100 | K57: =IF(J57=0,0,I57/J57) -> 0 | L57: =K57 -> 0 | M57: Matched via manual alias/name rule
... A95: rohan@WearCheckRS.com | B95: Rohan Willer | C95: Namibia | D95: WC381 | E95: Matched | F95: No | G95: Microsoft Power Automate Free | H95: Likely free / trial | I95: =IFERROR(VLOOKUP(G95,SKU_Cost_Input!$A$2:$E$15,4,FALSE),0) -> 0 | J95: =IFERROR(VLOOKUP(G95,SKU_Cost_Input!$A$2:$E$15,2,FALSE),0) -> 52 | K95: =IF(J95=0,0,I95/J95) -> 0 | L95: =K95 -> 0 | M95: Exact company email match
A96: afs_app@WearCheckRS.com | B96: AFS Application | C96: RS | E96: Mapped by rule | F96: No | G96: Microsoft Power Automate Free | H96: Likely free / trial | I96: =IFERROR(VLOOKUP(G96,SKU_Cost_Input!$A$2:$E$15,4,FALSE),0) -> 0 | J96: =IFERROR(VLOOKUP(G96,SKU_Cost_Input!$A$2:$E$15,2,FALSE),0) -> 52 | K96: =IF(J96=0,0,I96/J96) -> 0 | L96: =K96 -> 0 | M96: Generic/shared/service account defaulted to RS per instruction
A97: afs_app@WearCheckRS.com | B97: AFS Application | C97: RS | E97: Mapped by rule | F97: No | G97: Exchange Online (Plan 1) | H97: Likely billable | I97: =IFERROR(VLOOKUP(G97,SKU_Cost_Input!$A$2:$E$15,4,FALSE),0) -> 0 | J97: =IFERROR(VLOOKUP(G97,SKU_Cost_Input!$A$2:$E$15,2,FALSE),0) -> 4 | K97: =IF(J97=0,0,I97/J97) -> 0 | L97: =K97 -> 0 | M97: Generic/shared/service account defaulted to RS per instruction
A98: admin@WearCheckRS.com | B98: Admin | C98: RS | E98: Mapped by rule | F98: No | G98: Microsoft Defender for Office 365 (Plan 2) | H98: Review invoice | I98: =IFERROR(VLOOKUP(G98,SKU_Cost_Input!$A$2:$E$15,4,FALSE),0) -> 0 | J98: =IFERROR(VLOOKUP(G98,SKU_Cost_Input!$A$2:$E$15,2,FALSE),0) -> 130 | K98: =IF(J98=0,0,I98/J98) -> 0 | L98: =K98 -> 0 | M98: Generic/shared/service account defaulted to RS per instruction
A99: admin@WearCheckRS.com | B99: Admin | C99: RS | E99: Mapped by rule | F99: No | G99: Microsoft Fabric (Free) | H99: Likely free / trial | I99: =IFERROR(VLOOKUP(G99,SKU_Cost_Input!$A$2:$E$15,4,FALSE),0) -> 0 | J99: =IFERROR(VLOOKUP(G99,SKU_Cost_Input!$A$2:$E$15,2,FALSE),0) -> 50 | K99: =IF(J99=0,0,I99/J99) -> 0 | L99: =K99 -> 0 | M99: Generic/shared/service account defaulted to RS per instruction
A100: admin@WearCheckRS.com | B100: Admin | C100: RS | E100: Mapped by rule | F100: No | G100: Microsoft 365 E3 | H100: Likely billable | I100: =IFERROR(VLOOKUP(G100,SKU_Cost_Input!$A$2:$E$15,4,FALSE),0) -> 0 | J100: =IFERROR(VLOOKUP(G100,SKU_Cost_Input!$A$2:$E$15,2,FALSE),0) -> 14 | K100: =IF(J100=0,0,I100/J100) -> 0 | L100: =K100 -> 0 | M100: Generic/shared/service account defaulted to RS per instruction
A101: A.Ludick@WearCheckRS.com | B101: Adri Ludick | C101: RS | D101: WC492 | E101: Matched | F101: No | G101: Microsoft 365 Business Premium | H101: Likely billable | I101: =IFERROR(VLOOKUP(G101,SKU_Cost_Input!$A$2:$E$15,4,FALSE),0) -> 0 | J101: =IFERROR(VLOOKUP(G101,SKU_Cost_Input!$A$2:$E$15,2,FALSE),0) -> 21 | K101: =IF(J101=0,0,I101/J101) -> 0 | L101: =K101 -> 0 | M101: Exact company email match
A102: A.Ludick@WearCheckRS.com | B102: Adri Ludick | C102: RS | D102: WC492 | E102: Matched | F102: No | G102: Microsoft Copilot Studio Viral Trial | H102: Likely free / trial | I102: =IFERROR(VLOOKUP(G102,SKU_Cost_Input!$A$2:$E$15,4,FALSE),0) -> 0 | J102: =IFERROR(VLOOKUP(G102,SKU_Cost_Input!$A$2:$E$15,2,FALSE),0) -> 7 | K102: =IF(J102=0,0,I102/J102) -> 0 | L102: =K102 -> 0 | M102: Exact company email match
A103: A.Ludick@WearCheckRS.com | B103: Adri Ludick | C103: RS | D103: WC492 | E103: Matched | F103: No | G103: Microsoft Defender for Office 365 (Plan 2) | H103: Review invoice | I103: =IFERROR(VLOOKUP(G103,SKU_Cost_Input!$A$2:$E$15,4,FALSE),0) -> 0 | J103: =IFERROR(VLOOKUP(G103,SKU_Cost_Input!$A$2:$E$15,2,FALSE),0) -> 130 | K103: =IF(J103=0,0,I103/J103) -> 0 | L103: =K103 -> 0 | M103: Exact company email match
A104: A.Ludick@WearCheckRS.com | B104: Adri Ludick | C104: RS | D104: WC492 | E104: Matched | F104: No | G104: Microsoft Power Automate Free | H104: Likely free / trial | I104: =IFERROR(VLOOKUP(G104,SKU_Cost_Input!$A$2:$E$15,4,FALSE),0) -> 0 | J104: =IFERROR(VLOOKUP(G104,SKU_Cost_Input!$A$2:$E$15,2,FALSE),0) -> 52 | K104: =IF(J104=0,0,I104/J104) -> 0 | L104: =K104 -> 0 | M104: Exact company email match
A105: adriaanb@WearCheckRS.com | B105: Adriaan Bouwer | C105: RS | D105: WC383 | E105: Matched | F105: No | G105: Microsoft Defender for Office 365 (Plan 2) | H105: Review invoice | I105: =IFERROR(VLOOKUP(G105,SKU_Cost_Input!$A$2:$E$15,4,FALSE),0) -> 0 | J105: =IFERROR(VLOOKUP(G105,SKU_Cost_Input!$A$2:$E$15,2,FALSE),0) -> 130 | K105: =IF(J105=0,0,I105/J105) -> 0 | L105: =K105 -> 0 | M105: Exact company email match
A106: adriaanb@WearCheckRS.com | B106: Adriaan Bouwer | C106: RS | D106: WC383 | E106: Matched | F106: No | G106: Microsoft Power Automate Free | H106: Likely free / trial | I106: =IFERROR(VLOOKUP(G106,SKU_Cost_Input!$A$2:$E$15,4,FALSE),0) -> 0 | J106: =IFERROR(VLOOKUP(G106,SKU_Cost_Input!$A$2:$E$15,2,FALSE),0) -> 52 | K106: =IF(J106=0,0,I106/J106) -> 0 | L106: =K106 -> 0 | M106: Exact company email match
A107: adriaanb@WearCheckRS.com | B107: Adriaan Bouwer | C107: RS | D107: WC383 | E107: Matched | F107: No | G107: Microsoft 365 Business Standard | H107: Likely billable | I107: =IFERROR(VLOOKUP(G107,SKU_Cost_Input!$A$2:$E$15,4,FALSE),0) -> 0 | J107: =IFERROR(VLOOKUP(G107,SKU_Cost_Input!$A$2:$E$15,2,FALSE),0) -> 100 | K107: =IF(J107=0,0,I107/J107) -> 0 | L107: =K107 -> 0 | M107: Exact company email match
A108: adriaanb@WearCheckRS.com | B108: Adriaan Bouwer | C108: RS | D108: WC383 | E108: Matched | F108: No | G108: Microsoft Fabric (Free) | H108: Likely free / trial | I108: =IFERROR(VLOOKUP(G108,SKU_Cost_Input!$A$2:$E$15,4,FALSE),0) -> 0 | J108: =IFERROR(VLOOKUP(G108,SKU_Cost_Input!$A$2:$E$15,2,FALSE),0) -> 50 | K108: =IF(J108=0,0,I108/J108) -> 0 | L108: =K108 -> 0 | M108: Exact company email match
A109: Alex@WearCheckRS.com | B109: Alex Outram | C109: RS | D109: WEC105 | E109: Matched | F109: No | G109: Microsoft Defender for Office 365 (Plan 2) | H109: Review invoice | I109: =IFERROR(VLOOKUP(G109,SKU_Cost_Input!$A$2:$E$15,4,FALSE),0) -> 0 | J109: =IFERROR(VLOOKUP(G109,SKU_Cost_Input!$A$2:$E$15,2,FALSE),0) -> 130 | K109: =IF(J109=0,0,I109/J109) -> 0 | L109: =K109 -> 0 | M109: Exact company email match
A110: Alex@WearCheckRS.com | B110: Alex Outram | C110: RS | D110: WEC105 | E110: Matched | F110: No | G110: Microsoft Power Automate Free | H110: Likely free / trial | I110: =IFERROR(VLOOKUP(G110,SKU_Cost_Input!$A$2:$E$15,4,FALSE),0) -> 0 | J110: =IFERROR(VLOOKUP(G110,SKU_Cost_Input!$A$2:$E$15,2,FALSE),0) -> 52 | K110: =IF(J110=0,0,I110/J110) -> 0 | L110: =K110 -> 0 | M110: Exact company email match
A111: Alex@WearCheckRS.com | B111: Alex Outram | C111: RS | D111: WEC105 | E111: Matched | F111: No | G111: Microsoft Fabric (Free) | H111: Likely free / trial | I111: =IFERROR(VLOOKUP(G111,SKU_Cost_Input!$A$2:$E$15,4,FALSE),0) -> 0 | J111: =IFERROR(VLOOKUP(G111,SKU_Cost_Input!$A$2:$E$15,2,FALSE),0) -> 50 | K111: =IF(J111=0,0,I111/J111) -> 0 | L111: =K111 -> 0 | M111: Exact company email match
A112: Alex@WearCheckRS.com | B112: Alex Outram | C112: RS | D112: WEC105 | E112: Matched | F112: No | G112: Microsoft 365 Business Standard | H112: Likely billable | I112: =IFERROR(VLOOKUP(G112,SKU_Cost_Input!$A$2:$E$15,4,FALSE),0) -> 0 | J112: =IFERROR(VLOOKUP(G112,SKU_Cost_Input!$A$2:$E$15,2,FALSE),0) -> 100 | K112: =IF(J112=0,0,I112/J112) -> 0 | L112: =K112 -> 0 | M112: Exact company email match
... A183: eugene@WearCheckRS.com | B183: Eugene Scheepers | C183: RS | D183: WEC090 | E183: Matched | F183: No | G183: Microsoft 365 Business Standard | H183: Likely billable | I183: =IFERROR(VLOOKUP(G183,SKU_Cost_Input!$A$2:$E$15,4,FALSE),0) -> 0 | J183: =IFERROR(VLOOKUP(G183,SKU_Cost_Input!$A$2:$E$15,2,FALSE),0) -> 100 | K183: =IF(J183=0,0,I183/J183) -> 0 | L183: =K183 -> 0 | M183: Exact company email match
A184: flirirvm1@WearCheckRS.com | B184: FLIRIRVM1 | C184: RS | E184: Mapped by rule | F184: No | G184: Microsoft Defender for Office 365 (Plan 2) | H184: Review invoice | I184: =IFERROR(VLOOKUP(G184,SKU_Cost_Input!$A$2:$E$15,4,FALSE),0) -> 0 | J184: =IFERROR(VLOOKUP(G184,SKU_Cost_Input!$A$2:$E$15,2,FALSE),0) -> 130 | K184: =IF(J184=0,0,I184/J184) -> 0 | L184: =K184 -> 0 | M184: Generic/shared/service account defaulted to RS per instruction
A185: flirirvm1@WearCheckRS.com | B185: FLIRIRVM1 | C185: RS | E185: Mapped by rule | F185: No | G185: Microsoft 365 Business Standard | H185: Likely billable | I185: =IFERROR(VLOOKUP(G185,SKU_Cost_Input!$A$2:$E$15,4,FALSE),0) -> 0 | J185: =IFERROR(VLOOKUP(G185,SKU_Cost_Input!$A$2:$E$15,2,FALSE),0) -> 100 | K185: =IF(J185=0,0,I185/J185) -> 0 | L185: =K185 -> 0 | M185: Generic/shared/service account defaulted to RS per instruction
A186: franciosp@WearCheckRS.com | B186: Francios Pretorius | C186: RS | D186: WEC080 | E186: Matched | F186: No | G186: Microsoft Defender for Office 365 (Plan 2) | H186: Review invoice | I186: =IFERROR(VLOOKUP(G186,SKU_Cost_Input!$A$2:$E$15,4,FALSE),0) -> 0 | J186: =IFERROR(VLOOKUP(G186,SKU_Cost_Input!$A$2:$E$15,2,FALSE),0) -> 130 | K186: =IF(J186=0,0,I186/J186) -> 0 | L186: =K186 -> 0 | M186: Exact company email match
A187: franciosp@WearCheckRS.com | B187: Francios Pretorius | C187: RS | D187: WEC080 | E187: Matched | F187: No | G187: Microsoft Power Automate Free | H187: Likely free / trial | I187: =IFERROR(VLOOKUP(G187,SKU_Cost_Input!$A$2:$E$15,4,FALSE),0) -> 0 | J187: =IFERROR(VLOOKUP(G187,SKU_Cost_Input!$A$2:$E$15,2,FALSE),0) -> 52 | K187: =IF(J187=0,0,I187/J187) -> 0 | L187: =K187 -> 0 | M187: Exact company email match
A188: franciosp@WearCheckRS.com | B188: Francios Pretorius | C188: RS | D188: WEC080 | E188: Matched | F188: No | G188: Microsoft 365 Business Standard | H188: Likely billable | I188: =IFERROR(VLOOKUP(G188,SKU_Cost_Input!$A$2:$E$15,4,FALSE),0) -> 0 | J188: =IFERROR(VLOOKUP(G188,SKU_Cost_Input!$A$2:$E$15,2,FALSE),0) -> 100 | K188: =IF(J188=0,0,I188/J188) -> 0 | L188: =K188 -> 0 | M188: Exact company email match
A189: FrancoisP@WearCheckRS.com | B189: Francois Pienaar | C189: RS | D189: WEC111 | E189: Matched | F189: No | G189: Microsoft Defender for Office 365 (Plan 2) | H189: Review invoice | I189: =IFERROR(VLOOKUP(G189,SKU_Cost_Input!$A$2:$E$15,4,FALSE),0) -> 0 | J189: =IFERROR(VLOOKUP(G189,SKU_Cost_Input!$A$2:$E$15,2,FALSE),0) -> 130 | K189: =IF(J189=0,0,I189/J189) -> 0 | L189: =K189 -> 0 | M189: Exact company email match
A190: FrancoisP@WearCheckRS.com | B190: Francois Pienaar | C190: RS | D190: WEC111 | E190: Matched | F190: No | G190: Microsoft Fabric (Free) | H190: Likely free / trial | I190: =IFERROR(VLOOKUP(G190,SKU_Cost_Input!$A$2:$E$15,4,FALSE),0) -> 0 | J190: =IFERROR(VLOOKUP(G190,SKU_Cost_Input!$A$2:$E$15,2,FALSE),0) -> 50 | K190: =IF(J190=0,0,I190/J190) -> 0 | L190: =K190 -> 0 | M190: Exact company email match
A191: FrancoisP@WearCheckRS.com | B191: Francois Pienaar | C191: RS | D191: WEC111 | E191: Matched | F191: No | G191: Microsoft 365 Business Standard | H191: Likely billable | I191: =IFERROR(VLOOKUP(G191,SKU_Cost_Input!$A$2:$E$15,4,FALSE),0) -> 0 | J191: =IFERROR(VLOOKUP(G191,SKU_Cost_Input!$A$2:$E$15,2,FALSE),0) -> 100 | K191: =IF(J191=0,0,I191/J191) -> 0 | L191: =K191 -> 0 | M191: Exact company email match
A192: FrancoisP@WearCheckRS.com | B192: Francois Pienaar | C192: RS | D192: WEC111 | E192: Matched | F192: No | G192: Microsoft Power Automate Free | H192: Likely free / trial | I192: =IFERROR(VLOOKUP(G192,SKU_Cost_Input!$A$2:$E$15,4,FALSE),0) -> 0 | J192: =IFERROR(VLOOKUP(G192,SKU_Cost_Input!$A$2:$E$15,2,FALSE),0) -> 52 | K192: =IF(J192=0,0,I192/J192) -> 0 | L192: =K192 -> 0 | M192: Exact company email match
A193: francoisve@wearcheckrs.com | B193: Francois van Eden | C193: RS | D193: WC287 | E193: Matched | F193: No | G193: Microsoft 365 Business Premium | H193: Likely billable | I193: =IFERROR(VLOOKUP(G193,SKU_Cost_Input!$A$2:$E$15,4,FALSE),0) -> 0 | J193: =IFERROR(VLOOKUP(G193,SKU_Cost_Input!$A$2:$E$15,2,FALSE),0) -> 21 | K193: =IF(J193=0,0,I193/J193) -> 0 | L193: =K193 -> 0 | M193: Exact company email match
A194: francoisve@wearcheckrs.com | B194: Francois van Eden | C194: RS | D194: WC287 | E194: Matched | F194: No | G194: Microsoft Defender for Office 365 (Plan 2) | H194: Review invoice | I194: =IFERROR(VLOOKUP(G194,SKU_Cost_Input!$A$2:$E$15,4,FALSE),0) -> 0 | J194: =IFERROR(VLOOKUP(G194,SKU_Cost_Input!$A$2:$E$15,2,FALSE),0) -> 130 | K194: =IF(J194=0,0,I194/J194) -> 0 | L194: =K194 -> 0 | M194: Exact company email match
A195: francoisve@wearcheckrs.com | B195: Francois van Eden | C195: RS | D195: WC287 | E195: Matched | F195: No | G195: Microsoft Fabric (Free) | H195: Likely free / trial | I195: =IFERROR(VLOOKUP(G195,SKU_Cost_Input!$A$2:$E$15,4,FALSE),0) -> 0 | J195: =IFERROR(VLOOKUP(G195,SKU_Cost_Input!$A$2:$E$15,2,FALSE),0) -> 50 | K195: =IF(J195=0,0,I195/J195) -> 0 | L195: =K195 -> 0 | M195: Exact company email match
A196: francoisve@wearcheckrs.com | B196: Francois van Eden | C196: RS | D196: WC287 | E196: Matched | F196: No | G196: Microsoft Power Automate Free | H196: Likely free / trial | I196: =IFERROR(VLOOKUP(G196,SKU_Cost_Input!$A$2:$E$15,4,FALSE),0) -> 0 | J196: =IFERROR(VLOOKUP(G196,SKU_Cost_Input!$A$2:$E$15,2,FALSE),0) -> 52 | K196: =IF(J196=0,0,I196/J196) -> 0 | L196: =K196 -> 0 | M196: Exact company email match
A197: gustav@WearCheckRS.com | B197: Gustav Lourens | C197: RS | D197: WC270 | E197: Matched | F197: No | G197: Microsoft Defender for Office 365 (Plan 2) | H197: Review invoice | I197: =IFERROR(VLOOKUP(G197,SKU_Cost_Input!$A$2:$E$15,4,FALSE),0) -> 0 | J197: =IFERROR(VLOOKUP(G197,SKU_Cost_Input!$A$2:$E$15,2,FALSE),0) -> 130 | K197: =IF(J197=0,0,I197/J197) -> 0 | L197: =K197 -> 0 | M197: Exact company email match
... A261: marshallr@WearCheckRS.com | B261: Marshall Rasimphi | C261: RS | D261: WEC094 | E261: Matched | F261: No | G261: Microsoft 365 Business Standard | H261: Likely billable | I261: =IFERROR(VLOOKUP(G261,SKU_Cost_Input!$A$2:$E$15,4,FALSE),0) -> 0 | J261: =IFERROR(VLOOKUP(G261,SKU_Cost_Input!$A$2:$E$15,2,FALSE),0) -> 100 | K261: =IF(J261=0,0,I261/J261) -> 0 | L261: =K261 -> 0 | M261: Exact company email match
A262: marthinus_admin@wearcheckrs.com | B262: Marthinus Admin Account | C262: RS | E262: Mapped by rule | F262: No | G262: Microsoft Power Automate Free | H262: Likely free / trial | I262: =IFERROR(VLOOKUP(G262,SKU_Cost_Input!$A$2:$E$15,4,FALSE),0) -> 0 | J262: =IFERROR(VLOOKUP(G262,SKU_Cost_Input!$A$2:$E$15,2,FALSE),0) -> 52 | K262: =IF(J262=0,0,I262/J262) -> 0 | L262: =K262 -> 0 | M262: Generic/shared/service account defaulted to RS per instruction
A263: marthinus_admin@wearcheckrs.com | B263: Marthinus Admin Account | C263: RS | E263: Mapped by rule | F263: No | G263: Microsoft Fabric (Free) | H263: Likely free / trial | I263: =IFERROR(VLOOKUP(G263,SKU_Cost_Input!$A$2:$E$15,4,FALSE),0) -> 0 | J263: =IFERROR(VLOOKUP(G263,SKU_Cost_Input!$A$2:$E$15,2,FALSE),0) -> 50 | K263: =IF(J263=0,0,I263/J263) -> 0 | L263: =K263 -> 0 | M263: Generic/shared/service account defaulted to RS per instruction
A264: martiens@WearCheckRS.com | B264: Martiens Van Aarde | C264: RS | D264: WEC106 | E264: Matched | F264: No | G264: Microsoft Power Automate Free | H264: Likely free / trial | I264: =IFERROR(VLOOKUP(G264,SKU_Cost_Input!$A$2:$E$15,4,FALSE),0) -> 0 | J264: =IFERROR(VLOOKUP(G264,SKU_Cost_Input!$A$2:$E$15,2,FALSE),0) -> 52 | K264: =IF(J264=0,0,I264/J264) -> 0 | L264: =K264 -> 0 | M264: Exact company email match
A265: martiens@WearCheckRS.com | B265: Martiens Van Aarde | C265: RS | D265: WEC106 | E265: Matched | F265: No | G265: Microsoft Defender for Office 365 (Plan 2) | H265: Review invoice | I265: =IFERROR(VLOOKUP(G265,SKU_Cost_Input!$A$2:$E$15,4,FALSE),0) -> 0 | J265: =IFERROR(VLOOKUP(G265,SKU_Cost_Input!$A$2:$E$15,2,FALSE),0) -> 130 | K265: =IF(J265=0,0,I265/J265) -> 0 | L265: =K265 -> 0 | M265: Exact company email match
A266: martiens@WearCheckRS.com | B266: Martiens Van Aarde | C266: RS | D266: WEC106 | E266: Matched | F266: No | G266: Microsoft 365 Business Standard | H266: Likely billable | I266: =IFERROR(VLOOKUP(G266,SKU_Cost_Input!$A$2:$E$15,4,FALSE),0) -> 0 | J266: =IFERROR(VLOOKUP(G266,SKU_Cost_Input!$A$2:$E$15,2,FALSE),0) -> 100 | K266: =IF(J266=0,0,I266/J266) -> 0 | L266: =K266 -> 0 | M266: Exact company email match
A267: Megan@wearcheckrs.com | B267: Megan Salzwedel | C267: RS | D267: WEC104 | E267: Matched | F267: No | G267: Microsoft 365 Business Premium | H267: Likely billable | I267: =IFERROR(VLOOKUP(G267,SKU_Cost_Input!$A$2:$E$15,4,FALSE),0) -> 0 | J267: =IFERROR(VLOOKUP(G267,SKU_Cost_Input!$A$2:$E$15,2,FALSE),0) -> 21 | K267: =IF(J267=0,0,I267/J267) -> 0 | L267: =K267 -> 0 | M267: Exact company email match
A268: Megan@wearcheckrs.com | B268: Megan Salzwedel | C268: RS | D268: WEC104 | E268: Matched | F268: No | G268: Microsoft Defender for Office 365 (Plan 2) | H268: Review invoice | I268: =IFERROR(VLOOKUP(G268,SKU_Cost_Input!$A$2:$E$15,4,FALSE),0) -> 0 | J268: =IFERROR(VLOOKUP(G268,SKU_Cost_Input!$A$2:$E$15,2,FALSE),0) -> 130 | K268: =IF(J268=0,0,I268/J268) -> 0 | L268: =K268 -> 0 | M268: Exact company email match
A269: Megan@wearcheckrs.com | B269: Megan Salzwedel | C269: RS | D269: WEC104 | E269: Matched | F269: No | G269: Microsoft Power Apps Plan 2 Trial | H269: Likely free / trial | I269: =IFERROR(VLOOKUP(G269,SKU_Cost_Input!$A$2:$E$15,4,FALSE),0) -> 0 | J269: =IFERROR(VLOOKUP(G269,SKU_Cost_Input!$A$2:$E$15,2,FALSE),0) -> 6 | K269: =IF(J269=0,0,I269/J269) -> 0 | L269: =K269 -> 0 | M269: Exact company email match
A270: Megan@wearcheckrs.com | B270: Megan Salzwedel | C270: RS | D270: WEC104 | E270: Matched | F270: No | G270: Microsoft Fabric (Free) | H270: Likely free / trial | I270: =IFERROR(VLOOKUP(G270,SKU_Cost_Input!$A$2:$E$15,4,FALSE),0) -> 0 | J270: =IFERROR(VLOOKUP(G270,SKU_Cost_Input!$A$2:$E$15,2,FALSE),0) -> 50 | K270: =IF(J270=0,0,I270/J270) -> 0 | L270: =K270 -> 0 | M270: Exact company email match
A271: Megan@wearcheckrs.com | B271: Megan Salzwedel | C271: RS | D271: WEC104 | E271: Matched | F271: No | G271: Microsoft Power Automate Free | H271: Likely free / trial | I271: =IFERROR(VLOOKUP(G271,SKU_Cost_Input!$A$2:$E$15,4,FALSE),0) -> 0 | J271: =IFERROR(VLOOKUP(G271,SKU_Cost_Input!$A$2:$E$15,2,FALSE),0) -> 52 | K271: =IF(J271=0,0,I271/J271) -> 0 | L271: =K271 -> 0 | M271: Exact company email match
A272: meshack@WearCheckRS.com | B272: Meshack Nxumalo | C272: RS | D272: WEC088 | E272: Matched | F272: No | G272: Microsoft Defender for Office 365 (Plan 2) | H272: Review invoice | I272: =IFERROR(VLOOKUP(G272,SKU_Cost_Input!$A$2:$E$15,4,FALSE),0) -> 0 | J272: =IFERROR(VLOOKUP(G272,SKU_Cost_Input!$A$2:$E$15,2,FALSE),0) -> 130 | K272: =IF(J272=0,0,I272/J272) -> 0 | L272: =K272 -> 0 | M272: Exact company email match
A273: meshack@WearCheckRS.com | B273: Meshack Nxumalo | C273: RS | D273: WEC088 | E273: Matched | F273: No | G273: Microsoft 365 Business Standard | H273: Likely billable | I273: =IFERROR(VLOOKUP(G273,SKU_Cost_Input!$A$2:$E$15,4,FALSE),0) -> 0 | J273: =IFERROR(VLOOKUP(G273,SKU_Cost_Input!$A$2:$E$15,2,FALSE),0) -> 100 | K273: =IF(J273=0,0,I273/J273) -> 0 | L273: =K273 -> 0 | M273: Exact company email match
A274: michealm@WearCheckRS.com | B274: Micheal Masemola | C274: RS | D274: WC291 | E274: Matched | F274: No | G274: Microsoft Defender for Office 365 (Plan 2) | H274: Review invoice | I274: =IFERROR(VLOOKUP(G274,SKU_Cost_Input!$A$2:$E$15,4,FALSE),0) -> 0 | J274: =IFERROR(VLOOKUP(G274,SKU_Cost_Input!$A$2:$E$15,2,FALSE),0) -> 130 | K274: =IF(J274=0,0,I274/J274) -> 0 | L274: =K274 -> 0 | M274: Exact company email match
A275: michealm@WearCheckRS.com | B275: Micheal Masemola | C275: RS | D275: WC291 | E275: Matched | F275: No | G275: Microsoft 365 Business Standard | H275: Likely billable | I275: =IFERROR(VLOOKUP(G275,SKU_Cost_Input!$A$2:$E$15,4,FALSE),0) -> 0 | J275: =IFERROR(VLOOKUP(G275,SKU_Cost_Input!$A$2:$E$15,2,FALSE),0) -> 100 | K275: =IF(J275=0,0,I275/J275) -> 0 | L275: =K275 -> 0 | M275: Exact company email match
... A288: Nadhira@WearCheckRS.com | B288: Nadhira Bux | C288: RS | D288: WEC113 | E288: Matched | F288: No | G288: Microsoft Fabric (Free) | H288: Likely free / trial | I288: =IFERROR(VLOOKUP(G288,SKU_Cost_Input!$A$2:$E$15,4,FALSE),0) -> 0 | J288: =IFERROR(VLOOKUP(G288,SKU_Cost_Input!$A$2:$E$15,2,FALSE),0) -> 50 | K288: =IF(J288=0,0,I288/J288) -> 0 | L288: =K288 -> 0 | M288: Exact company email match
A289: noreply@WearCheckRS.com | B289: No Reply | C289: RS | E289: Mapped by rule | F289: No | G289: Microsoft Defender for Office 365 (Plan 2) | H289: Review invoice | I289: =IFERROR(VLOOKUP(G289,SKU_Cost_Input!$A$2:$E$15,4,FALSE),0) -> 0 | J289: =IFERROR(VLOOKUP(G289,SKU_Cost_Input!$A$2:$E$15,2,FALSE),0) -> 130 | K289: =IF(J289=0,0,I289/J289) -> 0 | L289: =K289 -> 0 | M289: Generic/shared/service account defaulted to RS per instruction
A290: noreply@WearCheckRS.com | B290: No Reply | C290: RS | E290: Mapped by rule | F290: No | G290: Microsoft 365 Business Standard | H290: Likely billable | I290: =IFERROR(VLOOKUP(G290,SKU_Cost_Input!$A$2:$E$15,4,FALSE),0) -> 0 | J290: =IFERROR(VLOOKUP(G290,SKU_Cost_Input!$A$2:$E$15,2,FALSE),0) -> 100 | K290: =IF(J290=0,0,I290/J290) -> 0 | L290: =K290 -> 0 | M290: Generic/shared/service account defaulted to RS per instruction
A291: NomvulaM@WearCheckRS.com | B291: Nomvula Mkhize | C291: RS | D291: WC651 | E291: Matched | F291: No | G291: Microsoft Defender for Office 365 (Plan 2) | H291: Review invoice | I291: =IFERROR(VLOOKUP(G291,SKU_Cost_Input!$A$2:$E$15,4,FALSE),0) -> 0 | J291: =IFERROR(VLOOKUP(G291,SKU_Cost_Input!$A$2:$E$15,2,FALSE),0) -> 130 | K291: =IF(J291=0,0,I291/J291) -> 0 | L291: =K291 -> 0 | M291: Exact company email match
A292: NomvulaM@WearCheckRS.com | B292: Nomvula Mkhize | C292: RS | D292: WC651 | E292: Matched | F292: No | G292: Microsoft 365 Business Standard | H292: Likely billable | I292: =IFERROR(VLOOKUP(G292,SKU_Cost_Input!$A$2:$E$15,4,FALSE),0) -> 0 | J292: =IFERROR(VLOOKUP(G292,SKU_Cost_Input!$A$2:$E$15,2,FALSE),0) -> 100 | K292: =IF(J292=0,0,I292/J292) -> 0 | L292: =K292 -> 0 | M292: Exact company email match
A293: passwell@WearCheckRS.com | B293: Passwell Mashoeou | C293: RS | D293: WC348 | E293: Matched | F293: No | G293: Microsoft Defender for Office 365 (Plan 2) | H293: Review invoice | I293: =IFERROR(VLOOKUP(G293,SKU_Cost_Input!$A$2:$E$15,4,FALSE),0) -> 0 | J293: =IFERROR(VLOOKUP(G293,SKU_Cost_Input!$A$2:$E$15,2,FALSE),0) -> 130 | K293: =IF(J293=0,0,I293/J293) -> 0 | L293: =K293 -> 0 | M293: Exact company email match
A294: passwell@WearCheckRS.com | B294: Passwell Mashoeou | C294: RS | D294: WC348 | E294: Matched | F294: No | G294: Microsoft 365 Business Standard | H294: Likely billable | I294: =IFERROR(VLOOKUP(G294,SKU_Cost_Input!$A$2:$E$15,4,FALSE),0) -> 0 | J294: =IFERROR(VLOOKUP(G294,SKU_Cost_Input!$A$2:$E$15,2,FALSE),0) -> 100 | K294: =IF(J294=0,0,I294/J294) -> 0 | L294: =K294 -> 0 | M294: Exact company email match
A295: Peet@WearCheckRS.com | B295: Peet Peacock | C295: RS | D295: WC520 | E295: Matched | F295: No | G295: Microsoft Defender for Office 365 (Plan 2) | H295: Review invoice | I295: =IFERROR(VLOOKUP(G295,SKU_Cost_Input!$A$2:$E$15,4,FALSE),0) -> 0 | J295: =IFERROR(VLOOKUP(G295,SKU_Cost_Input!$A$2:$E$15,2,FALSE),0) -> 130 | K295: =IF(J295=0,0,I295/J295) -> 0 | L295: =K295 -> 0 | M295: Exact company email match
A296: Peet@WearCheckRS.com | B296: Peet Peacock | C296: RS | D296: WC520 | E296: Matched | F296: No | G296: Microsoft 365 E3 | H296: Likely billable | I296: =IFERROR(VLOOKUP(G296,SKU_Cost_Input!$A$2:$E$15,4,FALSE),0) -> 0 | J296: =IFERROR(VLOOKUP(G296,SKU_Cost_Input!$A$2:$E$15,2,FALSE),0) -> 14 | K296: =IF(J296=0,0,I296/J296) -> 0 | L296: =K296 -> 0 | M296: Exact company email match
A297: Percy@WearCheckRS.com | B297: Percy Hall | C297: RS | D297: WEC115 | E297: Matched | F297: No | G297: Microsoft Defender for Office 365 (Plan 2) | H297: Review invoice | I297: =IFERROR(VLOOKUP(G297,SKU_Cost_Input!$A$2:$E$15,4,FALSE),0) -> 0 | J297: =IFERROR(VLOOKUP(G297,SKU_Cost_Input!$A$2:$E$15,2,FALSE),0) -> 130 | K297: =IF(J297=0,0,I297/J297) -> 0 | L297: =K297 -> 0 | M297: Exact company email match
A298: Percy@WearCheckRS.com | B298: Percy Hall | C298: RS | D298: WEC115 | E298: Matched | F298: No | G298: Microsoft 365 Business Standard | H298: Likely billable | I298: =IFERROR(VLOOKUP(G298,SKU_Cost_Input!$A$2:$E$15,4,FALSE),0) -> 0 | J298: =IFERROR(VLOOKUP(G298,SKU_Cost_Input!$A$2:$E$15,2,FALSE),0) -> 100 | K298: =IF(J298=0,0,I298/J298) -> 0 | L298: =K298 -> 0 | M298: Exact company email match
A299: permission@WearCheckRS.com | B299: Permission Melele | C299: RS | D299: WC393 | E299: Matched | F299: No | G299: Microsoft Defender for Office 365 (Plan 2) | H299: Review invoice | I299: =IFERROR(VLOOKUP(G299,SKU_Cost_Input!$A$2:$E$15,4,FALSE),0) -> 0 | J299: =IFERROR(VLOOKUP(G299,SKU_Cost_Input!$A$2:$E$15,2,FALSE),0) -> 130 | K299: =IF(J299=0,0,I299/J299) -> 0 | L299: =K299 -> 0 | M299: Exact company email match
A300: permission@WearCheckRS.com | B300: Permission Melele | C300: RS | D300: WC393 | E300: Matched | F300: No | G300: Microsoft 365 Business Standard | H300: Likely billable | I300: =IFERROR(VLOOKUP(G300,SKU_Cost_Input!$A$2:$E$15,4,FALSE),0) -> 0 | J300: =IFERROR(VLOOKUP(G300,SKU_Cost_Input!$A$2:$E$15,2,FALSE),0) -> 100 | K300: =IF(J300=0,0,I300/J300) -> 0 | L300: =K300 -> 0 | M300: Exact company email match
A301: philip@WearCheckRS.com | B301: Philip Schutte | C301: RS | D301: WC253 | E301: Matched | F301: No | G301: Microsoft Defender for Office 365 (Plan 2) | H301: Review invoice | I301: =IFERROR(VLOOKUP(G301,SKU_Cost_Input!$A$2:$E$15,4,FALSE),0) -> 0 | J301: =IFERROR(VLOOKUP(G301,SKU_Cost_Input!$A$2:$E$15,2,FALSE),0) -> 130 | K301: =IF(J301=0,0,I301/J301) -> 0 | L301: =K301 -> 0 | M301: Exact company email match
A302: philip@WearCheckRS.com | B302: Philip Schutte | C302: RS | D302: WC253 | E302: Matched | F302: No | G302: Microsoft Fabric (Free) | H302: Likely free / trial | I302: =IFERROR(VLOOKUP(G302,SKU_Cost_Input!$A$2:$E$15,4,FALSE),0) -> 0 | J302: =IFERROR(VLOOKUP(G302,SKU_Cost_Input!$A$2:$E$15,2,FALSE),0) -> 50 | K302: =IF(J302=0,0,I302/J302) -> 0 | L302: =K302 -> 0 | M302: Exact company email match
... A305: Philip_Zoho@WearCheckRS.com | B305: Philip Zoho | C305: RS | D305: WC253 | E305: Matched | F305: No | G305: Microsoft 365 Business Standard | H305: Likely billable | I305: =IFERROR(VLOOKUP(G305,SKU_Cost_Input!$A$2:$E$15,4,FALSE),0) -> 0 | J305: =IFERROR(VLOOKUP(G305,SKU_Cost_Input!$A$2:$E$15,2,FALSE),0) -> 100 | K305: =IF(J305=0,0,I305/J305) -> 0 | L305: =K305 -> 0 | M305: Matched via email alias/local-part
A306: srv_acc_pbi_gw@WearCheckRS.com | B306: Power Bi Gateway Service Account | C306: RS | E306: Mapped by rule | F306: No | G306: Microsoft Power Automate Free | H306: Likely free / trial | I306: =IFERROR(VLOOKUP(G306,SKU_Cost_Input!$A$2:$E$15,4,FALSE),0) -> 0 | J306: =IFERROR(VLOOKUP(G306,SKU_Cost_Input!$A$2:$E$15,2,FALSE),0) -> 52 | K306: =IF(J306=0,0,I306/J306) -> 0 | L306: =K306 -> 0 | M306: Generic/shared/service account defaulted to RS per instruction
A307: srv_acc_pbi_gw@WearCheckRS.com | B307: Power Bi Gateway Service Account | C307: RS | E307: Mapped by rule | F307: No | G307: Power BI Premium Per User | H307: Likely billable | I307: =IFERROR(VLOOKUP(G307,SKU_Cost_Input!$A$2:$E$15,4,FALSE),0) -> 0 | J307: =IFERROR(VLOOKUP(G307,SKU_Cost_Input!$A$2:$E$15,2,FALSE),0) -> 6 | K307: =IF(J307=0,0,I307/J307) -> 0 | L307: =K307 -> 0 | M307: Generic/shared/service account defaulted to RS per instruction
A308: srv_acc_pbi_gw@WearCheckRS.com | B308: Power Bi Gateway Service Account | C308: RS | E308: Mapped by rule | F308: No | G308: Exchange Online (Plan 1) | H308: Likely billable | I308: =IFERROR(VLOOKUP(G308,SKU_Cost_Input!$A$2:$E$15,4,FALSE),0) -> 0 | J308: =IFERROR(VLOOKUP(G308,SKU_Cost_Input!$A$2:$E$15,2,FALSE),0) -> 4 | K308: =IF(J308=0,0,I308/J308) -> 0 | L308: =K308 -> 0 | M308: Generic/shared/service account defaulted to RS per instruction
A309: printer@WearCheckRS.com | B309: Printer Account | C309: RS | E309: Mapped by rule | F309: No | G309: Exchange Online (Plan 1) | H309: Likely billable | I309: =IFERROR(VLOOKUP(G309,SKU_Cost_Input!$A$2:$E$15,4,FALSE),0) -> 0 | J309: =IFERROR(VLOOKUP(G309,SKU_Cost_Input!$A$2:$E$15,2,FALSE),0) -> 4 | K309: =IF(J309=0,0,I309/J309) -> 0 | L309: =K309 -> 0 | M309: Generic/shared/service account defaulted to RS per instruction
A310: rakcal@WearCheckRS.com | B310: Rakcal Balaram | C310: RS | D310: WEC074 | E310: Matched | F310: No | G310: Microsoft Defender for Office 365 (Plan 2) | H310: Review invoice | I310: =IFERROR(VLOOKUP(G310,SKU_Cost_Input!$A$2:$E$15,4,FALSE),0) -> 0 | J310: =IFERROR(VLOOKUP(G310,SKU_Cost_Input!$A$2:$E$15,2,FALSE),0) -> 130 | K310: =IF(J310=0,0,I310/J310) -> 0 | L310: =K310 -> 0 | M310: Exact company email match
A311: rakcal@WearCheckRS.com | B311: Rakcal Balaram | C311: RS | D311: WEC074 | E311: Matched | F311: No | G311: Microsoft 365 Business Standard | H311: Likely billable | I311: =IFERROR(VLOOKUP(G311,SKU_Cost_Input!$A$2:$E$15,4,FALSE),0) -> 0 | J311: =IFERROR(VLOOKUP(G311,SKU_Cost_Input!$A$2:$E$15,2,FALSE),0) -> 100 | K311: =IF(J311=0,0,I311/J311) -> 0 | L311: =K311 -> 0 | M311: Exact company email match
A312: reinierk@wearcheckrs.com | B312: Reinier Kalp | C312: RS | D312: WC382 | E312: Matched | F312: No | G312: Microsoft 365 Business Premium | H312: Likely billable | I312: =IFERROR(VLOOKUP(G312,SKU_Cost_Input!$A$2:$E$15,4,FALSE),0) -> 0 | J312: =IFERROR(VLOOKUP(G312,SKU_Cost_Input!$A$2:$E$15,2,FALSE),0) -> 21 | K312: =IF(J312=0,0,I312/J312) -> 0 | L312: =K312 -> 0 | M312: Exact company email match
A313: reinierk@wearcheckrs.com | B313: Reinier Kalp | C313: RS | D313: WC382 | E313: Matched | F313: No | G313: Microsoft Defender for Office 365 (Plan 2) | H313: Review invoice | I313: =IFERROR(VLOOKUP(G313,SKU_Cost_Input!$A$2:$E$15,4,FALSE),0) -> 0 | J313: =IFERROR(VLOOKUP(G313,SKU_Cost_Input!$A$2:$E$15,2,FALSE),0) -> 130 | K313: =IF(J313=0,0,I313/J313) -> 0 | L313: =K313 -> 0 | M313: Exact company email match
...

Sheet Review_Queue
A1: Licensed Display Name | B1: Licensed Email | C1: Suggested Division | D1: Matched Employee Name | E1: Candidate Employee Email | F1: Employee Number | G1: Confidence | H1: Review Type | I1: Mapping Note | J1: Licenses Raw
A2: Jean Pierre Du Plessis | B2: Jean-Pierre@WearCheckRS.com | C2: AFS | D2: Jean Pierre du Plessis | G2: Low | H2: Low confidence match | I2: Matched via exact name | J2: Microsoft 365 Business Standard+Microsoft Defender for Office 365 (Plan 2)
A3: Joe Kies | B3: Joe@WearCheckRS.com | C3: AFS | D3: Joseph Benjamin Kies | E3: josephk@wearcheck.co.za | F3: WC531 | G3: Low | H3: Low confidence match | I3: Matched via manual alias/name rule | J3: Microsoft Power Automate Free+Microsoft 365 Business Standard+Microsoft Power Apps Plan 2 Trial+Microsoft Fabric (Free)+Microsoft Copilot Studio Viral Trial+Microsoft Power Apps for Developer+Power Pages vTrial for Makers+Microsoft Defender for Office 365 (Plan 2)+Dynamics 365 Customer Insights Self-Service
A4: Johan Stols | B4: Johan.Stols@WearCheckRS.com | C4: AFS | D4: Johannes Gideon Francios Stols | E4: Johans@wearcheckrs.com | F4: WC508 | G4: Low | H4: Low confidence match | I4: Matched via manual alias/name rule | J4: Microsoft Defender for Office 365 (Plan 2)+Microsoft Power Automate Free+Microsoft 365 Business Standard
A5: Lorraine Mokgethi | B5: Lorraine@WearCheckRS.com | C5: AFS | D5: Lorraine Lerato Mokgethi | E5: lorrainem@wearcheck.co.za | F5: WC495 | G5: Low | H5: Low confidence match | I5: Matched via close email alias + surname | J5: Microsoft Defender for Office 365 (Plan 2)+Microsoft 365 Business Premium
A6: Mervyn Gibbons | B6: Mervyn@WearCheckRS.com | C6: AFS | D6: Mervyn Thomas Gibbons | E6: mervyng@wearcheck.co.za | F6: WC536 | G6: Low | H6: Low confidence match | I6: Matched via close email alias + surname | J6: Microsoft Power Automate Free+Microsoft 365 Business Standard+Microsoft Power Apps Plan 2 Trial+Microsoft Fabric (Free)+Microsoft Copilot Studio Viral Trial+Microsoft Power Apps for Developer+Power Pages vTrial for Makers+Microsoft Defender for Office 365 (Plan 2)+Dynamics 365 Customer Insights Self-Service
A7: Adri Ludick Old | B7: Adri.ludick@WearCheckRS.com | C7: Unassigned - Review | G7: Unassigned | H7: Unassigned / no confident match | I7: No employee match found in employee master | J7: Microsoft Defender for Office 365 (Plan 2)+Microsoft Power Automate Free+Microsoft 365 Business Standard
A8: Boitumelo Makgamatha | B8: Boitumelo@WearCheckRS.com | C8: Unassigned - Review | G8: Unassigned | H8: Unassigned / no confident match | I8: No employee match found in employee master | J8: Microsoft Defender for Office 365 (Plan 2)+Microsoft 365 Business Standard
A9: Christene Fourie | B9: Christene@WearCheckRS.com | C9: Unassigned - Review | E9: chrstene@wearcheckrs.com | G9: Unassigned | H9: Unassigned / no confident match | I9: Possible email alias match to chrstene@wearcheckrs.com | J9: Microsoft Defender for Office 365 (Plan 2)+Microsoft Power Automate Free+Microsoft 365 Business Standard
A10: Christian Geel | B10: Christian@WearCheckRS.com | C10: Unassigned - Review | G10: Unassigned | H10: Unassigned / no confident match | I10: No employee match found in employee master | J10: Microsoft Fabric (Free)+Microsoft Power Automate Free
A11: Christie | B11: christie.samancor@WearCheckRS.com | C11: Unassigned - Review | G11: Unassigned | H11: Unassigned / no confident match | I11: No employee match found in employee master | J11: Microsoft Fabric (Free)
A12: Gladwin Sekharume | B12: GladwinS@WearCheckRS.com | C12: Unassigned - Review | G12: Unassigned | H12: Unassigned / no confident match | I12: No employee match found in employee master | J12: Microsoft Defender for Office 365 (Plan 2)+Microsoft 365 Business Standard
A13: Ivan Langa | B13: Ivan@WearCheckRS.com | C13: Unassigned - Review | G13: Unassigned | H13: Unassigned / no confident match | I13: No employee match found in employee master | J13: Microsoft Defender for Office 365 (Plan 2)+Microsoft Fabric (Free)+Microsoft 365 Business Standard
A14: Kenneth Moremi | B14: kenneth@WearCheckRS.com | C14: Unassigned - Review | G14: Unassigned | H14: Unassigned / no confident match | I14: No employee match found in employee master | J14: Microsoft Defender for Office 365 (Plan 2)+Microsoft 365 Business Standard
A15: Kevin Jonker | B15: kevinj@WearCheckRS.com | C15: Unassigned - Review | E15: kevin@wearcheckrs.com | G15: Unassigned | H15: Unassigned / no confident match | I15: Possible email alias match to kevin@wearcheckrs.com | J15: Microsoft Fabric (Free)+Microsoft Power Automate Free
A16: Lea Bodenstein | B16: Lea@WearCheckRS.com | C16: Unassigned - Review | G16: Unassigned | H16: Unassigned / no confident match | I16: No employee match found in employee master | J16: Microsoft 365 Business Premium+Microsoft Defender for Office 365 (Plan 2)+Microsoft Fabric (Free)
A17: Mandiso Muchanga | B17: Mandiso@WearCheckRS.com | C17: Unassigned - Review | G17: Unassigned | H17: Unassigned / no confident match | I17: No employee match found in employee master | J17: Microsoft Defender for Office 365 (Plan 2)+Microsoft 365 Business Standard
A18: Marthinus Steenkamp | B18: Marthinus@WearCheckRS.com | C18: Unassigned - Review | G18: Unassigned | H18: Unassigned / no confident match | I18: No employee match found in employee master | J18: Microsoft Defender for Office 365 (Plan 2)+Microsoft 365 E3+Microsoft Fabric (Free)
A19: Martin Prinsloo | B19: martin.prinsloo@WearCheckRS.com | C19: Unassigned - Review | G19: Unassigned | H19: Unassigned / no confident match | I19: No employee match found in employee master | J19: Microsoft Fabric (Free)
A20: Nicolien Schutte | B20: Nicoliens@WearCheckRS.com | C20: Unassigned - Review | G20: Unassigned | H20: Unassigned / no confident match | I20: No employee match found in employee master | J20: Microsoft Defender for Office 365 (Plan 2)+Power BI Premium Per User+Microsoft 365 E3+Microsoft Fabric (Free)+Microsoft Power Automate Free
A21: Peter | B21: Peter@WearCheckRS.com | C21: Unassigned - Review | G21: Unassigned | H21: Unassigned / no confident match | I21: No employee match found in employee master | J21: Microsoft 365 Business Standard
A22: Stephanie Du Plessis | B22: stephanied@wearcheckrs.com | C22: Unassigned - Review | G22: Unassigned | H22: Unassigned / no confident match | I22: No employee match found in employee master | J22: Microsoft 365 Business Standard+Microsoft Defender for Office 365 (Plan 2)
A23: Thabang Mathumba | B23: thabang@WearCheckRS.com | C23: Unassigned - Review | G23: Unassigned | H23: Unassigned / no confident match | I23: No employee match found in employee master | J23: Microsoft Defender for Office 365 (Plan 2)+Microsoft 365 Business Standard
A24: Tumelo | B24: tumelo.samancor@WearCheckRS.com | C24: Unassigned - Review | G24: Unassigned | H24: Unassigned / no confident match | I24: No employee match found in employee master | J24: Microsoft Fabric (Free)

Sheet Employee_Master
A1: Company Email | B1: Employee Name | C1: Employee Code | D1: Department 1 | E1: Department 2 | F1: Site | G1: Derived Division | H1: Job Title | I1: Supervisor | J1: Cell Number | K1: Status | L1: Source Row
A2: andree@wearcheck.co.za | B2: André Erasmus | C2: WC511 | D2: ARC-TCA | E2: AFS | G2: AFS | H2: Machinery Inspector / Auditor | I2: Johan Stols | J2: 0833088571 | K2: Submitted | L2: 7
A3: antonio.ehrke@wearcheckrs.com | B3: Antonio Ehrke | C3: WC503 | D3: ARC-RCA | E3: AFS | G3: AFS | H3: RCA Inspector | I3: Roger Henwood | J3: 0834695668 | K3: Submitted | L3: 11
A4: Arnold@WearCheckRS.com | B4: Arnoldus Johannes van Zyl | C4: WC526 | D4: ARC-TCA | E4: AFS | G4: AFS | H4: Electrical Inspector | I4: Johan Stols | J4: 067412 1369 | K4: Submitted | L4: 13
A5: colleen.pyper@WearCheckRS.com | B5: Colleen Pyper | C5: WC486 | D5: AFS | E5: AFS | G5: AFS | H5: Admin and Finance Assistant | I5: Adri Ludick | J5: 0662916811 | K5: Submitted | L5: 21
A6: greeffm@wearcheck.co.za | B6: Daniel Greef Meintjies | C6: WC528 | D6: ARC-NDT | E6: AFS | G6: AFS | H6: Inspector (Lifting and NDT) | I6: Adri Ludick | J6: 0674121318 | K6: Submitted | L6: 22
A7: edwin@wearcheckrs.com | B7: Edwin Ashley Gibbons | C7: WEC138 | D7: ARC-TCA | E7: AFS | G7: AFS | H7: ARC TC Machinery Inspector | I7: Johan Stols | J7: 0725336075 | K7: Submitted | L7: 32
A8: ethel.mienie@WearCheckRS.com | B8: Ethel Mienie | C8: WC488 | D8: AFS | E8: AFS | G8: AFS | H8: Administration Assistant | I8: Adri Ludick | J8: 0660215452 | K8: Submitted | L8: 33
A9: evertv@wearcheck.co.za | B9: Evert Viljoen | C9: WC497 | D9: ARC-NDT | E9: AFS | G9: AFS | H9: Senior Machinery Inspector | I9: Adri Ludick | J9: 0795284219 | K9: Submitted | L9: 36
A10: godfreyb@wearcheck.co.za | B10: Godfrey Boikhutso | C10: WC510 | D10: ARC-TCA | E10: AFS | G10: AFS | H10: Inspector | I10: Johan Stols | J10: 0718609242 | K10: Submitted | L10: 42
A11: jacov@wearcheck.co.za | B11: Jacobus Frederick Venter | C11: WC493 | D11: ARC-NDT | E11: AFS | G11: AFS | H11: Senior Machinery Inspector | I11: Adri Ludick | J11: 0834009604 | K11: Submitted | L11: 50
A12: janb@wearcheck.co.za | B12: Jan Booysens | C12: WC496 | D12: ARC-NDT | E12: AFS | G12: AFS | H12: Senior Machinery Inspector | I12: Adri Ludick | J12: 0718665249 | K12: Submitted | L12: 54
B13: Jean Pierre du Plessis | D13: ARC-TCA | E13: AFS | G13: AFS | H13: Machinery Inspector | I13: Johan Stols | J13: 0602033229 | K13: Not Submitted | L13: 57
A14: jeanj@wearcheck.co.za | B14: Jean-Pierre Jordaan | C14: WC527 | D14: ARC-NDT | E14: AFS | G14: AFS | H14: Inspector (Lifting and NDT) | I14: Adri Ludick | J14: 0674121382 | K14: Submitted | L14: 63
A15: JohanB@wearcheckRS.com | B15: Johan Bekker | C15: WC645 | D15: ARC-TCA | E15: AFS | G15: AFS | H15: ARC TC Inspector | I15: Johan Stols | J15: 0675951633 | K15: Submitted | L15: 58
A16: johanr@wearcheckrs.com | B16: Johan Rossouw | C16: WC491 | D16: ARC-TCA | E16: AFS | G16: AFS | H16: Senior Inspector | I16: Johan Stols | J16: 0829274240 | K16: Submitted | L16: 59
A17: janniel@wearcheck.co.za | B17: Johann Louw | C17: WC494 | D17: ARC-NDT | E17: AFS | G17: AFS | H17: Inspector | I17: Adri Ludick | J17: 0718607663 | K17: Submitted | L17: 55
A18: Johans@wearcheckrs.com | B18: Johannes Gideon Francios Stols | C18: WC508 | D18: ARC-TCA | E18: AFS | G18: AFS | H18: ARC TC Manager | I18: Philip Schutte | J18: 0832943748 | K18: Submitted | L18: 60
A19: josephk@wearcheck.co.za | B19: Joseph Benjamin Kies | C19: WC531 | D19: ARC-TCA | E19: AFS | G19: AFS | H19: Machinery Inspector | I19: Johan Stols | J19: 0674121368 | K19: Submitted | L19: 62
A20: khotso@wearcheckrs.com | B20: Khotso Thabo Mosala | C20: WC482 | D20: ARC-TCA | E20: AFS | G20: AFS | H20: Inspector | I20: Johan Stols | J20: 0823321905 | K20: Submitted | L20: 65
A21: lorrainem@wearcheck.co.za | B21: Lorraine Lerato Mokgethi | C21: WC495 | D21: ARC-NDT | E21: AFS | G21: AFS | H21: Technician | I21: Adri Ludick | J21: 786 672 158 | K21: Submitted | L21: 68
A22: mervyng@wearcheck.co.za | B22: Mervyn Thomas Gibbons | C22: WC536 | D22: ARC-TCA | E22: AFS | G22: AFS | H22: ARC TC Machinery Inspector | I22: Johan Stols | J22: 0674193633 | K22: Submitted | L22: 80
A23: mikes@weacheckrs.com | B23: Mike Mbongeni Shongwe | C23: WC483 | D23: ARC-NDT | E23: AFS | G23: AFS | H23: Senior Inspector | I23: Adri Ludick | J23: 0718507077 | K23: Submitted | L23: 78
A24: nico.duplessis@wearcheckrs.com | B24: Nicolaas du Plessis | C24: WC506 | D24: ARC-RCA | E24: AFS | G24: AFS | H24: RCA Inspector | I24: Roger Henwood | J24: 0718937378 | K24: Submitted | L24: 87
A25: Landus@wearcheckrs.com | B25: Norman Landus Walters | C25: WC509 | D25: ARC-TCA | E25: AFS | G25: AFS | H25: Machinery Inspector | I25: Johan Stols | J25: 076 385 2151 | K25: Submitted | L25: 91
A26: patrick@wearcheckrs.com | B26: Patrick Nel | C26: WC498 | D26: ARC-NDT | E26: AFS | G26: AFS | H26: Machinery Inspector | I26: Adri Ludick | J26: 0723633245 | K26: Submitted | L26: 93
B27: Richard van Vuuren | C27: WC507 | E27: AFS | G27: AFS | I27: Adri Ludick | L27: 103
A28: rogerh@wearcheckrs.com | B28: Roger Henwood | C28: WC504 | D28: ARC-RCA | E28: AFS | G28: AFS | H28: RCA Operations Manager | I28: Philip Schutte | J28: 0834465155 | K28: Submitted | L28: 104
A29: rynhardt.smit@wearcheckrs.com | B29: Rynhardt Smit | C29: WC501 | D29: ARC-RCA | E29: AFS | G29: AFS | H29: RCA Inspector | I29: Roger Henwood | J29: 0833081601 | K29: Submitted | L29: 108
A30: simondifutso@WearCheckRS.com | B30: Simon Petrus Difutso | C30: WC485 | D30: ARC-NDT | E30: AFS | G30: AFS | H30: AMM Junior Management | I30: Adri Ludick | J30: 0838541915 | K30: Submitted | L30: 113
A31: teresa.venter@wearcheckRS.com | B31: Teresa Venter | C31: WC487 | D31: AFS | E31: AFS | G31: AFS | H31: Administration Assistant | I31: Adri Ludick | J31: 0662916929 | K31: Submitted | L31: 116
A32: Riaandp@wearcheckRS.com | B32: Adriaan Johannes du Plooy | C32: WC591 | D32: ARC-RCM | E32: WearCheck | F32: Mozambique | G32: Mozambique | H32: Country Manager | I32: Jaco Willer | J32: 0835965562 | K32: Submitted | L32: 101
A33: armindo@wearcheckrs.com | B33: Armindo Muchacho | C33: Unknown | D33: ARC-RCM | E33: WearCheck | F33: Mozambique | G33: Mozambique | H33: Site Supervisor | I33: Riaan du Plooy | J33: 258848349643 | K33: Submitted | L33: 12
A34: N/A | B34: Benedito Timana | C34: Unknown | D34: ARC-RCM | E34: WearCheck | F34: Mozambique | G34: Mozambique | H34: Oil Sampler / Data collector | I34: Riaan du Plooy | J34: 258 879321970 | K34: Submitted | L34: 15
A35: davidl@wearcheckrs.com | B35: David Lipague | C35: Unknown | D35: ARC-RCM | E35: WearCheck | F35: Mozambique | G35: Mozambique | H35: Reliability Technician | I35: Riaan du Plooy | J35: 258847817888 | K35: Submitted | L35: 25
A36: isac@wearcheckrs.com | B36: Isac Zacarias | C36: Unknown | D36: ARC-RCM | E36: WearCheck | F36: Mozambique | G36: Mozambique | H36: Reliability Technician | I36: Riaan du Plooy | J36: 258849439848 | K36: Submitted | L36: 49
A37: Muhamad@wearcheckRS.com | B37: Muhamad Hanif | C37: Unknown | D37: ARC-RCM | E37: WearCheck | F37: Mozambique | G37: Mozambique | H37: Reliability Technician | I37: Riaan du Plooy | J37: 258878054903 | K37: Submitted | L37: 88
A38: N/A | B38: Peter Ivo Mateus Mahlangu | D38: ARC-RCM | E38: WearCheck | F38: Mozambique | G38: Mozambique | H38: Senior Technician | I38: Riaan du Plooy | J38: 258842628215 | K38: Submitted | L38: 97
A39: Placido@wearcheckrs.com | B39: Placido Maculuve | C39: Unknown | D39: ARC-RCM | E39: WearCheck | F39: Mozambique | G39: Mozambique | H39: Senior Technician | I39: Riaan du Plooy | J39: 258845070300 | K39: Submitted | L39: 99
A40: dian@wearcheckrs.com | B40: Dian Leff | C40: WCN008 | D40: ARC-RCM | E40: WearCheck | F40: Namibia | G40: Namibia | H40: Reliability Technician | I40: Rohan Willer | J40: 0817614612 | K40: Submitted | L40: 28
A41: Freddy-Ben@wearcheckRS.com | B41: Freddy-Ben Gariseb | C41: WCN004 | D41: ARC-RCM | E41: WearCheck | F41: Namibia | G41: Namibia | H41: Reliability Technician | I41: Rohan Willer | J41: 264813707010 | K41: Submitted | L41: 40
A42: gabriel@wearcheckrs.com | B42: Gabriel Shikongo Nuunyango | C42: WCN007 | D42: ARC-RCM | E42: WearCheck | F42: Namibia | G42: Namibia | H42: Reliability Technician | I42: Rohan Willer | J42: +264 81 364 5524 | K42: Submitted | L42: 41
A43: rohan@wearcheckrs.com | B43: Hermanus Johannes Willer | C43: WC381 | D43: ARC-RCM | E43: WearCheck | F43: Namibia | G43: Namibia | H43: Site Manager | I43: Jaco Willer | J43: 0812165890 | K43: Submitted | L43: 106
A44: a.ludick@wearcheckRS.com | B44: Adri Ludick | C44: WC492 | D44: ARC-NDT | E44: GP Consult | G44: RS | H44: Manager Mechanical | I44: Philip Schutte | J44: 0832816896 | K44: Submitted | L44: 2
A45: adriaanb@wearcheckrs.com | B45: Adriaan Pertus Johannes Bouwer | C45: WC383 | D45: ARC-RCM | E45: WearCheck | F45: KwaZulu Natal | G45: RS | H45: Thermal Manager | I45: Louis Peacock | J45: 0608498504 | K45: Submitted | L45: 3
A46: marshallr@wearcheckrs.com | B46: Ailwel Marshall Rasimphi | C46: WEC094 | D46: ARC-RCM | E46: GP Consult | F46: Valterra - Waterval | G46: RS | H46: Reliability Technician | I46: Riaan de Beer | J46: 0768219444 | K46: Submitted | L46: 4
A47: alex@wearcheckrs.com | B47: Alexander Outram | C47: WEC105 | D47: ARC-RCM | E47: GP Consult | F47: RBMR and PMR | G47: RS | H47: Reliability Technologist | I47: Micheal Pretorius | J47: 0662213616 / 0720164289 | K47: Submitted | L47: 5
A48: allan@wearcheckrs.com | B48: Allan Stuurman | C48: WEC123 | D48: ARC-RCM | E48: GP Consult | F48: Samancor - ECM Tweefontein | G48: RS | H48: Reliability Technologist - Site Suprevisor | I48: Peet Peacock | J48: 0799121301 | K48: Submitted | L48: 6
A49: andrew@wearcheckRS.com | B49: Andrew John Walker Robb | C49: WEC103 | D49: ARC-RCM | E49: GP Consult | F49: Remote Centre | G49: RS | H49: ARC Centre Manager | I49: Louis Peacock | J49: 0636504444 | K49: Submitted | L49: 8
A50: annahm@wearcheckrs.com | B50: Annah Seipone Modutwane | C50: WC484 | D50: ARC-RCM | E50: WearCheck | F50: Valterra - Mototolo | G50: RS | H50: Trainee Inspector B5 | I50: Londolani Managa | J50: 0833579812 | K50: Submitted | L50: 9
A51: annemie@wearcheckrs.com | B51: Annemie Willer | C51: WC319 | D51: ARC-RCM | E51: WearCheck | F51: Longmeadow H/O | G51: RS | H51: Divisional Manager | I51: Philip Schutte | J51: 0716096197 | K51: Incomplete | L51: 10
A52: aubrey@wearcheckRS.com | B52: Aubrey Tshabalala | C52: WEC114 | D52: ARC-RCM | E52: GP Consult | F52: Valterra - Mototolo | G52: RS | H52: Reliability Technologist | I52: Annah Modutwane | J52: 0824871527 | K52: Submitted | L52: 14
A53: lopim@wearcheck.co.za | B53: Bernard Lopi Molangoane | C53: WC269 | D53: ARC-RCM | E53: WearCheck | F53: Valterra - Mototolo | G53: RS | H53: Sampler | I53: Annah Modutwane | J53: 0636888886 | K53: Submitted | L53: 70
A54: Bianka@WearCheckRS.com | B54: Bianka de Beer | C54: WEC142 | D54: ARC-RCM | E54: GP Consult | F54: Longmeadow H/O | G54: RS | H54: Administrator | I54: Megan Salzwedel | J54: 0740317981 | K54: Submitted | L54: 16
A55: cj@wearcheckrs.com | B55: CJ Woller | C55: WEC120 | D55: ARC-RCM | E55: GP Consult | F55: RBMR and PMR | G55: RS | H55: Reliability Technician | I55: Michael Preotrius | J55: 0835965562 | K55: Submitted | L55: 20
A56: chicco@wearcheckrs.com | B56: Chicco Fransisco Tivane | C56: WC380 | D56: ARC-RCM | E56: WearCheck | F56: Steelpoort | G56: RS | H56: Reliability Technologist | I56: Londolani Managa | J56: 0818190051 | K56: Submitted | L56: 17
... A67: francoisve@wearcheckrs.com | B67: Francois Jacobus van Eeden | C67: WC287 | D67: ARC-RCM | E67: WearCheck | F67: Remote Centre | G67: RS | H67: Condition Monitoring Specialist | I67: Andrew Robb | J67: 0828023072 | K67: Submitted | L67: 38
A68: heinrich@wearcheckrs.com | B68: Fritz Kusel | C68: WEC134 | D68: ARC-RCA | E68: GP Consult | G68: RS | H68: RCA Technician | I68: Roger Henwood | J68: 0796959474 | K68: Submitted | L68: 47
A69: freddieh@wearcheck.co.za | B69: Gordon John Frederick Hoy | C69: WEC093 | D69: AFS | E69: GP Consult | G69: RS | H69: Mechanical Technician | I69: Adri Ludick | J69: 0825967126 | K69: Submitted | L69: 43
A70: gustav@wearcheckrs.com | B70: Gustav Lourens | C70: WC270 | D70: ARC-RCM | E70: WearCheck | F70: Springs | G70: RS | H70: Reliability Technologist | I70: Eddie Pieterse Snr | J70: 0829057631 | K70: Submitted | L70: 44
A71: hannest@wearcheckrs.com | B71: Hannest Koegelenberg | C71: WEC047 | D71: ARC-RCM | E71: GP Consult | F71: Springs | G71: RS | H71: Reliability Technologist | I71: Eddie Pieterse Snr | J71: 0823832542 | K71: Submitted | L71: 45
A72: heinc@wearcheckrs.com | B72: Hein Coetzer | C72: WEC129 | D72: ARC-RCM | E72: GP Consult | F72: Samancor - TAS | G72: RS | H72: Precision Maintenance Technologist | I72: Peet Peacock | J72: 0828887419 | K72: Submitted | L72: 46
A73: henry@wearcheckrs.com | B73: Henry Mherekumombe | C73: WEC098 | D73: ARC-NDT | E73: GP Consult | G73: RS | H73: Level 2 Inspector | I73: Adri Ludick | J73: 0664844117 | K73: Submitted | L73: 48
A74: jaco@wearcheckrs.com | B74: Jacobus Johannes Willer | C74: WC352 | D74: ARC-RCM | E74: WearCheck | F74: Longmeadow H/O | G74: RS | H74: Foreign Operations Business Unit Manager | I74: Philip Schutte | J74: 0762681425 | K74: Submitted | L74: 51
A75: james@WearCheckRS.com | B75: James Papayito Tshabalala | C75: WC236 | D75: ARC-RCM | E75: WearCheck | F75: Valterra - Mototolo | G75: RS | H75: Reliability Technologist | I75: Annah Modutwane | J75: 0662479987 | K75: Submitted | L75: 53
A76: jj@wearcheckrs.com | B76: Jean Jacques de Beer | C76: WEC137 | D76: ARC-RCM | E76: GP Consult | F76: Remote Centre | G76: RS | H76: Technical Advisor | I76: Andrew Robb | J76: 0676700396 | K76: Submitted | L76: 56
A77: johandre@wearcheckrs.com | B77: Johannes Andréas Oosthuizen | C77: WEC089 | D77: ARC-RCM | E77: GP Consult | F77: Samancor - Mooinooi | G77: RS | H77: Reliability Technician | J77: 0834373969 | K77: Submitted | L77: 61
A78: francoisp@wearcheckrs.com | B78: Jozua Francois Joubert Pienaar | C78: WEC111 | D78: ARC-RCM | E78: GP Consult | F78: KwaZulu Natal - Hillside | G78: RS | H78: Reliability Analyst | I78: Peet Peacock | J78: 0785618579 | K78: Submitted | L78: 39
A79: permission@wearcheckrs.com | B79: Katishi Permission Malele | C79: WC393 | D79: ARC-RCM | E79: WearCheck | F79: Valterra - Mototolo | G79: RS | H79: Sampler | I79: Annah Modutwane | J79: 606314865 | K79: Submitted | L79: 96
A80: kevin@wearcheckrs.com | B80: Kevin Henwood | C80: WEC135 | D80: ARC-RCA | E80: GP Consult | G80: RS | H80: RCA Technician | I80: Roger Henwood | J80: 0829072077 | K80: Submitted | L80: 64
A81: lubby@wearcheckrs.com | B81: Labby Jeffrey Lubis | C81: WEC118 | D81: ARC-RCM | E81: GP Consult | F81: Samancor - Doornbosch | G81: RS | H81: Reliability Technologist - Site Suprevisor | I81: Peet Peacock | J81: 0796915943 | K81: Submitted | L81: 72
A82: Leon@wearcheckrs.com | B82: Leon Coetzee | C82: WC455 | D82: ARC-RCM | E82: WearCheck | F82: Steelpoort | G82: RS | H82: Reliability Technologist | I82: Londolani Managa | J82: 0832881463 | K82: Submitted | L82: 66
A83: Lesego@WearCheckRS.com | B83: Lesego Khuthwane | C83: WEC126 | D83: ARC-RCM | E83: GP Consult | F83: Longmeadow H/O | G83: RS | H83: Remote Centre Administrator | I83: Andrew Robb | J83: 0849892260 | K83: Submitted | L83: 67
A84: lloyd@wearcheckrs.com | B84: Lloyd Ngobeni | C84: WEC099 | D84: ARC-NDT | E84: GP Consult | F84: Valterra - Waterval | G84: RS | H84: Precision Maintenance Technologist | I84: Riaan de Beer | J84: 0664844084 | K84: Submitted | L84: 89
A85: londolanim@wearcheckrs.com | B85: Londolani Managa | C85: WC648 | D85: ARC-RCM | E85: WearCheck | F85: Samancor - MFC | G85: RS | H85: Precision Maintenance Technologist | I85: Peet Peacock | J85: 0711682839 | K85: Submitted | L85: 69
A86: louis@wearcheckrs.com | B86: Louis Robert Peacock | C86: WC277 | D86: ARC-RCM | E86: WearCheck | F86: Longmeadow H/O | G86: RS | H86: Technical & Training Manager | I86: Annemie Willer | K86: Incomplete | L86: 71
A87: lucas@wearcheckrs.com | B87: Lucas Johannes Bartel Luus | C87: WEC068 | D87: ARC-RCM | E87: GP Consult | F87: Kathu | G87: RS | H87: Reliability Technician | I87: Andrew Robb | J87: 0763455962 | K87: Submitted | L87: 73
A88: mande@wearcheckrs.com | B88: Mandé Coetzee | C88: WEC116 | D88: ARC-RCM | E88: GP Consult | F88: Longmeadow H/O | G88: RS | H88: RS Administrator | I88: Shivon Alberts | J88: 079 128 9133 | K88: Submitted | L88: 74
A89: marcel@wearcheckrs.com | B89: Marcel Schoeman | C89: WEC102 | D89: ARC-RCM | E89: GP Consult | F89: Roamer | G89: RS | H89: Sales Manager | I89: Annemie Willer | J89: 0767946353 | K89: Submitted | L89: 75
A90: mariette@wearcheckrs.com | B90: Mariette du Rand | C90: WEC109 | D90: ARC-RCM | E90: GP Consult | F90: Longmeadow H/O | G90: RS | H90: RS Administrator | I90: Megan Salzwedel | J90: 0837835814 | K90: Submitted | L90: 76
A91: martiens@wearcheckrs.com | B91: Marthinus Jacobus van Aarde | C91: WEC106 | D91: ARC-RCM | E91: GP Consult | F91: Eskom - Matimba | G91: RS | H91: Reliability Technician | I91: Tsietsi Monnanyne | J91: 0834550909 | K91: Submitted | L91: 77
A92: megan@wearcheckrs.com | B92: Megan Salzwedel | C92: WEC104 | D92: ARC-RCM | E92: GP Consult | F92: Longmeadow H/O | G92: RS | H92: Administration Manager | I92: Edward Pieterse Jnr | J92: 0720591125 | K92: Submitted | L92: 79
A93: meshack@wearcheckrs.com | B93: Meshack Welcome Nxumalo | C93: WEC088 | D93: ARC-RCM | E93: GP Consult | F93: KwaZulu Natal | G93: RS | H93: Reliability Technologist | I93: Francois Pienaar | J93: 0638165404 | K93: Submitted | L93: 81
A94: Franciosp@wearcheckRS.com | B94: Michael Francios Pretorius | C94: WEC080 | D94: ARC-RCM | E94: GP Consult | F94: Neopak - Rosslyn | G94: RS | H94: Reliability Analyst | I94: Peet Peacock | J94: 0832773047 | K94: Submitted | L94: 37
A95: micheal@wearcheckrs.com | B95: Micheal Francios Pretorius | C95: WEC076 | D95: ARC-RCM | E95: GP Consult | F95: RBMR and PMR | G95: RS | H95: Reliability Analyst - Site Supervisor | I95: Peet Peacock | J95: 0828864900 | K95: Submitted | L95: 82
A96: betty@wearcheckrs.com | B96: Mmatapa Betty Monyepao | C96: WC465 | D96: ARC-RCM | E96: WearCheck | F96: Valterra - Mototolo | G96: RS | H96: Reliability Technician | I96: Annah Modutwane | J96: 0768125164 | K96: Submitted | L96: 84
A97: simon@wearcheckrs.com | B97: Mokale Simon Mosima | C97: WC283 | D97: ARC-RCM | E97: WearCheck | F97: Eskom - Matimba | G97: RS | H97: Reliability Technician | I97: Tsietsi Monnanyne | J97: 0784570962 | K97: Submitted | L97: 112
A98: mornea@wearcheckrs.com | B98: Mórne Alberts | C98: WC361 | D98: ARC-RCM | E98: WearCheck | F98: Remote Centre | G98: RS | H98: ARC Reliability Specialist | I98: Andrew Robb | J98: 0810132168 | K98: Submitted | L98: 85
... A101: percy@wearcheckrs.com | B101: Percy Hall | C101: WEC115 | D101: ARC-RCM | E101: GP Consult | F101: Seriti - Khutala | G101: RS | H101: Reliability Technologist | I101: Londolani Managa | J101: 0826828862 / 0827307344 | K101: Submitted | L101: 95
A102: Peet@wearcheckrs.com | B102: Petrus Johannes Peacock | C102: WC520 | D102: ARC-RCM | E102: WearCheck | G102: RS | H102: Service Manager | I102: Annemie Willer | J102: 0716700710 | K102: Submitted | L102: 94
A103: philip@wearcheckrs.com | B103: Philippus Jacobus Wilhelmus (Philip) Schutte | C103: WC253 | D103: ARC-RCM | E103: WearCheck | F103: Longmeadow H/O | G103: RS | H103: General Manager | I103: N/A | J103: 0769829774 | K103: Incomplete | L103: 98
A104: passwell@wearcheckrs.com | B104: Putaneng Paswell Mashoeu | C104: WC348 | D104: ARC-RCM | E104: WearCheck | F104: Valterra - Mototolo | G104: RS | H104: Sampler | I104: Annah Modutwane | J104: 06364888867 | K104: Submitted | L104: 92
A105: rakcal@wearcheckrs.com | B105: Rakcal Monroe Balaram | C105: WEC074 | D105: ARC-RCM | E105: GP Consult | F105: KwaZulu Natal - Tronox | G105: RS | H105: Reliability Technologist | I105: Francois Pienaar | J105: 0749705467 | K105: Submitted | L105: 105
A106: reinierk@wearcheckrs.com | B106: Reinier Kalp | C106: WC382 | D106: ARC-RCM | E106: WearCheck | F106: Remote Centre | G106: RS | H106: Remote Center Analyst | I106: Andrew Robb | J106: 0810132176 | K106: Submitted | L106: 100
A107: riaandb@wearcheckrs.com | B107: Riaan de Beer | C107: WC363 | D107: ARC-RCM | E107: WearCheck | F107: Valterra - Waterval | G107: RS | H107: Supervisor | I107: Peet Peacock | J107: 0745880347 | K107: Submitted | L107: 102
A108: rynhardt@wearcheckrs.com | B108: Rynhardt Meyer | C108: WEC096 | D108: ARC-NDT | E108: GP Consult | F108: Valterra - Waterval | G108: RS | H108: Precision Maintenance Technologist | I108: Riaan de Beer | J108: 0649557747 | K108: Submitted | L108: 107
A109: michealm@wearcheckrs.com | B109: Seporo Micheal Masemola | C109: WC291 | D109: ARC-RCM | E109: WearCheck | F109: Valterra - Mototolo | G109: RS | H109: Reliability Technologist | I109: Annah Modutwane | J109: 0820828925 | K109: Submitted | L109: 83
A110: sergent@wearcheckrs.com | B110: Sergant Sakhile Tlou | C110: WC264 | D110: ARC-RCM | E110: Wearcheck | F110: Roamer | G110: RS | H110: Reliability Technologist | I110: Eben Prinsloo | J110: 0828827758 | K110: Submitted | L110: 109
A111: shaun@wearcheckrs.com | B111: Shaun Janse van Rensburg | C111: WEC136 | D111: ARC-TCA | E111: GP Consult | G111: RS | H111: Machinery Inspector | I111: Johan Stols | J111: 082 497 1146 | K111: Submitted | L111: 110
A112: shivon@wearcheckrs.com | B112: Shivon Chantelle Alberts | C112: WEC130 | D112: ARC-RCM | E112: GP Consult | F112: Longmeadow H/O | G112: RS | H112: Financial Manager | I112: Megan Salzwedel | J112: 0793152710 | K112: Submitted | L112: 111
...

Sheet License_Raw
A1: Display Name | B1: User Principal Name | C1: Licenses
A2: Admin | B2: admin@WearCheckRS.com | C2: Microsoft Defender for Office 365 (Plan 2)+Microsoft Fabric (Free)+Microsoft 365 E3
A3: Adri Ludick | B3: A.Ludick@WearCheckRS.com | C3: Microsoft 365 Business Premium+Microsoft Copilot Studio Viral Trial+Microsoft Defender for Office 365 (Plan 2)+Microsoft Power Automate Free
A4: Adri Ludick Old | B4: Adri.ludick@WearCheckRS.com | C4: Microsoft Defender for Office 365 (Plan 2)+Microsoft Power Automate Free+Microsoft 365 Business Standard
A5: Adriaan Bouwer | B5: adriaanb@WearCheckRS.com | C5: Microsoft Defender for Office 365 (Plan 2)+Microsoft Power Automate Free+Microsoft 365 Business Standard+Microsoft Fabric (Free)
A6: AFS Application | B6: afs_app@WearCheckRS.com | C6: Microsoft Power Automate Free+Exchange Online (Plan 1)
A7: Alex Outram | B7: Alex@WearCheckRS.com | C7: Microsoft Defender for Office 365 (Plan 2)+Microsoft Power Automate Free+Microsoft Fabric (Free)+Microsoft 365 Business Standard
A8: Allan Stuurman | B8: Allan@WearCheckRS.com | C8: Microsoft Defender for Office 365 (Plan 2)+Microsoft 365 Business Standard
A9: Andrew Robb | B9: Andrew@wearcheckrs.com | C9: Microsoft 365 Business Premium+Microsoft Defender for Office 365 (Plan 2)+Microsoft Fabric (Free)
A10: Annah Modutwane | B10: annahm@WearCheckRS.com | C10: Microsoft Defender for Office 365 (Plan 2)+Microsoft Power Automate Free+Microsoft Fabric (Free)+Microsoft 365 Business Standard
A11: Annemie Willer | B11: annemie@WearCheckRS.com | C11: Microsoft Defender for Office 365 (Plan 2)+Power BI Premium Per User+Microsoft Copilot Studio Viral Trial+Microsoft Power Apps Plan 2 Trial+Microsoft 365 E3+Microsoft Fabric (Free)+Microsoft Power Automate Free
A12: Antonio Ehrke | B12: Antonio.Ehrke@WearCheckRS.com | C12: Microsoft Defender for Office 365 (Plan 2)+Microsoft 365 Business Standard
... A148: Wihan Willer | B148: Wihan@WearCheckRS.com | C148: Microsoft Defender for Office 365 (Plan 2)+Microsoft 365 Business Standard
